Workbook
Name Commercial: User_Inputs!$L$20:$L$28
Name Factory: User_Inputs!$L$31:$L$38
Name Home: User_Inputs!$L$4:$L$10
Name Hospital: User_Inputs!$L$41:$L$45
Name Hotel: User_Inputs!$L$13:$L$17
Name School: User_Inputs!$L$48:$L$53

Sheet Overview
A1: Solarvy Energy Platform Calculation Engine - Master Workbook
A3: Purpose
A4: How to use | B4: Inputs in blue tab
A5: Input routes
A6: Objectives
A7: Primary output | B7: Outputs in green tab

Sheet User_Inputs
A1: User Inputs
A3: Assessment Identity | I3: State | J3: City | L3: Home_Templates | N3: Home_Templates | Q3: Category | R3: Templates
A4: Assessment_ID | B4: SV-0001 | I4: Abia | J4: Abuja | L4: Studio / Self-contained | N4: Studio / Self-contained - Essential | P4: 1 | Q4: Home | R4: Studio / Self-contained - Essential
A5: Scenario_Name | B5: Base Case | I5: Adamawa | J5: Lagos | L5: 1-Bedroom Flat | N5: Studio / Self-contained - Standard | P5: 2 | Q5: Home | R5: Studio / Self-contained - Standard
A6: Currency_Symbol | B6: ₦ | I6: Akwa Ibom | J6: Kano | L6: 2-Bedroom Flat | N6: 1-Bedroom Flat - Essential | P6: 3 | Q6: Home | R6: 1-Bedroom Flat - Essential
A7: Country | B7: Nigeria | I7: Anambra | J7: Ibadan | L7: 3-Bedroom House | N7: 1-Bedroom Flat - Standard | P7: 4 | Q7: Home | R7: 1-Bedroom Flat - Standard
A8: State | B8: Lagos | I8: Bauchi | J8: Port Harcourt | L8: 4-Bedroom Duplex | N8: 1-Bedroom Flat - Comfort | P8: 5 | Q8: Home | R8: 1-Bedroom Flat - Comfort
A9: City | I9: Bayelsa | J9: Benin City | L9: 5-Bedroom Duplex / Large Home | N9: 2-Bedroom Flat - Essential | P9: 6 | Q9: Home | R9: 2-Bedroom Flat - Essential
A10: Building Information | B10: Home | C10: Property_Type | I10: Benue | J10: Kaduna | L10: Mini Estate / Shared Services | N10: 2-Bedroom Flat - Standard | P10: 7 | Q10: Home | R10: 2-Bedroom Flat - Standard
A11: Template | B11: 2-Bedroom Flat | C11: =B11 -> 2-Bedroom Flat | D11: =IF(C11="Studio / Self-contained",1, IF(C11="1-Bedroom Flat",2, IF(C11="2-Bedroom Flat",3, IF(C11="3-Bedroom House",4, IF(C11="4-Bedroom Duplex",5, IF(C11="5-Bedroom Duplex / Large Home",6, IF(C11="Mini Estate / Shared Services",7,IF(C11="Short-let Apartment - Standard",8, IF(C11="Guest House - 6 Rooms",9, IF(C11="Small Hotel - 12 Rooms Partial Backup",10, IF(C11="Medium Hotel - 25 Rooms Critical Loads",11, IF(C11="Lounge / Bar",12,IF(C11="Small Shop / Retail Kiosk",13, IF(C11="Pharmacy",14, IF(C11="Supermarket / Grocery",15, IF(C11="Salon / Barbershop",16, IF(C11="Small Office",17, IF(C11="Restaurant / Cafe",18, IF(C11="Bakery",19, IF(C11="Fuel Station Retail / Office",20,IF(C11="Bank / ATM Lobby",21, IF(C11="Warehouse",22, IF(C11="Cold Room / Frozen Storage",23, IF(C11="Light Factory / Small Production",24, IF(C11="Welding Workshop",25, IF(C11="Poultry Farm",26, IF(C11="Irrigation Pumping",27, IF(C11="Agro-Processing / Milling",28,IF(C11="Printing / Small Manufacturing",29, IF(C11="Small Clinic",30, IF(C11="Diagnostic Lab",31, IF(C11="Maternity Clinic",32, IF(C11="Small Hospital - Critical Loads",33, IF(C11="Dental Clinic",34, IF(C11="Nursery / Primary School",35, IF(C11="Secondary School",36, IF(C11="Computer Lab / Training Centre",37, IF(C11="Training Centre / Office",38, IF(C11="Church / Mosque / Event Hall",39,IF(C11="Boarding School Common Services",40)))))))))))))))))))))))))))))))))))))))) -> 3 | I11: Borno | J11: Maiduguri | N11: 2-Bedroom Flat - Comfort | P11: 8 | Q11: Home | R11: 2-Bedroom Flat - Comfort
A12: Usage Profile | B12: Standard | I12: Cross River | J12: Zaria | L12: Hotel_Templates | N12: 3-Bedroom Flat - Standard | P12: 9 | Q12: Home | R12: 3-Bedroom Flat - Standard
A13: Current Power Setup | B13: Grid + Generator | C13: Power_Setup | I13: Delta | J13: Aba | L13: Short-let Apartment - Standard | N13: 3-Bedroom House - Standard | P13: 10 | Q13: Home | R13: 3-Bedroom House - Standard
A14: Main Objective | B14: Reduce Diesel Use | C14: Objective_Mode | I14: Ebonyi | J14: Onitsha | L14: Guest House - 6 Rooms | N14: 3-Bedroom House - Comfort | P14: 11 | Q14: Home | R14: 3-Bedroom House - Comfort
A15: Choose Input Method | B15: Appliances | C15: Input_Method | I15: Edo | J15: Owerri | L15: Small Hotel - 12 Rooms Partial Backup | N15: 4-Bedroom Duplex - Essential | P15: 12 | Q15: Home | R15: 4-Bedroom Duplex - Essential
I16: Ekiti | J16: Enugu | L16: Medium Hotel - 25 Rooms Critical Loads | N16: 4-Bedroom Duplex - Standard | P16: 13 | Q16: Home | R16: 4-Bedroom Duplex - Standard
A17: Site and Usage Inputs | I17: Enugu | J17: Abeokuta | L17: Lounge / Bar | N17: 4-Bedroom Duplex - Comfort | P17: 14 | Q17: Home | R17: 4-Bedroom Duplex - Comfort
A18: Monthly_Usage_kWh | B18: 0 | I18: Gombe | J18: Jos | N18: 5-Bedroom Duplex / Large Home - Standard | P18: 15 | Q18: Home | R18: 5-Bedroom Duplex / Large Home - Standard
A19: Peak_Load_kW | B19: 0 | I19: Imo | J19: Warri | L19: Commercial Building_Templates | N19: 5-Bedroom Duplex / Large Home - Premium | P19: 16 | Q19: Home | R19: 5-Bedroom Duplex / Large Home - Premium
A20: Outage Hours per Day | B20: 6 | C20: Outage_Hours_per_Day | I20: Jigawa | J20: Sokoto | L20: Small Shop / Retail Kiosk | N20: Mini Estate / Shared Services | P20: 17 | Q20: Home | R20: Mini Estate / Shared Services
A21: Roof Area | B21: 200 | C21: Roof_Area_m2 | I21: Kaduna | J21: Ilorin | L21: Pharmacy | P21: 18 | Q21: Hotel | R21: Short-let Apartment - Standard
A22: Roof_Usability_Factor | B22: 0.6 | I22: Kano | J22: Oyo | L22: Supermarket / Grocery | N22: Hotel_Templates | P22: 19 | Q22: Hotel | R22: Guest House - 6 Rooms
A23: Daytime_Load_Share | B23: 0.15 | I23: Katsina | J23: Uyo | L23: Salon / Barbershop | N23: Short-let Apartment - Standard | P23: 20 | Q23: Hotel | R23: Small Hotel - 12 Rooms Partial Backup
A24: Critical_Load_Percent | B24: 0.6 | I24: Kebbi | J24: Calabar | L24: Small Office | N24: Guest House - 6 Rooms | P24: 21 | Q24: Hotel | R24: Medium Hotel - 25 Rooms Critical Loads
A25: Backup Duration Required | B25: 4 | C25: Backup_Hours_Target | I25: Kogi | J25: Osogbo | L25: Restaurant / Cafe | N25: Small Hotel - 12 Rooms Partial Backup | P25: 22 | Q25: Hotel | R25: Lounge / Bar
A26: Target_Solar_Share | B26: 0.9 | I26: Kwara | J26: Akure | L26: Bakery | N26: Medium Hotel - 25 Rooms Critical Loads | P26: 23 | Q26: Commercial | R26: Small Shop / Retail Kiosk
A27: Battery_DoD | B27: 0.2 | I27: Lagos | J27: Katsina | L27: Fuel Station Retail / Office | N27: Lounge / Bar | P27: 24 | Q27: Commercial | R27: Pharmacy
I28: Nasarawa | J28: Minna | L28: Bank / ATM Lobby | P28: 25 | Q28: Commercial | R28: Supermarket / Grocery
A29: Commercial Inputs | I29: Niger | J29: Makurdi | N29: Commercial Building_Templates | P29: 26 | Q29: Commercial | R29: Salon / Barbershop
A30: Grid_Tariff_per_kWh | B30: 209.5 | E30: Band A = N209.50/kWh | I30: Ogun | J30: Bauchi | L30: Factory_Templates | N30: Small Shop / Retail Kiosk | P30: 27 | Q30: Commercial | R30: Small Office
A31: Diesel_Price_per_Litre | B31: 1200 | E31: Band B = N63.00/kWh | I31: Ondo | J31: Gombe | L31: Warehouse | N31: Pharmacy | P31: 28 | Q31: Commercial | R31: Restaurant / Cafe
A32: Generator_kWh_per_Litre | B32: 3.5 | E32: Band C = N50.00/kWh | I32: Osun | J32: Yola | L32: Cold Room / Frozen Storage | N32: Supermarket / Grocery | P32: 29 | Q32: Commercial | R32: Bakery
A33: PV_Capex_per_kWp | B33: =IF($B$10="Home", 300000,IF($B$10="Office",420000,IF($B$10="Factory",320000,550000))) -> 300000 | E33: Band D = N43.00/kWh | I33: Oyo | J33: Jalingo | L33: Light Factory / Small Production | N33: Salon / Barbershop | P33: 30 | Q33: Commercial | R33: Fuel Station Retail / Office
A34: Battery_Capex_per_kWh | B34: =IF($B$10="Home",260000,IF($B$10="Office",350000,IF($B$10="Factory",300000,420000))) -> 260000 | E34: Band E = N40.00/kWh | I34: Plateau | J34: Damaturu | L34: Welding Workshop | N34: Small Office | P34: 31 | Q34: Commercial | R34: Bank / ATM Lobby
A35: Inverter_Capex_per_kW | B35: =IF($B$10="Home",230000,IF($B$10="Office",300000,IF($B$10="Factory",220000,380000))) -> 230000 | I35: Rivers | J35: Dutse | L35: Poultry Farm | N35: Restaurant / Cafe | P35: 32 | Q35: Factory | R35: Warehouse
A36: BOS_Factor | B36: =IF($B$10="Home",0.12,IF($B$10="Office",0.15,IF($B$10="Factory",0.12,0.2))) -> 0.12 | I36: Sokoto | J36: Gusau | L36: Irrigation Pumping | N36: Bakery | P36: 33 | Q36: Factory | R36: Cold Room / Frozen Storage
A37: Annual_OM_Rate | B37: 0.02 | I37: Taraba | J37: Birnin Kebbi | L37: Agro-Processing / Milling | N37: Fuel Station Retail / Office | P37: 34 | Q37: Factory | R37: Light Factory / Small Production
A38: Discount_Rate | B38: 0.15 | I38: Yobe | J38: Lokoja | L38: Printing / Small Manufacturing | N38: Bank / ATM Lobby | P38: 35 | Q38: Factory | R38: Welding Workshop
A39: System_Life_Years | B39: 15 | I39: Zamfara | J39: Asaba | P39: 36 | Q39: Factory | R39: Poultry Farm
I40: FCT Abuja | J40: Awka | L40: Hospital_Templates | N40: Factory_Templates | P40: 37 | Q40: Factory | R40: Irrigation Pumping
A41: Regional Technical Inputs / Overrides | J41: Ado-Ekiti | L41: Small Clinic | N41: Warehouse | P41: 38 | Q41: Factory | R41: Agro-Processing / Milling
A42: Solar_Yield_kWh_per_kWp_yr | B42: =IF(B7="Nigeria",1450, IF(B7="Kenya",1550, IF(B7="Ghana",1500, IF(B7="South Africa",1600, IF(B7="United Kingdom",950, 1450))))) -> 1450 | J42: Yenagoa | L42: Diagnostic Lab | N42: Cold Room / Frozen Storage | P42: 39 | Q42: Factory | R42: Printing / Small Manufacturing
A43: Self_Consumption_Factor | B43: =IF(B10="Home",0.75, IF(B10="Office",0.7, IF(B10="Factory",0.85, IF(B10="School",0.8, 0.75)))) -> 0.75 | L43: Maternity Clinic | N43: Light Factory / Small Production | P43: 40 | Q43: Hospital | R43: Small Clinic
A44: Inverter_Oversize_Factor | B44: =Assumptions!B19 -> 1 | L44: Small Hospital - Critical Loads | N44: Welding Workshop | P44: 41 | Q44: Hospital | R44: Diagnostic Lab
A45: Area_per_kWp_m2 | B45: 5.5 | L45: Dental Clinic | N45: Poultry Farm | P45: 42 | Q45: Hospital | R45: Maternity Clinic
A46: Notes | B46: Use only one main input route per scenario | N46: Irrigation Pumping | P46: 43 | Q46: Hospital | R46: Small Hospital - Critical Loads
L47: School_Templates | N47: Agro-Processing / Milling | P47: 44 | Q47: Hospital | R47: Dental Clinic
L48: Nursery / Primary School | N48: Printing / Small Manufacturing | P48: 45 | Q48: School | R48: Nursery / Primary School
A49: Capex_per_kWp_kWh_kW | B49: PV (₦/kWp) | C49: Battery (₦/kWh) | D49: Inverter (₦/kW) | E49: BOS (%) | F49: O&M (%) | L49: Secondary School | P49: 46 | Q49: School | R49: Secondary School
A50: Home | B50: ₦330,000 | C50: ₦265,000 | D50: ₦235,000 | E50: 0.13 | F50: 0.02 | L50: Computer Lab / Training Centre | N50: Hospital_Templates | P50: 47 | Q50: School | R50: Computer Lab / Training Centre
A51: School | B51: ₦280,000 | C51: ₦235,000 | D51: ₦215,000 | E51: 0.1 | F51: 0.02 | L51: Training Centre / Office | N51: Small Clinic | P51: 48 | Q51: School | R51: Training Centre / Office
A52: Commercial | B52: ₦265,000 | C52: ₦220,000 | D52: ₦205,000 | E52: 0.09 | F52: 0.025 | L52: Church / Mosque / Event Hall | N52: Diagnostic Lab | P52: 49 | Q52: School | R52: Church / Mosque / Event Hall
A53: Hotel | B53: ₦260,000 | C53: ₦240,000 | D53: ₦225,000 | E53: 0.12 | F53: 0.035 | L53: Boarding School Common Services | N53: Maternity Clinic | P53: 50 | Q53: School | R53: Boarding School Common Services
A54: Hospital | B54: ₦290,000 | C54: ₦260,000 | D54: ₦250,000 | E54: 0.15 | F54: 0.045 | N54: Small Hospital - Critical Loads
A55: Factory | B55: ₦240,000 | C55: ₦200,000 | D55: ₦175,000 | E55: 0.08 | F55: 0.025 | N55: Dental Clinic
N57: School_Templates
N58: Nursery / Primary School
A59: Grid Availability (%) | B59: 0.75 | N59: Secondary School
N60: Computer Lab / Training Centre
N61: Training Centre / Office
N62: Church / Mosque / Event Hall
N63: Boarding School Common Services

Sheet Bill_Input
A1: Bill Input
A3: User-entered bill route
A4: Field | B4: Value | C4: Unit / Notes | D4: Formula / Derivation
A5: Monthly Electricity Usage | B5: =User_Inputs!B18 -> 0 | C5: kWh/month | D5: Monthly_Usage_kWh_Direct
A6: Average Monthly Electricity Spend | B6: 556000 | C6: Currency/month | D6: This is an input | E6: Monthly_Spend
A7: Tariff_per_kWh | B7: =IF(B5>0, B6/B5, User_Inputs!B30) -> 209.5 | C7: Currency/kWh | D7: linked from User_Inputs if not overridden
A8: Billing_Days | B8: 30 | C8: days
A9: If only spend known -> Estimated_kWh | B9: =IF(B5>0,B5,IFERROR(B6/B7,0)) -> 2653.9379 | C9: kWh/month | D9: =IF(B5>0,B5,IFERROR(B6/B7,0)) -> 2653.9379
A10: Effective_Bill_Monthly_kWh | B10: =IF(B5>0,B5,IFERROR(B6/B7,0)) -> 2653.9379 | C10: kWh/month | D10: =IF(B5>0,B5,B9) -> 2653.9379
B11: =IF(B5>0,B5,B10) -> 2653.9379
A13: Estimated Monthly spend | B13: =Appliance_Input!L5*B7 -> 50625.675

Sheet Equipment Default
A1: Equipment | B1: Wattage | C1: Hours/Day | D1: Usage Pattern | E1: Duty Cycle | F1: Surge Factor | G1: Critical by Default? | H1: Notes
A2: LED bulb | B2: 10 | C2: 6 | D2: Continuous | E2: 1 | F2: 1 | G2: Yes | H2: Lighting usually continuous when switched on
A3: Fan | B3: 60 | C3: 8 | D3: Continuous | E3: 1 | F3: 1.2 | G3: Optional | H3: Ceiling/standing fan
A4: TV | B4: 100 | C4: 6 | D4: Continuous | E4: 1 | F4: 1.2 | G4: Optional | H4: Average LED TV
A5: Router | B5: 15 | C5: 24 | D5: Continuous | E5: 1 | F5: 1 | G5: Yes | H5: Internet is often critical for remote work
A6: Refrigerator | B6: 150 | C6: 24 | D6: Cycles on/off | E6: 0.4 | F6: 2 | G6: Yes | H6: Compressor duty cycle varies
A7: Deep freezer | B7: 250 | C7: 24 | D7: Cycles on/off | E7: 0.45 | F7: 2.5 | G7: Optional | H7: Higher compressor surge
A8: AC 1HP | B8: 900 | C8: 5 | D8: Cycles heavily | E8: 0.6 | F8: 3 | G8: Optional | H8: Use inverter/non-inverter distinction later
A9: AC 1.5HP | B9: 1200 | C9: 5 | D9: Cycles heavily | E9: 0.6 | F9: 3.5 | G9: Optional | H9: High impact on battery sizing
A10: Water pump | B10: 1100 | C10: 1 | D10: Short use | E10: 1 | F10: 3 | G10: Yes | H10: Large surge; use short hours
A11: Display fridge | B11: 300 | C11: 24 | D11: Cycles on/off | E11: 0.5 | F11: 2.5 | G11: Yes | H11: Commercial refrigeration
A12: Medical refrigerator | B12: 180 | C12: 24 | D12: Cycles on/off | E12: 0.45 | F12: 2 | G12: Yes | H12: Critical healthcare load
A13: Computer / POS | B13: 120 | C13: 8 | D13: Continuous | E13: 1 | F13: 1.2 | G13: Yes | H13: Commercial ICT
... A16: Compressor | B16: 3000 | C16: 4 | D16: Cycles heavily | E16: 0.6 | F16: 3 | G16: Depends | H16: High surge and duty variation

Sheet Category Menu
A1: Category | B1: Column1 | C1: Column2 | D1: Column3 | E1: Column4
A2: Home
A3: Hotel
A4: Commercial
A5: Factory
A6: Hospital
A7: School

Sheet Appliance_Library
A1: Appliance Library
A3: Solarvy Category | B3: Template Name | C3: Template Level | D3: Equipment | E3: Qty | F3: Wattage W | G3: Hours/Day | H3: Duty Cycle | I3: Critical Load? | J3: Surge Factor | K3: Daily Wh | L3: Daily kWh | M3: Running W | N3: Surge W | O3: Notes
A4: Home | B4: Studio / Self-contained - Standard | C4: Standard | D4: LED Bulbs | E4: 6 | F4: 10 | G4: 6 | H4: 1 | I4: Yes | J4: 1 | K4: =E4*F4*G4*H4 -> 360 | L4: =K4/1000 -> 0.36 | M4: =E4*F4 -> 60 | N4: =M4*J4 -> 60
A5: Home | B5: Studio / Self-contained - Standard | C5: Standard | D5: Fans | E5: 2 | F5: 60 | G5: 8 | H5: 1 | I5: Yes | J5: 1.2 | K5: =E5*F5*G5*H5 -> 960 | L5: =K5/1000 -> 0.96 | M5: =E5*F5 -> 120 | N5: =M5*J5 -> 144
A6: Home | B6: Studio / Self-contained - Standard | C6: Standard | D6: Television | E6: 1 | F6: 100 | G6: 6 | H6: 1 | I6: Optional | J6: 1.2 | K6: =E6*F6*G6*H6 -> 600 | L6: =K6/1000 -> 0.6 | M6: =E6*F6 -> 100 | N6: =M6*J6 -> 120
A7: Home | B7: Studio / Self-contained - Standard | C7: Standard | D7: Decoder | E7: 1 | F7: 25 | G7: 6 | H7: 1 | I7: Optional | J7: 1 | K7: =E7*F7*G7*H7 -> 150 | L7: =K7/1000 -> 0.15 | M7: =E7*F7 -> 25 | N7: =M7*J7 -> 25
A8: Home | B8: Studio / Self-contained - Standard | C8: Standard | D8: Refrigerator | E8: 1 | F8: 150 | G8: 24 | H8: 0.4 | I8: Yes | J8: 2 | K8: =E8*F8*G8*H8 -> 1440 | L8: =K8/1000 -> 1.44 | M8: =E8*F8 -> 150 | N8: =M8*J8 -> 300
A9: Home | B9: Studio / Self-contained - Standard | C9: Standard | D9: WiFi Router | E9: 1 | F9: 15 | G9: 24 | H9: 1 | I9: Yes | J9: 1 | K9: =E9*F9*G9*H9 -> 360 | L9: =K9/1000 -> 0.36 | M9: =E9*F9 -> 15 | N9: =M9*J9 -> 15
A10: Home | B10: Studio / Self-contained - Standard | C10: Standard | D10: Laptop | E10: 1 | F10: 65 | G10: 5 | H10: 1 | I10: Optional | J10: 1 | K10: =E10*F10*G10*H10 -> 325 | L10: =K10/1000 -> 0.325 | M10: =E10*F10 -> 65 | N10: =M10*J10 -> 65
A11: Home | B11: Studio / Self-contained - Standard | C11: Standard | D11: Phone Chargers | E11: 2 | F11: 10 | G11: 3 | H11: 1 | I11: Yes | J11: 1 | K11: =E11*F11*G11*H11 -> 60 | L11: =K11/1000 -> 0.06 | M11: =E11*F11 -> 20 | N11: =M11*J11 -> 20
A12: Home | B12: Studio / Self-contained - Standard | C12: Standard | D12: Microwave | E12: 1 | F12: 1200 | G12: 0.15 | H12: 1 | I12: No | J12: 1 | K12: =E12*F12*G12*H12 -> 180 | L12: =K12/1000 -> 0.18 | M12: =E12*F12 -> 1200 | N12: =M12*J12 -> 1200
A13: Home | B13: 1-Bedroom Flat - Standard | C13: Standard | D13: LED Bulbs | E13: 8 | F13: 10 | G13: 6 | H13: 1 | I13: Yes | J13: 1 | K13: =E13*F13*G13*H13 -> 480 | L13: =K13/1000 -> 0.48 | M13: =E13*F13 -> 80 | N13: =M13*J13 -> 80
A14: Home | B14: 1-Bedroom Flat - Standard | C14: Standard | D14: Fans | E14: 2 | F14: 60 | G14: 8 | H14: 1 | I14: Yes | J14: 1.2 | K14: =E14*F14*G14*H14 -> 960 | L14: =K14/1000 -> 0.96 | M14: =E14*F14 -> 120 | N14: =M14*J14 -> 144
A15: Home | B15: 1-Bedroom Flat - Standard | C15: Standard | D15: Television | E15: 1 | F15: 100 | G15: 6 | H15: 1 | I15: Optional | J15: 1.2 | K15: =E15*F15*G15*H15 -> 600 | L15: =K15/1000 -> 0.6 | M15: =E15*F15 -> 100 | N15: =M15*J15 -> 120
... A312: School | B312: Boarding School Common Services | C312: Institution | D312: Fans | E312: 20 | F312: 60 | G312: 8 | H312: 1 | I312: Optional | J312: 1.2 | K312: =E312*F312*G312*H312 -> 9600 | L312: =K312/1000 -> 9.6 | M312: =E312*F312 -> 1200 | N312: =M312*J312 -> 1440

Sheet Appliance_Input
A1: Appliance Input
A3: Equipment | B3: Qty | C3: Wattage W | D3: Hours/Day | E3: Duty Cycle | F3: Effective_Watts | G3: Daily_kWh | H3: Monthly_kWh | I3: Peak_Watts | J3: Notes | K3: Appliance Totals
A4: =IF(User_Inputs!$D$11="","", INDEX( CHOOSE(User_Inputs!$D$11, Appliance_Library!D4:D12, Appliance_Library!D13:D22, Appliance_Library!D23:D33, Appliance_Library!D34:D46, Appliance_Library!D47:D60, Appliance_Library!D61:D73, Appliance_Library!D74:D82, Appliance_Library!D83:D92, Appliance_Library!D93:D102, Appliance_Library!D103:D111, Appliance_Library!D112:D120, Appliance_Library!D121:D128, Appliance_Library!D129:D133, Appliance_Library!D134:D140, Appliance_Library!D141:D148, Appliance_Library!D149:D156, Appliance_Library!D157:D163, Appliance_Library!D164:D173, Appliance_Library!D174:D180, Appliance_Library!D181:D186, Appliance_Library!D187:D191, Appliance_Library!D192:D197, Appliance_Library!D198:D202, Appliance_Library!D203:D208, Appliance_Library!D209:D213, Appliance_Library!D214:D219, Appliance_Library!D220:D223, Appliance_Library!D224:D228, Appliance_Library!D229:D233, Appliance_Library!D234:D241, Appliance_Library!D242:D248, Appliance_Library!D249:D256, Appliance_Library!D257:D265, Appliance_Library!D266:D272, Appliance_Library!D273:D279, Appliance_Library!D280:D286, Appliance_Library!D287:D292, Appliance_Library!D293:D298, Appliance_Library!D299:D305, Appliance_Library!D306:D312 ), ROW()-ROW($D$4)+1)) -> LED Bulbs | B4: =IF(User_Inputs!$D$11="","", INDEX( CHOOSE(User_Inputs!$D$11, Appliance_Library!E4:E12, Appliance_Library!E13:E22, Appliance_Library!E23:E33, Appliance_Library!E34:E46, Appliance_Library!E47:E60, Appliance_Library!E61:E73, Appliance_Library!E74:E82, Appliance_Library!E83:E92, Appliance_Library!E93:E102, Appliance_Library!E103:E111, Appliance_Library!E112:E120, Appliance_Library!E121:E128, Appliance_Library!E129:E133, Appliance_Library!E134:E140, Appliance_Library!E141:E148, Appliance_Library!E149:E156, Appliance_Library!E157:E163, Appliance_Library!E164:E173, Appliance_Library!E174:E180, Appliance_Library!E181:E186, Appliance_Library!E187:E191, Appliance_Library!E192:E197, Appliance_Library!E198:E202, Appliance_Library!E203:E208, Appliance_Library!E209:E213, Appliance_Library!E214:E219, Appliance_Library!E220:E223, Appliance_Library!E224:E228, Appliance_Library!E229:E233, Appliance_Library!E234:E241, Appliance_Library!E242:E248, Appliance_Library!E249:E256, Appliance_Library!E257:E265, Appliance_Library!E266:E272, Appliance_Library!E273:E279, Appliance_Library!E280:E286, Appliance_Library!E287:E292, Appliance_Library!E293:E298, Appliance_Library!E299:E305, Appliance_Library!E306:E312 ), ROW()-ROW($E$4)+1)) -> 12 | C4: =IF(User_Inputs!$D$11="","", INDEX( CHOOSE(User_Inputs!$D$11, Appliance_Library!F4:F12, Appliance_Library!F13:F22, Appliance_Library!F23:F33, Appliance_Library!F34:F46, Appliance_Library!F47:F60, Appliance_Library!F61:F73, Appliance_Library!F74:F82, Appliance_Library!F83:F92, Appliance_Library!F93:F102, Appliance_Library!F103:F111, Appliance_Library!F112:F120, Appliance_Library!F121:F128, Appliance_Library!F129:F133, Appliance_Library!F134:F140, Appliance_Library!F141:F148, Appliance_Library!F149:F156, Appliance_Library!F157:F163, Appliance_Library!F164:F173, Appliance_Library!F174:F180, Appliance_Library!F181:F186, Appliance_Library!F187:F191, Appliance_Library!F192:F197, Appliance_Library!F198:F202, Appliance_Library!F203:F208, Appliance_Library!F209:F213, Appliance_Library!F214:F219, Appliance_Library!F220:F223, Appliance_Library!F224:F228, Appliance_Library!F229:F233, Appliance_Library!F234:F241, Appliance_Library!F242:F248, Appliance_Library!F249:F256, Appliance_Library!F257:F265, Appliance_Library!F266:F272, Appliance_Library!F273:F279, Appliance_Library!F280:F286, Appliance_Library!F287:F292, Appliance_Library!F293:F298, Appliance_Library!F299:F305, Appliance_Library!F306:F312 ), ROW()-ROW($F$4)+1)) -> 10 | D4: =IF(User_Inputs!$D$11="","", INDEX( CHOOSE(User_Inputs!$D$11, Appliance_Library!G4:G12, Appliance_Library!G13:G22, Appliance_Library!G23:G33, Appliance_Library!G34:G46, Appliance_Library!G47:G60, Appliance_Library!G61:G73, Appliance_Library!G74:G82, Appliance_Library!G83:G92, Appliance_Library!G93:G102, Appliance_Library!G103:G111, Appliance_Library!G112:G120, Appliance_Library!G121:G128, Appliance_Library!G129:G133, Appliance_Library!G134:G140, Appliance_Library!G141:G148, Appliance_Library!G149:G156, Appliance_Library!G157:G163, Appliance_Library!G164:G173, Appliance_Library!G174:G180, Appliance_Library!G181:G186, Appliance_Library!G187:G191, Appliance_Library!G192:G197, Appliance_Library!G198:G202, Appliance_Library!G203:G208, Appliance_Library!G209:G213, Appliance_Library!G214:G219, Appliance_Library!G220:G223, Appliance_Library!G224:G228, Appliance_Library!G229:G233, Appliance_Library!G234:G241, Appliance_Library!G242:G248, Appliance_Library!G249:G256, Appliance_Library!G257:G265, Appliance_Library!G266:G272, Appliance_Library!G273:G279, Appliance_Library!G280:G286, Appliance_Library!G287:G292, Appliance_Library!G293:G298, Appliance_Library!G299:G305, Appliance_Library!G306:G312 ), ROW()-ROW($G$4)+1)) -> 6 | E4: =IF(User_Inputs!$D$11="","", INDEX( CHOOSE(User_Inputs!$D$11, Appliance_Library!H4:H12, Appliance_Library!H13:H22, Appliance_Library!H23:H33, Appliance_Library!H34:H46, Appliance_Library!H47:H60, Appliance_Library!H61:H73, Appliance_Library!H74:H82, Appliance_Library!H83:H92, Appliance_Library!H93:H102, Appliance_Library!H103:H111, Appliance_Library!H112:H120, Appliance_Library!H121:H128, Appliance_Library!H129:H133, Appliance_Library!H134:H140, Appliance_Library!H141:H148, Appliance_Library!H149:H156, Appliance_Library!H157:H163, Appliance_Library!H164:H173, Appliance_Library!H174:H180, Appliance_Library!H181:H186, Appliance_Library!H187:H191, Appliance_Library!H192:H197, Appliance_Library!H198:H202, Appliance_Library!H203:H208, Appliance_Library!H209:H213, Appliance_Library!H214:H219, Appliance_Library!H220:H223, Appliance_Library!H224:H228, Appliance_Library!H229:H233, Appliance_Library!H234:H241, Appliance_Library!H242:H248, Appliance_Library!H249:H256, Appliance_Library!H257:H265, Appliance_Library!H266:H272, Appliance_Library!H273:H279, Appliance_Library!H280:H286, Appliance_Library!H287:H292, Appliance_Library!H293:H298, Appliance_Library!H299:H305, Appliance_Library!H306:H312 ), ROW()-ROW($H$4)+1)) -> 1 | F4: =IFERROR(C4*E4,0) -> 10 | G4: =IFERROR(F4*B4*D4/1000,0) -> 0.72 | H4: =G4*30 -> 21.6 | I4: =IFERROR(F4*B4,0) -> 120 | K4: Daily kWh | L4: =SUM(G4:G23) -> 8.055
A5: =IF(User_Inputs!$D$11="","", INDEX( CHOOSE(User_Inputs!$D$11, Appliance_Library!D5:D13, Appliance_Library!D14:D23, Appliance_Library!D24:D34, Appliance_Library!D35:D47, Appliance_Library!D48:D61, Appliance_Library!D62:D74, Appliance_Library!D75:D83, Appliance_Library!D84:D93, Appliance_Library!D94:D103, Appliance_Library!D104:D112, Appliance_Library!D113:D121, Appliance_Library!D122:D129, Appliance_Library!D130:D134, Appliance_Library!D135:D141, Appliance_Library!D142:D149, Appliance_Library!D150:D157, Appliance_Library!D158:D164, Appliance_Library!D165:D174, Appliance_Library!D175:D181, Appliance_Library!D182:D187, Appliance_Library!D188:D192, Appliance_Library!D193:D198, Appliance_Library!D199:D203, Appliance_Library!D204:D209, Appliance_Library!D210:D214, Appliance_Library!D215:D220, Appliance_Library!D221:D224, Appliance_Library!D225:D229, Appliance_Library!D230:D234, Appliance_Library!D235:D242, Appliance_Library!D243:D249, Appliance_Library!D250:D257, Appliance_Library!D258:D266, Appliance_Library!D267:D273, Appliance_Library!D274:D280, Appliance_Library!D281:D287, Appliance_Library!D288:D293, Appliance_Library!D294:D299, Appliance_Library!D300:D306, Appliance_Library!D307:D313 ), ROW()-ROW($D$4)+1)) -> Television | B5: =IF(User_Inputs!$D$11="","", INDEX( CHOOSE(User_Inputs!$D$11, Appliance_Library!E5:E13, Appliance_Library!E14:E23, Appliance_Library!E24:E34, Appliance_Library!E35:E47, Appliance_Library!E48:E61, Appliance_Library!E62:E74, Appliance_Library!E75:E83, Appliance_Library!E84:E93, Appliance_Library!E94:E103, Appliance_Library!E104:E112, Appliance_Library!E113:E121, Appliance_Library!E122:E129, Appliance_Library!E130:E134, Appliance_Library!E135:E141, Appliance_Library!E142:E149, Appliance_Library!E150:E157, Appliance_Library!E158:E164, Appliance_Library!E165:E174, Appliance_Library!E175:E181, Appliance_Library!E182:E187, Appliance_Library!E188:E192, Appliance_Library!E193:E198, Appliance_Library!E199:E203, Appliance_Library!E204:E209, Appliance_Library!E210:E214, Appliance_Library!E215:E220, Appliance_Library!E221:E224, Appliance_Library!E225:E229, Appliance_Library!E230:E234, Appliance_Library!E235:E242, Appliance_Library!E243:E249, Appliance_Library!E250:E257, Appliance_Library!E258:E266, Appliance_Library!E267:E273, Appliance_Library!E274:E280, Appliance_Library!E281:E287, Appliance_Library!E288:E293, Appliance_Library!E294:E299, Appliance_Library!E300:E306, Appliance_Library!E307:E313 ), ROW()-ROW($E$4)+1)) -> 1 | C5: =IF(User_Inputs!$D$11="","", INDEX( CHOOSE(User_Inputs!$D$11, Appliance_Library!F5:F13, Appliance_Library!F14:F23, Appliance_Library!F24:F34, Appliance_Library!F35:F47, Appliance_Library!F48:F61, Appliance_Library!F62:F74, Appliance_Library!F75:F83, Appliance_Library!F84:F93, Appliance_Library!F94:F103, Appliance_Library!F104:F112, Appliance_Library!F113:F121, Appliance_Library!F122:F129, Appliance_Library!F130:F134, Appliance_Library!F135:F141, Appliance_Library!F142:F149, Appliance_Library!F150:F157, Appliance_Library!F158:F164, Appliance_Library!F165:F174, Appliance_Library!F175:F181, Appliance_Library!F182:F187, Appliance_Library!F188:F192, Appliance_Library!F193:F198, Appliance_Library!F199:F203, Appliance_Library!F204:F209, Appliance_Library!F210:F214, Appliance_Library!F215:F220, Appliance_Library!F221:F224, Appliance_Library!F225:F229, Appliance_Library!F230:F234, Appliance_Library!F235:F242, Appliance_Library!F243:F249, Appliance_Library!F250:F257, Appliance_Library!F258:F266, Appliance_Library!F267:F273, Appliance_Library!F274:F280, Appliance_Library!F281:F287, Appliance_Library!F288:F293, Appliance_Library!F294:F299, Appliance_Library!F300:F306, Appliance_Library!F307:F313 ), ROW()-ROW($F$4)+1)) -> 100 | D5: =IF(User_Inputs!$D$11="","", INDEX( CHOOSE(User_Inputs!$D$11, Appliance_Library!G5:G13, Appliance_Library!G14:G23, Appliance_Library!G24:G34, Appliance_Library!G35:G47, Appliance_Library!G48:G61, Appliance_Library!G62:G74, Appliance_Library!G75:G83, Appliance_Library!G84:G93, Appliance_Library!G94:G103, Appliance_Library!G104:G112, Appliance_Library!G113:G121, Appliance_Library!G122:G129, Appliance_Library!G130:G134, Appliance_Library!G135:G141, Appliance_Library!G142:G149, Appliance_Library!G150:G157, Appliance_Library!G158:G164, Appliance_Library!G165:G174, Appliance_Library!G175:G181, Appliance_Library!G182:G187, Appliance_Library!G188:G192, Appliance_Library!G193:G198, Appliance_Library!G199:G203, Appliance_Library!G204:G209, Appliance_Library!G210:G214, Appliance_Library!G215:G220, Appliance_Library!G221:G224, Appliance_Library!G225:G229, Appliance_Library!G230:G234, Appliance_Library!G235:G242, Appliance_Library!G243:G249, Appliance_Library!G250:G257, Appliance_Library!G258:G266, Appliance_Library!G267:G273, Appliance_Library!G274:G280, Appliance_Library!G281:G287, Appliance_Library!G288:G293, Appliance_Library!G294:G299, Appliance_Library!G300:G306, Appliance_Library!G307:G313 ), ROW()-ROW($G$4)+1)) -> 6 | E5: =IF(User_Inputs!$D$11="","", INDEX( CHOOSE(User_Inputs!$D$11, Appliance_Library!H5:H13, Appliance_Library!H14:H23, Appliance_Library!H24:H34, Appliance_Library!H35:H47, Appliance_Library!H48:H61, Appliance_Library!H62:H74, Appliance_Library!H75:H83, Appliance_Library!H84:H93, Appliance_Library!H94:H103, Appliance_Library!H104:H112, Appliance_Library!H113:H121, Appliance_Library!H122:H129, Appliance_Library!H130:H134, Appliance_Library!H135:H141, Appliance_Library!H142:H149, Appliance_Library!H150:H157, Appliance_Library!H158:H164, Appliance_Library!H165:H174, Appliance_Library!H175:H181, Appliance_Library!H182:H187, Appliance_Library!H188:H192, Appliance_Library!H193:H198, Appliance_Library!H199:H203, Appliance_Library!H204:H209, Appliance_Library!H210:H214, Appliance_Library!H215:H220, Appliance_Library!H221:H224, Appliance_Library!H225:H229, Appliance_Library!H230:H234, Appliance_Library!H235:H242, Appliance_Library!H243:H249, Appliance_Library!H250:H257, Appliance_Library!H258:H266, Appliance_Library!H267:H273, Appliance_Library!H274:H280, Appliance_Library!H281:H287, Appliance_Library!H288:H293, Appliance_Library!H294:H299, Appliance_Library!H300:H306, Appliance_Library!H307:H313 ), ROW()-ROW($H$4)+1)) -> 1 | F5: =IFERROR(C5*E5,0) -> 100 | G5: =IFERROR(F5*B5*D5/1000,0) -> 0.6 | H5: =G5*30 -> 18 | I5: =IFERROR(F5*B5,0) -> 100 | K5: Monthly kWh | L5: =SUM(H4:H23) -> 241.65
A6: =IF(User_Inputs!$D$11="","", INDEX( CHOOSE(User_Inputs!$D$11, Appliance_Library!D6:D14, Appliance_Library!D15:D24, Appliance_Library!D25:D35, Appliance_Library!D36:D48, Appliance_Library!D49:D62, Appliance_Library!D63:D75, Appliance_Library!D76:D84, Appliance_Library!D85:D94, Appliance_Library!D95:D104, Appliance_Library!D105:D113, Appliance_Library!D114:D122, Appliance_Library!D123:D130, Appliance_Library!D131:D135, Appliance_Library!D136:D142, Appliance_Library!D143:D150, Appliance_Library!D151:D158, Appliance_Library!D159:D165, Appliance_Library!D166:D175, Appliance_Library!D176:D182, Appliance_Library!D183:D188, Appliance_Library!D189:D193, Appliance_Library!D194:D199, Appliance_Library!D200:D204, Appliance_Library!D205:D210, Appliance_Library!D211:D215, Appliance_Library!D216:D221, Appliance_Library!D222:D225, Appliance_Library!D226:D230, Appliance_Library!D231:D235, Appliance_Library!D236:D243, Appliance_Library!D244:D250, Appliance_Library!D251:D258, Appliance_Library!D259:D267, Appliance_Library!D268:D274, Appliance_Library!D275:D281, Appliance_Library!D282:D288, Appliance_Library!D289:D294, Appliance_Library!D295:D300, Appliance_Library!D301:D307, Appliance_Library!D308:D314 ), ROW()-ROW($D$4)+1)) -> Refrigerator | B6: =IF(User_Inputs!$D$11="","", INDEX( CHOOSE(User_Inputs!$D$11, Appliance_Library!E6:E14, Appliance_Library!E15:E24, Appliance_Library!E25:E35, Appliance_Library!E36:E48, Appliance_Library!E49:E62, Appliance_Library!E63:E75, Appliance_Library!E76:E84, Appliance_Library!E85:E94, Appliance_Library!E95:E104, Appliance_Library!E105:E113, Appliance_Library!E114:E122, Appliance_Library!E123:E130, Appliance_Library!E131:E135, Appliance_Library!E136:E142, Appliance_Library!E143:E150, Appliance_Library!E151:E158, Appliance_Library!E159:E165, Appliance_Library!E166:E175, Appliance_Library!E176:E182, Appliance_Library!E183:E188, Appliance_Library!E189:E193, Appliance_Library!E194:E199, Appliance_Library!E200:E204, Appliance_Library!E205:E210, Appliance_Library!E211:E215, Appliance_Library!E216:E221, Appliance_Library!E222:E225, Appliance_Library!E226:E230, Appliance_Library!E231:E235, Appliance_Library!E236:E243, Appliance_Library!E244:E250, Appliance_Library!E251:E258, Appliance_Library!E259:E267, Appliance_Library!E268:E274, Appliance_Library!E275:E281, Appliance_Library!E282:E288, Appliance_Library!E289:E294, Appliance_Library!E295:E300, Appliance_Library!E301:E307, Appliance_Library!E308:E314 ), ROW()-ROW($E$4)+1)) -> 1 | C6: =IF(User_Inputs!$D$11="","", INDEX( CHOOSE(User_Inputs!$D$11, Appliance_Library!F6:F14, Appliance_Library!F15:F24, Appliance_Library!F25:F35, Appliance_Library!F36:F48, Appliance_Library!F49:F62, Appliance_Library!F63:F75, Appliance_Library!F76:F84, Appliance_Library!F85:F94, Appliance_Library!F95:F104, Appliance_Library!F105:F113, Appliance_Library!F114:F122, Appliance_Library!F123:F130, Appliance_Library!F131:F135, Appliance_Library!F136:F142, Appliance_Library!F143:F150, Appliance_Library!F151:F158, Appliance_Library!F159:F165, Appliance_Library!F166:F175, Appliance_Library!F176:F182, Appliance_Library!F183:F188, Appliance_Library!F189:F193, Appliance_Library!F194:F199, Appliance_Library!F200:F204, Appliance_Library!F205:F210, Appliance_Library!F211:F215, Appliance_Library!F216:F221, Appliance_Library!F222:F225, Appliance_Library!F226:F230, Appliance_Library!F231:F235, Appliance_Library!F236:F243, Appliance_Library!F244:F250, Appliance_Library!F251:F258, Appliance_Library!F259:F267, Appliance_Library!F268:F274, Appliance_Library!F275:F281, Appliance_Library!F282:F288, Appliance_Library!F289:F294, Appliance_Library!F295:F300, Appliance_Library!F301:F307, Appliance_Library!F308:F314 ), ROW()-ROW($F$4)+1)) -> 150 | D6: =IF(User_Inputs!$D$11="","", INDEX( CHOOSE(User_Inputs!$D$11, Appliance_Library!G6:G14, Appliance_Library!G15:G24, Appliance_Library!G25:G35, Appliance_Library!G36:G48, Appliance_Library!G49:G62, Appliance_Library!G63:G75, Appliance_Library!G76:G84, Appliance_Library!G85:G94, Appliance_Library!G95:G104, Appliance_Library!G105:G113, Appliance_Library!G114:G122, Appliance_Library!G123:G130, Appliance_Library!G131:G135, Appliance_Library!G136:G142, Appliance_Library!G143:G150, Appliance_Library!G151:G158, Appliance_Library!G159:G165, Appliance_Library!G166:G175, Appliance_Library!G176:G182, Appliance_Library!G183:G188, Appliance_Library!G189:G193, Appliance_Library!G194:G199, Appliance_Library!G200:G204, Appliance_Library!G205:G210, Appliance_Library!G211:G215, Appliance_Library!G216:G221, Appliance_Library!G222:G225, Appliance_Library!G226:G230, Appliance_Library!G231:G235, Appliance_Library!G236:G243, Appliance_Library!G244:G250, Appliance_Library!G251:G258, Appliance_Library!G259:G267, Appliance_Library!G268:G274, Appliance_Library!G275:G281, Appliance_Library!G282:G288, Appliance_Library!G289:G294, Appliance_Library!G295:G300, Appliance_Library!G301:G307, Appliance_Library!G308:G314 ), ROW()-ROW($G$4)+1)) -> 24 | E6: =IF(User_Inputs!$D$11="","", INDEX( CHOOSE(User_Inputs!$D$11, Appliance_Library!H6:H14, Appliance_Library!H15:H24, Appliance_Library!H25:H35, Appliance_Library!H36:H48, Appliance_Library!H49:H62, Appliance_Library!H63:H75, Appliance_Library!H76:H84, Appliance_Library!H85:H94, Appliance_Library!H95:H104, Appliance_Library!H105:H113, Appliance_Library!H114:H122, Appliance_Library!H123:H130, Appliance_Library!H131:H135, Appliance_Library!H136:H142, Appliance_Library!H143:H150, Appliance_Library!H151:H158, Appliance_Library!H159:H165, Appliance_Library!H166:H175, Appliance_Library!H176:H182, Appliance_Library!H183:H188, Appliance_Library!H189:H193, Appliance_Library!H194:H199, Appliance_Library!H200:H204, Appliance_Library!H205:H210, Appliance_Library!H211:H215, Appliance_Library!H216:H221, Appliance_Library!H222:H225, Appliance_Library!H226:H230, Appliance_Library!H231:H235, Appliance_Library!H236:H243, Appliance_Library!H244:H250, Appliance_Library!H251:H258, Appliance_Library!H259:H267, Appliance_Library!H268:H274, Appliance_Library!H275:H281, Appliance_Library!H282:H288, Appliance_Library!H289:H294, Appliance_Library!H295:H300, Appliance_Library!H301:H307, Appliance_Library!H308:H314 ), ROW()-ROW($H$4)+1)) -> 0.4 | F6: =IFERROR(C6*E6,0) -> 60 | G6: =IFERROR(F6*B6*D6/1000,0) -> 1.44 | H6: =G6*30 -> 43.2 | I6: =IFERROR(F6*B6,0) -> 60 | K6: Raw Peak kW | L6: =SUM(I4:I23)/1000 -> 2.885
A7: =IF(User_Inputs!$D$11="","", INDEX( CHOOSE(User_Inputs!$D$11, Appliance_Library!D7:D15, Appliance_Library!D16:D25, Appliance_Library!D26:D36, Appliance_Library!D37:D49, Appliance_Library!D50:D63, Appliance_Library!D64:D76, Appliance_Library!D77:D85, Appliance_Library!D86:D95, Appliance_Library!D96:D105, Appliance_Library!D106:D114, Appliance_Library!D115:D123, Appliance_Library!D124:D131, Appliance_Library!D132:D136, Appliance_Library!D137:D143, Appliance_Library!D144:D151, Appliance_Library!D152:D159, Appliance_Library!D160:D166, Appliance_Library!D167:D176, Appliance_Library!D177:D183, Appliance_Library!D184:D189, Appliance_Library!D190:D194, Appliance_Library!D195:D200, Appliance_Library!D201:D205, Appliance_Library!D206:D211, Appliance_Library!D212:D216, Appliance_Library!D217:D222, Appliance_Library!D223:D226, Appliance_Library!D227:D231, Appliance_Library!D232:D236, Appliance_Library!D237:D244, Appliance_Library!D245:D251, Appliance_Library!D252:D259, Appliance_Library!D260:D268, Appliance_Library!D269:D275, Appliance_Library!D276:D282, Appliance_Library!D283:D289, Appliance_Library!D290:D295, Appliance_Library!D296:D301, Appliance_Library!D302:D308, Appliance_Library!D309:D315 ), ROW()-ROW($D$4)+1)) -> Laptop | B7: =IF(User_Inputs!$D$11="","", INDEX( CHOOSE(User_Inputs!$D$11, Appliance_Library!E7:E15, Appliance_Library!E16:E25, Appliance_Library!E26:E36, Appliance_Library!E37:E49, Appliance_Library!E50:E63, Appliance_Library!E64:E76, Appliance_Library!E77:E85, Appliance_Library!E86:E95, Appliance_Library!E96:E105, Appliance_Library!E106:E114, Appliance_Library!E115:E123, Appliance_Library!E124:E131, Appliance_Library!E132:E136, Appliance_Library!E137:E143, Appliance_Library!E144:E151, Appliance_Library!E152:E159, Appliance_Library!E160:E166, Appliance_Library!E167:E176, Appliance_Library!E177:E183, Appliance_Library!E184:E189, Appliance_Library!E190:E194, Appliance_Library!E195:E200, Appliance_Library!E201:E205, Appliance_Library!E206:E211, Appliance_Library!E212:E216, Appliance_Library!E217:E222, Appliance_Library!E223:E226, Appliance_Library!E227:E231, Appliance_Library!E232:E236, Appliance_Library!E237:E244, Appliance_Library!E245:E251, Appliance_Library!E252:E259, Appliance_Library!E260:E268, Appliance_Library!E269:E275, Appliance_Library!E276:E282, Appliance_Library!E283:E289, Appliance_Library!E290:E295, Appliance_Library!E296:E301, Appliance_Library!E302:E308, Appliance_Library!E309:E315 ), ROW()-ROW($E$4)+1)) -> 2 | C7: =IF(User_Inputs!$D$11="","", INDEX( CHOOSE(User_Inputs!$D$11, Appliance_Library!F7:F15, Appliance_Library!F16:F25, Appliance_Library!F26:F36, Appliance_Library!F37:F49, Appliance_Library!F50:F63, Appliance_Library!F64:F76, Appliance_Library!F77:F85, Appliance_Library!F86:F95, Appliance_Library!F96:F105, Appliance_Library!F106:F114, Appliance_Library!F115:F123, Appliance_Library!F124:F131, Appliance_Library!F132:F136, Appliance_Library!F137:F143, Appliance_Library!F144:F151, Appliance_Library!F152:F159, Appliance_Library!F160:F166, Appliance_Library!F167:F176, Appliance_Library!F177:F183, Appliance_Library!F184:F189, Appliance_Library!F190:F194, Appliance_Library!F195:F200, Appliance_Library!F201:F205, Appliance_Library!F206:F211, Appliance_Library!F212:F216, Appliance_Library!F217:F222, Appliance_Library!F223:F226, Appliance_Library!F227:F231, Appliance_Library!F232:F236, Appliance_Library!F237:F244, Appliance_Library!F245:F251, Appliance_Library!F252:F259, Appliance_Library!F260:F268, Appliance_Library!F269:F275, Appliance_Library!F276:F282, Appliance_Library!F283:F289, Appliance_Library!F290:F295, Appliance_Library!F296:F301, Appliance_Library!F302:F308, Appliance_Library!F309:F315 ), ROW()-ROW($F$4)+1)) -> 65 | D7: =IF(User_Inputs!$D$11="","", INDEX( CHOOSE(User_Inputs!$D$11, Appliance_Library!G7:G15, Appliance_Library!G16:G25, Appliance_Library!G26:G36, Appliance_Library!G37:G49, Appliance_Library!G50:G63, Appliance_Library!G64:G76, Appliance_Library!G77:G85, Appliance_Library!G86:G95, Appliance_Library!G96:G105, Appliance_Library!G106:G114, Appliance_Library!G115:G123, Appliance_Library!G124:G131, Appliance_Library!G132:G136, Appliance_Library!G137:G143, Appliance_Library!G144:G151, Appliance_Library!G152:G159, Appliance_Library!G160:G166, Appliance_Library!G167:G176, Appliance_Library!G177:G183, Appliance_Library!G184:G189, Appliance_Library!G190:G194, Appliance_Library!G195:G200, Appliance_Library!G201:G205, Appliance_Library!G206:G211, Appliance_Library!G212:G216, Appliance_Library!G217:G222, Appliance_Library!G223:G226, Appliance_Library!G227:G231, Appliance_Library!G232:G236, Appliance_Library!G237:G244, Appliance_Library!G245:G251, Appliance_Library!G252:G259, Appliance_Library!G260:G268, Appliance_Library!G269:G275, Appliance_Library!G276:G282, Appliance_Library!G283:G289, Appliance_Library!G290:G295, Appliance_Library!G296:G301, Appliance_Library!G302:G308, Appliance_Library!G309:G315 ), ROW()-ROW($G$4)+1)) -> 5 | E7: =IF(User_Inputs!$D$11="","", INDEX( CHOOSE(User_Inputs!$D$11, Appliance_Library!H7:H15, Appliance_Library!H16:H25, Appliance_Library!H26:H36, Appliance_Library!H37:H49, Appliance_Library!H50:H63, Appliance_Library!H64:H76, Appliance_Library!H77:H85, Appliance_Library!H86:H95, Appliance_Library!H96:H105, Appliance_Library!H106:H114, Appliance_Library!H115:H123, Appliance_Library!H124:H131, Appliance_Library!H132:H136, Appliance_Library!H137:H143, Appliance_Library!H144:H151, Appliance_Library!H152:H159, Appliance_Library!H160:H166, Appliance_Library!H167:H176, Appliance_Library!H177:H183, Appliance_Library!H184:H189, Appliance_Library!H190:H194, Appliance_Library!H195:H200, Appliance_Library!H201:H205, Appliance_Library!H206:H211, Appliance_Library!H212:H216, Appliance_Library!H217:H222, Appliance_Library!H223:H226, Appliance_Library!H227:H231, Appliance_Library!H232:H236, Appliance_Library!H237:H244, Appliance_Library!H245:H251, Appliance_Library!H252:H259, Appliance_Library!H260:H268, Appliance_Library!H269:H275, Appliance_Library!H276:H282, Appliance_Library!H283:H289, Appliance_Library!H290:H295, Appliance_Library!H296:H301, Appliance_Library!H302:H308, Appliance_Library!H309:H315 ), ROW()-ROW($H$4)+1)) -> 1 | F7: =IFERROR(C7*E7,0) -> 65 | G7: =IFERROR(F7*B7*D7/1000,0) -> 0.65 | H7: =G7*30 -> 19.5 | I7: =IFERROR(F7*B7,0) -> 130 | K7: Diversity-adjusted Peak kW | L7: =L6*0.65 -> 1.87525
A8: =IF(User_Inputs!$D$11="","", INDEX( CHOOSE(User_Inputs!$D$11, Appliance_Library!D8:D16, Appliance_Library!D17:D26, Appliance_Library!D27:D37, Appliance_Library!D38:D50, Appliance_Library!D51:D64, Appliance_Library!D65:D77, Appliance_Library!D78:D86, Appliance_Library!D87:D96, Appliance_Library!D97:D106, Appliance_Library!D107:D115, Appliance_Library!D116:D124, Appliance_Library!D125:D132, Appliance_Library!D133:D137, Appliance_Library!D138:D144, Appliance_Library!D145:D152, Appliance_Library!D153:D160, Appliance_Library!D161:D167, Appliance_Library!D168:D177, Appliance_Library!D178:D184, Appliance_Library!D185:D190, Appliance_Library!D191:D195, Appliance_Library!D196:D201, Appliance_Library!D202:D206, Appliance_Library!D207:D212, Appliance_Library!D213:D217, Appliance_Library!D218:D223, Appliance_Library!D224:D227, Appliance_Library!D228:D232, Appliance_Library!D233:D237, Appliance_Library!D238:D245, Appliance_Library!D246:D252, Appliance_Library!D253:D260, Appliance_Library!D261:D269, Appliance_Library!D270:D276, Appliance_Library!D277:D283, Appliance_Library!D284:D290, Appliance_Library!D291:D296, Appliance_Library!D297:D302, Appliance_Library!D303:D309, Appliance_Library!D310:D316 ), ROW()-ROW($D$4)+1)) -> Sound Bar | B8: =IF(User_Inputs!$D$11="","", INDEX( CHOOSE(User_Inputs!$D$11, Appliance_Library!E8:E16, Appliance_Library!E17:E26, Appliance_Library!E27:E37, Appliance_Library!E38:E50, Appliance_Library!E51:E64, Appliance_Library!E65:E77, Appliance_Library!E78:E86, Appliance_Library!E87:E96, Appliance_Library!E97:E106, Appliance_Library!E107:E115, Appliance_Library!E116:E124, Appliance_Library!E125:E132, Appliance_Library!E133:E137, Appliance_Library!E138:E144, Appliance_Library!E145:E152, Appliance_Library!E153:E160, Appliance_Library!E161:E167, Appliance_Library!E168:E177, Appliance_Library!E178:E184, Appliance_Library!E185:E190, Appliance_Library!E191:E195, Appliance_Library!E196:E201, Appliance_Library!E202:E206, Appliance_Library!E207:E212, Appliance_Library!E213:E217, Appliance_Library!E218:E223, Appliance_Library!E224:E227, Appliance_Library!E228:E232, Appliance_Library!E233:E237, Appliance_Library!E238:E245, Appliance_Library!E246:E252, Appliance_Library!E253:E260, Appliance_Library!E261:E269, Appliance_Library!E270:E276, Appliance_Library!E277:E283, Appliance_Library!E284:E290, Appliance_Library!E291:E296, Appliance_Library!E297:E302, Appliance_Library!E303:E309, Appliance_Library!E310:E316 ), ROW()-ROW($E$4)+1)) -> 1 | C8: =IF(User_Inputs!$D$11="","", INDEX( CHOOSE(User_Inputs!$D$11, Appliance_Library!F8:F16, Appliance_Library!F17:F26, Appliance_Library!F27:F37, Appliance_Library!F38:F50, Appliance_Library!F51:F64, Appliance_Library!F65:F77, Appliance_Library!F78:F86, Appliance_Library!F87:F96, Appliance_Library!F97:F106, Appliance_Library!F107:F115, Appliance_Library!F116:F124, Appliance_Library!F125:F132, Appliance_Library!F133:F137, Appliance_Library!F138:F144, Appliance_Library!F145:F152, Appliance_Library!F153:F160, Appliance_Library!F161:F167, Appliance_Library!F168:F177, Appliance_Library!F178:F184, Appliance_Library!F185:F190, Appliance_Library!F191:F195, Appliance_Library!F196:F201, Appliance_Library!F202:F206, Appliance_Library!F207:F212, Appliance_Library!F213:F217, Appliance_Library!F218:F223, Appliance_Library!F224:F227, Appliance_Library!F228:F232, Appliance_Library!F233:F237, Appliance_Library!F238:F245, Appliance_Library!F246:F252, Appliance_Library!F253:F260, Appliance_Library!F261:F269, Appliance_Library!F270:F276, Appliance_Library!F277:F283, Appliance_Library!F284:F290, Appliance_Library!F291:F296, Appliance_Library!F297:F302, Appliance_Library!F303:F309, Appliance_Library!F310:F316 ), ROW()-ROW($F$4)+1)) -> 50 | D8: =IF(User_Inputs!$D$11="","", INDEX( CHOOSE(User_Inputs!$D$11, Appliance_Library!G8:G16, Appliance_Library!G17:G26, Appliance_Library!G27:G37, Appliance_Library!G38:G50, Appliance_Library!G51:G64, Appliance_Library!G65:G77, Appliance_Library!G78:G86, Appliance_Library!G87:G96, Appliance_Library!G97:G106, Appliance_Library!G107:G115, Appliance_Library!G116:G124, Appliance_Library!G125:G132, Appliance_Library!G133:G137, Appliance_Library!G138:G144, Appliance_Library!G145:G152, Appliance_Library!G153:G160, Appliance_Library!G161:G167, Appliance_Library!G168:G177, Appliance_Library!G178:G184, Appliance_Library!G185:G190, Appliance_Library!G191:G195, Appliance_Library!G196:G201, Appliance_Library!G202:G206, Appliance_Library!G207:G212, Appliance_Library!G213:G217, Appliance_Library!G218:G223, Appliance_Library!G224:G227, Appliance_Library!G228:G232, Appliance_Library!G233:G237, Appliance_Library!G238:G245, Appliance_Library!G246:G252, Appliance_Library!G253:G260, Appliance_Library!G261:G269, Appliance_Library!G270:G276, Appliance_Library!G277:G283, Appliance_Library!G284:G290, Appliance_Library!G291:G296, Appliance_Library!G297:G302, Appliance_Library!G303:G309, Appliance_Library!G310:G316 ), ROW()-ROW($G$4)+1)) -> 2 | E8: =IF(User_Inputs!$D$11="","", INDEX( CHOOSE(User_Inputs!$D$11, Appliance_Library!H8:H16, Appliance_Library!H17:H26, Appliance_Library!H27:H37, Appliance_Library!H38:H50, Appliance_Library!H51:H64, Appliance_Library!H65:H77, Appliance_Library!H78:H86, Appliance_Library!H87:H96, Appliance_Library!H97:H106, Appliance_Library!H107:H115, Appliance_Library!H116:H124, Appliance_Library!H125:H132, Appliance_Library!H133:H137, Appliance_Library!H138:H144, Appliance_Library!H145:H152, Appliance_Library!H153:H160, Appliance_Library!H161:H167, Appliance_Library!H168:H177, Appliance_Library!H178:H184, Appliance_Library!H185:H190, Appliance_Library!H191:H195, Appliance_Library!H196:H201, Appliance_Library!H202:H206, Appliance_Library!H207:H212, Appliance_Library!H213:H217, Appliance_Library!H218:H223, Appliance_Library!H224:H227, Appliance_Library!H228:H232, Appliance_Library!H233:H237, Appliance_Library!H238:H245, Appliance_Library!H246:H252, Appliance_Library!H253:H260, Appliance_Library!H261:H269, Appliance_Library!H270:H276, Appliance_Library!H277:H283, Appliance_Library!H284:H290, Appliance_Library!H291:H296, Appliance_Library!H297:H302, Appliance_Library!H303:H309, Appliance_Library!H310:H316 ), ROW()-ROW($H$4)+1)) -> 1 | F8: =IFERROR(C8*E8,0) -> 50 | G8: =IFERROR(F8*B8*D8/1000,0) -> 0.1 | H8: =G8*30 -> 3 | I8: =IFERROR(F8*B8,0) -> 50
A9: =IF(User_Inputs!$D$11="","", INDEX( CHOOSE(User_Inputs!$D$11, Appliance_Library!D9:D17, Appliance_Library!D18:D27, Appliance_Library!D28:D38, Appliance_Library!D39:D51, Appliance_Library!D52:D65, Appliance_Library!D66:D78, Appliance_Library!D79:D87, Appliance_Library!D88:D97, Appliance_Library!D98:D107, Appliance_Library!D108:D116, Appliance_Library!D117:D125, Appliance_Library!D126:D133, Appliance_Library!D134:D138, Appliance_Library!D139:D145, Appliance_Library!D146:D153, Appliance_Library!D154:D161, Appliance_Library!D162:D168, Appliance_Library!D169:D178, Appliance_Library!D179:D185, Appliance_Library!D186:D191, Appliance_Library!D192:D196, Appliance_Library!D197:D202, Appliance_Library!D203:D207, Appliance_Library!D208:D213, Appliance_Library!D214:D218, Appliance_Library!D219:D224, Appliance_Library!D225:D228, Appliance_Library!D229:D233, Appliance_Library!D234:D238, Appliance_Library!D239:D246, Appliance_Library!D247:D253, Appliance_Library!D254:D261, Appliance_Library!D262:D270, Appliance_Library!D271:D277, Appliance_Library!D278:D284, Appliance_Library!D285:D291, Appliance_Library!D292:D297, Appliance_Library!D298:D303, Appliance_Library!D304:D310, Appliance_Library!D311:D317 ), ROW()-ROW($D$4)+1)) -> Water Pump | B9: =IF(User_Inputs!$D$11="","", INDEX( CHOOSE(User_Inputs!$D$11, Appliance_Library!E9:E17, Appliance_Library!E18:E27, Appliance_Library!E28:E38, Appliance_Library!E39:E51, Appliance_Library!E52:E65, Appliance_Library!E66:E78, Appliance_Library!E79:E87, Appliance_Library!E88:E97, Appliance_Library!E98:E107, Appliance_Library!E108:E116, Appliance_Library!E117:E125, Appliance_Library!E126:E133, Appliance_Library!E134:E138, Appliance_Library!E139:E145, Appliance_Library!E146:E153, Appliance_Library!E154:E161, Appliance_Library!E162:E168, Appliance_Library!E169:E178, Appliance_Library!E179:E185, Appliance_Library!E186:E191, Appliance_Library!E192:E196, Appliance_Library!E197:E202, Appliance_Library!E203:E207, Appliance_Library!E208:E213, Appliance_Library!E214:E218, Appliance_Library!E219:E224, Appliance_Library!E225:E228, Appliance_Library!E229:E233, Appliance_Library!E234:E238, Appliance_Library!E239:E246, Appliance_Library!E247:E253, Appliance_Library!E254:E261, Appliance_Library!E262:E270, Appliance_Library!E271:E277, Appliance_Library!E278:E284, Appliance_Library!E285:E291, Appliance_Library!E292:E297, Appliance_Library!E298:E303, Appliance_Library!E304:E310, Appliance_Library!E311:E317 ), ROW()-ROW($E$4)+1)) -> 1 | C9: =IF(User_Inputs!$D$11="","", INDEX( CHOOSE(User_Inputs!$D$11, Appliance_Library!F9:F17, Appliance_Library!F18:F27, Appliance_Library!F28:F38, Appliance_Library!F39:F51, Appliance_Library!F52:F65, Appliance_Library!F66:F78, Appliance_Library!F79:F87, Appliance_Library!F88:F97, Appliance_Library!F98:F107, Appliance_Library!F108:F116, Appliance_Library!F117:F125, Appliance_Library!F126:F133, Appliance_Library!F134:F138, Appliance_Library!F139:F145, Appliance_Library!F146:F153, Appliance_Library!F154:F161, Appliance_Library!F162:F168, Appliance_Library!F169:F178, Appliance_Library!F179:F185, Appliance_Library!F186:F191, Appliance_Library!F192:F196, Appliance_Library!F197:F202, Appliance_Library!F203:F207, Appliance_Library!F208:F213, Appliance_Library!F214:F218, Appliance_Library!F219:F224, Appliance_Library!F225:F228, Appliance_Library!F229:F233, Appliance_Library!F234:F238, Appliance_Library!F239:F246, Appliance_Library!F247:F253, Appliance_Library!F254:F261, Appliance_Library!F262:F270, Appliance_Library!F271:F277, Appliance_Library!F278:F284, Appliance_Library!F285:F291, Appliance_Library!F292:F297, Appliance_Library!F298:F303, Appliance_Library!F304:F310, Appliance_Library!F311:F317 ), ROW()-ROW($F$4)+1)) -> 750 | D9: =IF(User_Inputs!$D$11="","", INDEX( CHOOSE(User_Inputs!$D$11, Appliance_Library!G9:G17, Appliance_Library!G18:G27, Appliance_Library!G28:G38, Appliance_Library!G39:G51, Appliance_Library!G52:G65, Appliance_Library!G66:G78, Appliance_Library!G79:G87, Appliance_Library!G88:G97, Appliance_Library!G98:G107, Appliance_Library!G108:G116, Appliance_Library!G117:G125, Appliance_Library!G126:G133, Appliance_Library!G134:G138, Appliance_Library!G139:G145, Appliance_Library!G146:G153, Appliance_Library!G154:G161, Appliance_Library!G162:G168, Appliance_Library!G169:G178, Appliance_Library!G179:G185, Appliance_Library!G186:G191, Appliance_Library!G192:G196, Appliance_Library!G197:G202, Appliance_Library!G203:G207, Appliance_Library!G208:G213, Appliance_Library!G214:G218, Appliance_Library!G219:G224, Appliance_Library!G225:G228, Appliance_Library!G229:G233, Appliance_Library!G234:G238, Appliance_Library!G239:G246, Appliance_Library!G247:G253, Appliance_Library!G254:G261, Appliance_Library!G262:G270, Appliance_Library!G271:G277, Appliance_Library!G278:G284, Appliance_Library!G285:G291, Appliance_Library!G292:G297, Appliance_Library!G298:G303, Appliance_Library!G304:G310, Appliance_Library!G311:G317 ), ROW()-ROW($G$4)+1)) -> 0.5 | E9: =IF(User_Inputs!$D$11="","", INDEX( CHOOSE(User_Inputs!$D$11, Appliance_Library!H9:H17, Appliance_Library!H18:H27, Appliance_Library!H28:H38, Appliance_Library!H39:H51, Appliance_Library!H52:H65, Appliance_Library!H66:H78, Appliance_Library!H79:H87, Appliance_Library!H88:H97, Appliance_Library!H98:H107, Appliance_Library!H108:H116, Appliance_Library!H117:H125, Appliance_Library!H126:H133, Appliance_Library!H134:H138, Appliance_Library!H139:H145, Appliance_Library!H146:H153, Appliance_Library!H154:H161, Appliance_Library!H162:H168, Appliance_Library!H169:H178, Appliance_Library!H179:H185, Appliance_Library!H186:H191, Appliance_Library!H192:H196, Appliance_Library!H197:H202, Appliance_Library!H203:H207, Appliance_Library!H208:H213, Appliance_Library!H214:H218, Appliance_Library!H219:H224, Appliance_Library!H225:H228, Appliance_Library!H229:H233, Appliance_Library!H234:H238, Appliance_Library!H239:H246, Appliance_Library!H247:H253, Appliance_Library!H254:H261, Appliance_Library!H262:H270, Appliance_Library!H271:H277, Appliance_Library!H278:H284, Appliance_Library!H285:H291, Appliance_Library!H292:H297, Appliance_Library!H298:H303, Appliance_Library!H304:H310, Appliance_Library!H311:H317 ), ROW()-ROW($H$4)+1)) -> 1 | F9: =IFERROR(C9*E9,0) -> 750 | G9: =IFERROR(F9*B9*D9/1000,0) -> 0.375 | H9: =G9*30 -> 11.25 | I9: =IFERROR(F9*B9,0) -> 750
A10: =IF(User_Inputs!$D$11="","", INDEX( CHOOSE(User_Inputs!$D$11, Appliance_Library!D10:D18, Appliance_Library!D19:D28, Appliance_Library!D29:D39, Appliance_Library!D40:D52, Appliance_Library!D53:D66, Appliance_Library!D67:D79, Appliance_Library!D80:D88, Appliance_Library!D89:D98, Appliance_Library!D99:D108, Appliance_Library!D109:D117, Appliance_Library!D118:D126, Appliance_Library!D127:D134, Appliance_Library!D135:D139, Appliance_Library!D140:D146, Appliance_Library!D147:D154, Appliance_Library!D155:D162, Appliance_Library!D163:D169, Appliance_Library!D170:D179, Appliance_Library!D180:D186, Appliance_Library!D187:D192, Appliance_Library!D193:D197, Appliance_Library!D198:D203, Appliance_Library!D204:D208, Appliance_Library!D209:D214, Appliance_Library!D215:D219, Appliance_Library!D220:D225, Appliance_Library!D226:D229, Appliance_Library!D230:D234, Appliance_Library!D235:D239, Appliance_Library!D240:D247, Appliance_Library!D248:D254, Appliance_Library!D255:D262, Appliance_Library!D263:D271, Appliance_Library!D272:D278, Appliance_Library!D279:D285, Appliance_Library!D286:D292, Appliance_Library!D293:D298, Appliance_Library!D299:D304, Appliance_Library!D305:D311, Appliance_Library!D312:D318 ), ROW()-ROW($D$4)+1)) -> Fans | B10: =IF(User_Inputs!$D$11="","", INDEX( CHOOSE(User_Inputs!$D$11, Appliance_Library!E10:E18, Appliance_Library!E19:E28, Appliance_Library!E29:E39, Appliance_Library!E40:E52, Appliance_Library!E53:E66, Appliance_Library!E67:E79, Appliance_Library!E80:E88, Appliance_Library!E89:E98, Appliance_Library!E99:E108, Appliance_Library!E109:E117, Appliance_Library!E118:E126, Appliance_Library!E127:E134, Appliance_Library!E135:E139, Appliance_Library!E140:E146, Appliance_Library!E147:E154, Appliance_Library!E155:E162, Appliance_Library!E163:E169, Appliance_Library!E170:E179, Appliance_Library!E180:E186, Appliance_Library!E187:E192, Appliance_Library!E193:E197, Appliance_Library!E198:E203, Appliance_Library!E204:E208, Appliance_Library!E209:E214, Appliance_Library!E215:E219, Appliance_Library!E220:E225, Appliance_Library!E226:E229, Appliance_Library!E230:E234, Appliance_Library!E235:E239, Appliance_Library!E240:E247, Appliance_Library!E248:E254, Appliance_Library!E255:E262, Appliance_Library!E263:E271, Appliance_Library!E272:E278, Appliance_Library!E279:E285, Appliance_Library!E286:E292, Appliance_Library!E293:E298, Appliance_Library!E299:E304, Appliance_Library!E305:E311, Appliance_Library!E312:E318 ), ROW()-ROW($E$4)+1)) -> 6 | C10: =IF(User_Inputs!$D$11="","", INDEX( CHOOSE(User_Inputs!$D$11, Appliance_Library!F10:F18, Appliance_Library!F19:F28, Appliance_Library!F29:F39, Appliance_Library!F40:F52, Appliance_Library!F53:F66, Appliance_Library!F67:F79, Appliance_Library!F80:F88, Appliance_Library!F89:F98, Appliance_Library!F99:F108, Appliance_Library!F109:F117, Appliance_Library!F118:F126, Appliance_Library!F127:F134, Appliance_Library!F135:F139, Appliance_Library!F140:F146, Appliance_Library!F147:F154, Appliance_Library!F155:F162, Appliance_Library!F163:F169, Appliance_Library!F170:F179, Appliance_Library!F180:F186, Appliance_Library!F187:F192, Appliance_Library!F193:F197, Appliance_Library!F198:F203, Appliance_Library!F204:F208, Appliance_Library!F209:F214, Appliance_Library!F215:F219, Appliance_Library!F220:F225, Appliance_Library!F226:F229, Appliance_Library!F230:F234, Appliance_Library!F235:F239, Appliance_Library!F240:F247, Appliance_Library!F248:F254, Appliance_Library!F255:F262, Appliance_Library!F263:F271, Appliance_Library!F272:F278, Appliance_Library!F279:F285, Appliance_Library!F286:F292, Appliance_Library!F293:F298, Appliance_Library!F299:F304, Appliance_Library!F305:F311, Appliance_Library!F312:F318 ), ROW()-ROW($F$4)+1)) -> 60 | D10: =IF(User_Inputs!$D$11="","", INDEX( CHOOSE(User_Inputs!$D$11, Appliance_Library!G10:G18, Appliance_Library!G19:G28, Appliance_Library!G29:G39, Appliance_Library!G40:G52, Appliance_Library!G53:G66, Appliance_Library!G67:G79, Appliance_Library!G80:G88, Appliance_Library!G89:G98, Appliance_Library!G99:G108, Appliance_Library!G109:G117, Appliance_Library!G118:G126, Appliance_Library!G127:G134, Appliance_Library!G135:G139, Appliance_Library!G140:G146, Appliance_Library!G147:G154, Appliance_Library!G155:G162, Appliance_Library!G163:G169, Appliance_Library!G170:G179, Appliance_Library!G180:G186, Appliance_Library!G187:G192, Appliance_Library!G193:G197, Appliance_Library!G198:G203, Appliance_Library!G204:G208, Appliance_Library!G209:G214, Appliance_Library!G215:G219, Appliance_Library!G220:G225, Appliance_Library!G226:G229, Appliance_Library!G230:G234, Appliance_Library!G235:G239, Appliance_Library!G240:G247, Appliance_Library!G248:G254, Appliance_Library!G255:G262, Appliance_Library!G263:G271, Appliance_Library!G272:G278, Appliance_Library!G279:G285, Appliance_Library!G286:G292, Appliance_Library!G293:G298, Appliance_Library!G299:G304, Appliance_Library!G305:G311, Appliance_Library!G312:G318 ), ROW()-ROW($G$4)+1)) -> 8 | E10: =IF(User_Inputs!$D$11="","", INDEX( CHOOSE(User_Inputs!$D$11, Appliance_Library!H10:H18, Appliance_Library!H19:H28, Appliance_Library!H29:H39, Appliance_Library!H40:H52, Appliance_Library!H53:H66, Appliance_Library!H67:H79, Appliance_Library!H80:H88, Appliance_Library!H89:H98, Appliance_Library!H99:H108, Appliance_Library!H109:H117, Appliance_Library!H118:H126, Appliance_Library!H127:H134, Appliance_Library!H135:H139, Appliance_Library!H140:H146, Appliance_Library!H147:H154, Appliance_Library!H155:H162, Appliance_Library!H163:H169, Appliance_Library!H170:H179, Appliance_Library!H180:H186, Appliance_Library!H187:H192, Appliance_Library!H193:H197, Appliance_Library!H198:H203, Appliance_Library!H204:H208, Appliance_Library!H209:H214, Appliance_Library!H215:H219, Appliance_Library!H220:H225, Appliance_Library!H226:H229, Appliance_Library!H230:H234, Appliance_Library!H235:H239, Appliance_Library!H240:H247, Appliance_Library!H248:H254, Appliance_Library!H255:H262, Appliance_Library!H263:H271, Appliance_Library!H272:H278, Appliance_Library!H279:H285, Appliance_Library!H286:H292, Appliance_Library!H293:H298, Appliance_Library!H299:H304, Appliance_Library!H305:H311, Appliance_Library!H312:H318 ), ROW()-ROW($H$4)+1)) -> 1 | F10: =IFERROR(C10*E10,0) -> 60 | G10: =IFERROR(F10*B10*D10/1000,0) -> 2.88 | H10: =G10*30 -> 86.4 | I10: =IFERROR(F10*B10,0) -> 360
A11: =IF(User_Inputs!$D$11="","", INDEX( CHOOSE(User_Inputs!$D$11, Appliance_Library!D11:D19, Appliance_Library!D20:D29, Appliance_Library!D30:D40, Appliance_Library!D41:D53, Appliance_Library!D54:D67, Appliance_Library!D68:D80, Appliance_Library!D81:D89, Appliance_Library!D90:D99, Appliance_Library!D100:D109, Appliance_Library!D110:D118, Appliance_Library!D119:D127, Appliance_Library!D128:D135, Appliance_Library!D136:D140, Appliance_Library!D141:D147, Appliance_Library!D148:D155, Appliance_Library!D156:D163, Appliance_Library!D164:D170, Appliance_Library!D171:D180, Appliance_Library!D181:D187, Appliance_Library!D188:D193, Appliance_Library!D194:D198, Appliance_Library!D199:D204, Appliance_Library!D205:D209, Appliance_Library!D210:D215, Appliance_Library!D216:D220, Appliance_Library!D221:D226, Appliance_Library!D227:D230, Appliance_Library!D231:D235, Appliance_Library!D236:D240, Appliance_Library!D241:D248, Appliance_Library!D249:D255, Appliance_Library!D256:D263, Appliance_Library!D264:D272, Appliance_Library!D273:D279, Appliance_Library!D280:D286, Appliance_Library!D287:D293, Appliance_Library!D294:D299, Appliance_Library!D300:D305, Appliance_Library!D306:D312, Appliance_Library!D313:D319 ), ROW()-ROW($D$4)+1)) -> Decoder | B11: =IF(User_Inputs!$D$11="","", INDEX( CHOOSE(User_Inputs!$D$11, Appliance_Library!E11:E19, Appliance_Library!E20:E29, Appliance_Library!E30:E40, Appliance_Library!E41:E53, Appliance_Library!E54:E67, Appliance_Library!E68:E80, Appliance_Library!E81:E89, Appliance_Library!E90:E99, Appliance_Library!E100:E109, Appliance_Library!E110:E118, Appliance_Library!E119:E127, Appliance_Library!E128:E135, Appliance_Library!E136:E140, Appliance_Library!E141:E147, Appliance_Library!E148:E155, Appliance_Library!E156:E163, Appliance_Library!E164:E170, Appliance_Library!E171:E180, Appliance_Library!E181:E187, Appliance_Library!E188:E193, Appliance_Library!E194:E198, Appliance_Library!E199:E204, Appliance_Library!E205:E209, Appliance_Library!E210:E215, Appliance_Library!E216:E220, Appliance_Library!E221:E226, Appliance_Library!E227:E230, Appliance_Library!E231:E235, Appliance_Library!E236:E240, Appliance_Library!E241:E248, Appliance_Library!E249:E255, Appliance_Library!E256:E263, Appliance_Library!E264:E272, Appliance_Library!E273:E279, Appliance_Library!E280:E286, Appliance_Library!E287:E293, Appliance_Library!E294:E299, Appliance_Library!E300:E305, Appliance_Library!E306:E312, Appliance_Library!E313:E319 ), ROW()-ROW($E$4)+1)) -> 2 | C11: =IF(User_Inputs!$D$11="","", INDEX( CHOOSE(User_Inputs!$D$11, Appliance_Library!F11:F19, Appliance_Library!F20:F29, Appliance_Library!F30:F40, Appliance_Library!F41:F53, Appliance_Library!F54:F67, Appliance_Library!F68:F80, Appliance_Library!F81:F89, Appliance_Library!F90:F99, Appliance_Library!F100:F109, Appliance_Library!F110:F118, Appliance_Library!F119:F127, Appliance_Library!F128:F135, Appliance_Library!F136:F140, Appliance_Library!F141:F147, Appliance_Library!F148:F155, Appliance_Library!F156:F163, Appliance_Library!F164:F170, Appliance_Library!F171:F180, Appliance_Library!F181:F187, Appliance_Library!F188:F193, Appliance_Library!F194:F198, Appliance_Library!F199:F204, Appliance_Library!F205:F209, Appliance_Library!F210:F215, Appliance_Library!F216:F220, Appliance_Library!F221:F226, Appliance_Library!F227:F230, Appliance_Library!F231:F235, Appliance_Library!F236:F240, Appliance_Library!F241:F248, Appliance_Library!F249:F255, Appliance_Library!F256:F263, Appliance_Library!F264:F272, Appliance_Library!F273:F279, Appliance_Library!F280:F286, Appliance_Library!F287:F293, Appliance_Library!F294:F299, Appliance_Library!F300:F305, Appliance_Library!F306:F312, Appliance_Library!F313:F319 ), ROW()-ROW($F$4)+1)) -> 25 | D11: =IF(User_Inputs!$D$11="","", INDEX( CHOOSE(User_Inputs!$D$11, Appliance_Library!G11:G19, Appliance_Library!G20:G29, Appliance_Library!G30:G40, Appliance_Library!G41:G53, Appliance_Library!G54:G67, Appliance_Library!G68:G80, Appliance_Library!G81:G89, Appliance_Library!G90:G99, Appliance_Library!G100:G109, Appliance_Library!G110:G118, Appliance_Library!G119:G127, Appliance_Library!G128:G135, Appliance_Library!G136:G140, Appliance_Library!G141:G147, Appliance_Library!G148:G155, Appliance_Library!G156:G163, Appliance_Library!G164:G170, Appliance_Library!G171:G180, Appliance_Library!G181:G187, Appliance_Library!G188:G193, Appliance_Library!G194:G198, Appliance_Library!G199:G204, Appliance_Library!G205:G209, Appliance_Library!G210:G215, Appliance_Library!G216:G220, Appliance_Library!G221:G226, Appliance_Library!G227:G230, Appliance_Library!G231:G235, Appliance_Library!G236:G240, Appliance_Library!G241:G248, Appliance_Library!G249:G255, Appliance_Library!G256:G263, Appliance_Library!G264:G272, Appliance_Library!G273:G279, Appliance_Library!G280:G286, Appliance_Library!G287:G293, Appliance_Library!G294:G299, Appliance_Library!G300:G305, Appliance_Library!G306:G312, Appliance_Library!G313:G319 ), ROW()-ROW($G$4)+1)) -> 6 | E11: =IF(User_Inputs!$D$11="","", INDEX( CHOOSE(User_Inputs!$D$11, Appliance_Library!H11:H19, Appliance_Library!H20:H29, Appliance_Library!H30:H40, Appliance_Library!H41:H53, Appliance_Library!H54:H67, Appliance_Library!H68:H80, Appliance_Library!H81:H89, Appliance_Library!H90:H99, Appliance_Library!H100:H109, Appliance_Library!H110:H118, Appliance_Library!H119:H127, Appliance_Library!H128:H135, Appliance_Library!H136:H140, Appliance_Library!H141:H147, Appliance_Library!H148:H155, Appliance_Library!H156:H163, Appliance_Library!H164:H170, Appliance_Library!H171:H180, Appliance_Library!H181:H187, Appliance_Library!H188:H193, Appliance_Library!H194:H198, Appliance_Library!H199:H204, Appliance_Library!H205:H209, Appliance_Library!H210:H215, Appliance_Library!H216:H220, Appliance_Library!H221:H226, Appliance_Library!H227:H230, Appliance_Library!H231:H235, Appliance_Library!H236:H240, Appliance_Library!H241:H248, Appliance_Library!H249:H255, Appliance_Library!H256:H263, Appliance_Library!H264:H272, Appliance_Library!H273:H279, Appliance_Library!H280:H286, Appliance_Library!H287:H293, Appliance_Library!H294:H299, Appliance_Library!H300:H305, Appliance_Library!H306:H312, Appliance_Library!H313:H319 ), ROW()-ROW($H$4)+1)) -> 1 | F11: =IFERROR(C11*E11,0) -> 25 | G11: =IFERROR(F11*B11*D11/1000,0) -> 0.3 | H11: =G11*30 -> 9 | I11: =IFERROR(F11*B11,0) -> 50
A12: =IF(User_Inputs!$D$11="","", INDEX( CHOOSE(User_Inputs!$D$11, Appliance_Library!D12:D20, Appliance_Library!D21:D30, Appliance_Library!D31:D41, Appliance_Library!D42:D54, Appliance_Library!D55:D68, Appliance_Library!D69:D81, Appliance_Library!D82:D90, Appliance_Library!D91:D100, Appliance_Library!D101:D110, Appliance_Library!D111:D119, Appliance_Library!D120:D128, Appliance_Library!D129:D136, Appliance_Library!D137:D141, Appliance_Library!D142:D148, Appliance_Library!D149:D156, Appliance_Library!D157:D164, Appliance_Library!D165:D171, Appliance_Library!D172:D181, Appliance_Library!D182:D188, Appliance_Library!D189:D194, Appliance_Library!D195:D199, Appliance_Library!D200:D205, Appliance_Library!D206:D210, Appliance_Library!D211:D216, Appliance_Library!D217:D221, Appliance_Library!D222:D227, Appliance_Library!D228:D231, Appliance_Library!D232:D236, Appliance_Library!D237:D241, Appliance_Library!D242:D249, Appliance_Library!D250:D256, Appliance_Library!D257:D264, Appliance_Library!D265:D273, Appliance_Library!D274:D280, Appliance_Library!D281:D287, Appliance_Library!D288:D294, Appliance_Library!D295:D300, Appliance_Library!D301:D306, Appliance_Library!D307:D313, Appliance_Library!D314:D320 ), ROW()-ROW($D$4)+1)) -> WiFi Router | B12: =IF(User_Inputs!$D$11="","", INDEX( CHOOSE(User_Inputs!$D$11, Appliance_Library!E12:E20, Appliance_Library!E21:E30, Appliance_Library!E31:E41, Appliance_Library!E42:E54, Appliance_Library!E55:E68, Appliance_Library!E69:E81, Appliance_Library!E82:E90, Appliance_Library!E91:E100, Appliance_Library!E101:E110, Appliance_Library!E111:E119, Appliance_Library!E120:E128, Appliance_Library!E129:E136, Appliance_Library!E137:E141, Appliance_Library!E142:E148, Appliance_Library!E149:E156, Appliance_Library!E157:E164, Appliance_Library!E165:E171, Appliance_Library!E172:E181, Appliance_Library!E182:E188, Appliance_Library!E189:E194, Appliance_Library!E195:E199, Appliance_Library!E200:E205, Appliance_Library!E206:E210, Appliance_Library!E211:E216, Appliance_Library!E217:E221, Appliance_Library!E222:E227, Appliance_Library!E228:E231, Appliance_Library!E232:E236, Appliance_Library!E237:E241, Appliance_Library!E242:E249, Appliance_Library!E250:E256, Appliance_Library!E257:E264, Appliance_Library!E265:E273, Appliance_Library!E274:E280, Appliance_Library!E281:E287, Appliance_Library!E288:E294, Appliance_Library!E295:E300, Appliance_Library!E301:E306, Appliance_Library!E307:E313, Appliance_Library!E314:E320 ), ROW()-ROW($E$4)+1)) -> 1 | C12: =IF(User_Inputs!$D$11="","", INDEX( CHOOSE(User_Inputs!$D$11, Appliance_Library!F12:F20, Appliance_Library!F21:F30, Appliance_Library!F31:F41, Appliance_Library!F42:F54, Appliance_Library!F55:F68, Appliance_Library!F69:F81, Appliance_Library!F82:F90, Appliance_Library!F91:F100, Appliance_Library!F101:F110, Appliance_Library!F111:F119, Appliance_Library!F120:F128, Appliance_Library!F129:F136, Appliance_Library!F137:F141, Appliance_Library!F142:F148, Appliance_Library!F149:F156, Appliance_Library!F157:F164, Appliance_Library!F165:F171, Appliance_Library!F172:F181, Appliance_Library!F182:F188, Appliance_Library!F189:F194, Appliance_Library!F195:F199, Appliance_Library!F200:F205, Appliance_Library!F206:F210, Appliance_Library!F211:F216, Appliance_Library!F217:F221, Appliance_Library!F222:F227, Appliance_Library!F228:F231, Appliance_Library!F232:F236, Appliance_Library!F237:F241, Appliance_Library!F242:F249, Appliance_Library!F250:F256, Appliance_Library!F257:F264, Appliance_Library!F265:F273, Appliance_Library!F274:F280, Appliance_Library!F281:F287, Appliance_Library!F288:F294, Appliance_Library!F295:F300, Appliance_Library!F301:F306, Appliance_Library!F307:F313, Appliance_Library!F314:F320 ), ROW()-ROW($F$4)+1)) -> 15 | D12: =IF(User_Inputs!$D$11="","", INDEX( CHOOSE(User_Inputs!$D$11, Appliance_Library!G12:G20, Appliance_Library!G21:G30, Appliance_Library!G31:G41, Appliance_Library!G42:G54, Appliance_Library!G55:G68, Appliance_Library!G69:G81, Appliance_Library!G82:G90, Appliance_Library!G91:G100, Appliance_Library!G101:G110, Appliance_Library!G111:G119, Appliance_Library!G120:G128, Appliance_Library!G129:G136, Appliance_Library!G137:G141, Appliance_Library!G142:G148, Appliance_Library!G149:G156, Appliance_Library!G157:G164, Appliance_Library!G165:G171, Appliance_Library!G172:G181, Appliance_Library!G182:G188, Appliance_Library!G189:G194, Appliance_Library!G195:G199, Appliance_Library!G200:G205, Appliance_Library!G206:G210, Appliance_Library!G211:G216, Appliance_Library!G217:G221, Appliance_Library!G222:G227, Appliance_Library!G228:G231, Appliance_Library!G232:G236, Appliance_Library!G237:G241, Appliance_Library!G242:G249, Appliance_Library!G250:G256, Appliance_Library!G257:G264, Appliance_Library!G265:G273, Appliance_Library!G274:G280, Appliance_Library!G281:G287, Appliance_Library!G288:G294, Appliance_Library!G295:G300, Appliance_Library!G301:G306, Appliance_Library!G307:G313, Appliance_Library!G314:G320 ), ROW()-ROW($G$4)+1)) -> 24 | E12: =IF(User_Inputs!$D$11="","", INDEX( CHOOSE(User_Inputs!$D$11, Appliance_Library!H12:H20, Appliance_Library!H21:H30, Appliance_Library!H31:H41, Appliance_Library!H42:H54, Appliance_Library!H55:H68, Appliance_Library!H69:H81, Appliance_Library!H82:H90, Appliance_Library!H91:H100, Appliance_Library!H101:H110, Appliance_Library!H111:H119, Appliance_Library!H120:H128, Appliance_Library!H129:H136, Appliance_Library!H137:H141, Appliance_Library!H142:H148, Appliance_Library!H149:H156, Appliance_Library!H157:H164, Appliance_Library!H165:H171, Appliance_Library!H172:H181, Appliance_Library!H182:H188, Appliance_Library!H189:H194, Appliance_Library!H195:H199, Appliance_Library!H200:H205, Appliance_Library!H206:H210, Appliance_Library!H211:H216, Appliance_Library!H217:H221, Appliance_Library!H222:H227, Appliance_Library!H228:H231, Appliance_Library!H232:H236, Appliance_Library!H237:H241, Appliance_Library!H242:H249, Appliance_Library!H250:H256, Appliance_Library!H257:H264, Appliance_Library!H265:H273, Appliance_Library!H274:H280, Appliance_Library!H281:H287, Appliance_Library!H288:H294, Appliance_Library!H295:H300, Appliance_Library!H301:H306, Appliance_Library!H307:H313, Appliance_Library!H314:H320 ), ROW()-ROW($H$4)+1)) -> 1 | F12: =IFERROR(C12*E12,0) -> 15 | G12: =IFERROR(F12*B12*D12/1000,0) -> 0.36 | H12: =G12*30 -> 10.8 | I12: =IFERROR(F12*B12,0) -> 15
A13: =IF(User_Inputs!$D$11="","", INDEX( CHOOSE(User_Inputs!$D$11, Appliance_Library!D13:D21, Appliance_Library!D22:D31, Appliance_Library!D32:D42, Appliance_Library!D43:D55, Appliance_Library!D56:D69, Appliance_Library!D70:D82, Appliance_Library!D83:D91, Appliance_Library!D92:D101, Appliance_Library!D102:D111, Appliance_Library!D112:D120, Appliance_Library!D121:D129, Appliance_Library!D130:D137, Appliance_Library!D138:D142, Appliance_Library!D143:D149, Appliance_Library!D150:D157, Appliance_Library!D158:D165, Appliance_Library!D166:D172, Appliance_Library!D173:D182, Appliance_Library!D183:D189, Appliance_Library!D190:D195, Appliance_Library!D196:D200, Appliance_Library!D201:D206, Appliance_Library!D207:D211, Appliance_Library!D212:D217, Appliance_Library!D218:D222, Appliance_Library!D223:D228, Appliance_Library!D229:D232, Appliance_Library!D233:D237, Appliance_Library!D238:D242, Appliance_Library!D243:D250, Appliance_Library!D251:D257, Appliance_Library!D258:D265, Appliance_Library!D266:D274, Appliance_Library!D275:D281, Appliance_Library!D282:D288, Appliance_Library!D289:D295, Appliance_Library!D296:D301, Appliance_Library!D302:D307, Appliance_Library!D308:D314, Appliance_Library!D315:D321 ), ROW()-ROW($D$4)+1)) -> Phone Chargers | B13: =IF(User_Inputs!$D$11="","", INDEX( CHOOSE(User_Inputs!$D$11, Appliance_Library!E13:E21, Appliance_Library!E22:E31, Appliance_Library!E32:E42, Appliance_Library!E43:E55, Appliance_Library!E56:E69, Appliance_Library!E70:E82, Appliance_Library!E83:E91, Appliance_Library!E92:E101, Appliance_Library!E102:E111, Appliance_Library!E112:E120, Appliance_Library!E121:E129, Appliance_Library!E130:E137, Appliance_Library!E138:E142, Appliance_Library!E143:E149, Appliance_Library!E150:E157, Appliance_Library!E158:E165, Appliance_Library!E166:E172, Appliance_Library!E173:E182, Appliance_Library!E183:E189, Appliance_Library!E190:E195, Appliance_Library!E196:E200, Appliance_Library!E201:E206, Appliance_Library!E207:E211, Appliance_Library!E212:E217, Appliance_Library!E218:E222, Appliance_Library!E223:E228, Appliance_Library!E229:E232, Appliance_Library!E233:E237, Appliance_Library!E238:E242, Appliance_Library!E243:E250, Appliance_Library!E251:E257, Appliance_Library!E258:E265, Appliance_Library!E266:E274, Appliance_Library!E275:E281, Appliance_Library!E282:E288, Appliance_Library!E289:E295, Appliance_Library!E296:E301, Appliance_Library!E302:E307, Appliance_Library!E308:E314, Appliance_Library!E315:E321 ), ROW()-ROW($E$4)+1)) -> 5 | C13: =IF(User_Inputs!$D$11="","", INDEX( CHOOSE(User_Inputs!$D$11, Appliance_Library!F13:F21, Appliance_Library!F22:F31, Appliance_Library!F32:F42, Appliance_Library!F43:F55, Appliance_Library!F56:F69, Appliance_Library!F70:F82, Appliance_Library!F83:F91, Appliance_Library!F92:F101, Appliance_Library!F102:F111, Appliance_Library!F112:F120, Appliance_Library!F121:F129, Appliance_Library!F130:F137, Appliance_Library!F138:F142, Appliance_Library!F143:F149, Appliance_Library!F150:F157, Appliance_Library!F158:F165, Appliance_Library!F166:F172, Appliance_Library!F173:F182, Appliance_Library!F183:F189, Appliance_Library!F190:F195, Appliance_Library!F196:F200, Appliance_Library!F201:F206, Appliance_Library!F207:F211, Appliance_Library!F212:F217, Appliance_Library!F218:F222, Appliance_Library!F223:F228, Appliance_Library!F229:F232, Appliance_Library!F233:F237, Appliance_Library!F238:F242, Appliance_Library!F243:F250, Appliance_Library!F251:F257, Appliance_Library!F258:F265, Appliance_Library!F266:F274, Appliance_Library!F275:F281, Appliance_Library!F282:F288, Appliance_Library!F289:F295, Appliance_Library!F296:F301, Appliance_Library!F302:F307, Appliance_Library!F308:F314, Appliance_Library!F315:F321 ), ROW()-ROW($F$4)+1)) -> 10 | D13: =IF(User_Inputs!$D$11="","", INDEX( CHOOSE(User_Inputs!$D$11, Appliance_Library!G13:G21, Appliance_Library!G22:G31, Appliance_Library!G32:G42, Appliance_Library!G43:G55, Appliance_Library!G56:G69, Appliance_Library!G70:G82, Appliance_Library!G83:G91, Appliance_Library!G92:G101, Appliance_Library!G102:G111, Appliance_Library!G112:G120, Appliance_Library!G121:G129, Appliance_Library!G130:G137, Appliance_Library!G138:G142, Appliance_Library!G143:G149, Appliance_Library!G150:G157, Appliance_Library!G158:G165, Appliance_Library!G166:G172, Appliance_Library!G173:G182, Appliance_Library!G183:G189, Appliance_Library!G190:G195, Appliance_Library!G196:G200, Appliance_Library!G201:G206, Appliance_Library!G207:G211, Appliance_Library!G212:G217, Appliance_Library!G218:G222, Appliance_Library!G223:G228, Appliance_Library!G229:G232, Appliance_Library!G233:G237, Appliance_Library!G238:G242, Appliance_Library!G243:G250, Appliance_Library!G251:G257, Appliance_Library!G258:G265, Appliance_Library!G266:G274, Appliance_Library!G275:G281, Appliance_Library!G282:G288, Appliance_Library!G289:G295, Appliance_Library!G296:G301, Appliance_Library!G302:G307, Appliance_Library!G308:G314, Appliance_Library!G315:G321 ), ROW()-ROW($G$4)+1)) -> 3 | E13: =IF(User_Inputs!$D$11="","", INDEX( CHOOSE(User_Inputs!$D$11, Appliance_Library!H13:H21, Appliance_Library!H22:H31, Appliance_Library!H32:H42, Appliance_Library!H43:H55, Appliance_Library!H56:H69, Appliance_Library!H70:H82, Appliance_Library!H83:H91, Appliance_Library!H92:H101, Appliance_Library!H102:H111, Appliance_Library!H112:H120, Appliance_Library!H121:H129, Appliance_Library!H130:H137, Appliance_Library!H138:H142, Appliance_Library!H143:H149, Appliance_Library!H150:H157, Appliance_Library!H158:H165, Appliance_Library!H166:H172, Appliance_Library!H173:H182, Appliance_Library!H183:H189, Appliance_Library!H190:H195, Appliance_Library!H196:H200, Appliance_Library!H201:H206, Appliance_Library!H207:H211, Appliance_Library!H212:H217, Appliance_Library!H218:H222, Appliance_Library!H223:H228, Appliance_Library!H229:H232, Appliance_Library!H233:H237, Appliance_Library!H238:H242, Appliance_Library!H243:H250, Appliance_Library!H251:H257, Appliance_Library!H258:H265, Appliance_Library!H266:H274, Appliance_Library!H275:H281, Appliance_Library!H282:H288, Appliance_Library!H289:H295, Appliance_Library!H296:H301, Appliance_Library!H302:H307, Appliance_Library!H308:H314, Appliance_Library!H315:H321 ), ROW()-ROW($H$4)+1)) -> 1 | F13: =IFERROR(C13*E13,0) -> 10 | G13: =IFERROR(F13*B13*D13/1000,0) -> 0.15 | H13: =G13*30 -> 4.5 | I13: =IFERROR(F13*B13,0) -> 50
A14: =IF(User_Inputs!$D$11="","", INDEX( CHOOSE(User_Inputs!$D$11, Appliance_Library!D14:D22, Appliance_Library!D23:D32, Appliance_Library!D33:D43, Appliance_Library!D44:D56, Appliance_Library!D57:D70, Appliance_Library!D71:D83, Appliance_Library!D84:D92, Appliance_Library!D93:D102, Appliance_Library!D103:D112, Appliance_Library!D113:D121, Appliance_Library!D122:D130, Appliance_Library!D131:D138, Appliance_Library!D139:D143, Appliance_Library!D144:D150, Appliance_Library!D151:D158, Appliance_Library!D159:D166, Appliance_Library!D167:D173, Appliance_Library!D174:D183, Appliance_Library!D184:D190, Appliance_Library!D191:D196, Appliance_Library!D197:D201, Appliance_Library!D202:D207, Appliance_Library!D208:D212, Appliance_Library!D213:D218, Appliance_Library!D219:D223, Appliance_Library!D224:D229, Appliance_Library!D230:D233, Appliance_Library!D234:D238, Appliance_Library!D239:D243, Appliance_Library!D244:D251, Appliance_Library!D252:D258, Appliance_Library!D259:D266, Appliance_Library!D267:D275, Appliance_Library!D276:D282, Appliance_Library!D283:D289, Appliance_Library!D290:D296, Appliance_Library!D297:D302, Appliance_Library!D303:D308, Appliance_Library!D309:D315, Appliance_Library!D316:D322 ), ROW()-ROW($D$4)+1)) -> Microwave | B14: =IF(User_Inputs!$D$11="","", INDEX( CHOOSE(User_Inputs!$D$11, Appliance_Library!E14:E22, Appliance_Library!E23:E32, Appliance_Library!E33:E43, Appliance_Library!E44:E56, Appliance_Library!E57:E70, Appliance_Library!E71:E83, Appliance_Library!E84:E92, Appliance_Library!E93:E102, Appliance_Library!E103:E112, Appliance_Library!E113:E121, Appliance_Library!E122:E130, Appliance_Library!E131:E138, Appliance_Library!E139:E143, Appliance_Library!E144:E150, Appliance_Library!E151:E158, Appliance_Library!E159:E166, Appliance_Library!E167:E173, Appliance_Library!E174:E183, Appliance_Library!E184:E190, Appliance_Library!E191:E196, Appliance_Library!E197:E201, Appliance_Library!E202:E207, Appliance_Library!E208:E212, Appliance_Library!E213:E218, Appliance_Library!E219:E223, Appliance_Library!E224:E229, Appliance_Library!E230:E233, Appliance_Library!E234:E238, Appliance_Library!E239:E243, Appliance_Library!E244:E251, Appliance_Library!E252:E258, Appliance_Library!E259:E266, Appliance_Library!E267:E275, Appliance_Library!E276:E282, Appliance_Library!E283:E289, Appliance_Library!E290:E296, Appliance_Library!E297:E302, Appliance_Library!E303:E308, Appliance_Library!E309:E315, Appliance_Library!E316:E322 ), ROW()-ROW($E$4)+1)) -> 1 | C14: =IF(User_Inputs!$D$11="","", INDEX( CHOOSE(User_Inputs!$D$11, Appliance_Library!F14:F22, Appliance_Library!F23:F32, Appliance_Library!F33:F43, Appliance_Library!F44:F56, Appliance_Library!F57:F70, Appliance_Library!F71:F83, Appliance_Library!F84:F92, Appliance_Library!F93:F102, Appliance_Library!F103:F112, Appliance_Library!F113:F121, Appliance_Library!F122:F130, Appliance_Library!F131:F138, Appliance_Library!F139:F143, Appliance_Library!F144:F150, Appliance_Library!F151:F158, Appliance_Library!F159:F166, Appliance_Library!F167:F173, Appliance_Library!F174:F183, Appliance_Library!F184:F190, Appliance_Library!F191:F196, Appliance_Library!F197:F201, Appliance_Library!F202:F207, Appliance_Library!F208:F212, Appliance_Library!F213:F218, Appliance_Library!F219:F223, Appliance_Library!F224:F229, Appliance_Library!F230:F233, Appliance_Library!F234:F238, Appliance_Library!F239:F243, Appliance_Library!F244:F251, Appliance_Library!F252:F258, Appliance_Library!F259:F266, Appliance_Library!F267:F275, Appliance_Library!F276:F282, Appliance_Library!F283:F289, Appliance_Library!F290:F296, Appliance_Library!F297:F302, Appliance_Library!F303:F308, Appliance_Library!F309:F315, Appliance_Library!F316:F322 ), ROW()-ROW($F$4)+1)) -> 1200 | D14: =IF(User_Inputs!$D$11="","", INDEX( CHOOSE(User_Inputs!$D$11, Appliance_Library!G14:G22, Appliance_Library!G23:G32, Appliance_Library!G33:G43, Appliance_Library!G44:G56, Appliance_Library!G57:G70, Appliance_Library!G71:G83, Appliance_Library!G84:G92, Appliance_Library!G93:G102, Appliance_Library!G103:G112, Appliance_Library!G113:G121, Appliance_Library!G122:G130, Appliance_Library!G131:G138, Appliance_Library!G139:G143, Appliance_Library!G144:G150, Appliance_Library!G151:G158, Appliance_Library!G159:G166, Appliance_Library!G167:G173, Appliance_Library!G174:G183, Appliance_Library!G184:G190, Appliance_Library!G191:G196, Appliance_Library!G197:G201, Appliance_Library!G202:G207, Appliance_Library!G208:G212, Appliance_Library!G213:G218, Appliance_Library!G219:G223, Appliance_Library!G224:G229, Appliance_Library!G230:G233, Appliance_Library!G234:G238, Appliance_Library!G239:G243, Appliance_Library!G244:G251, Appliance_Library!G252:G258, Appliance_Library!G259:G266, Appliance_Library!G267:G275, Appliance_Library!G276:G282, Appliance_Library!G283:G289, Appliance_Library!G290:G296, Appliance_Library!G297:G302, Appliance_Library!G303:G308, Appliance_Library!G309:G315, Appliance_Library!G316:G322 ), ROW()-ROW($G$4)+1)) -> 0.4 | E14: =IF(User_Inputs!$D$11="","", INDEX( CHOOSE(User_Inputs!$D$11, Appliance_Library!H14:H22, Appliance_Library!H23:H32, Appliance_Library!H33:H43, Appliance_Library!H44:H56, Appliance_Library!H57:H70, Appliance_Library!H71:H83, Appliance_Library!H84:H92, Appliance_Library!H93:H102, Appliance_Library!H103:H112, Appliance_Library!H113:H121, Appliance_Library!H122:H130, Appliance_Library!H131:H138, Appliance_Library!H139:H143, Appliance_Library!H144:H150, Appliance_Library!H151:H158, Appliance_Library!H159:H166, Appliance_Library!H167:H173, Appliance_Library!H174:H183, Appliance_Library!H184:H190, Appliance_Library!H191:H196, Appliance_Library!H197:H201, Appliance_Library!H202:H207, Appliance_Library!H208:H212, Appliance_Library!H213:H218, Appliance_Library!H219:H223, Appliance_Library!H224:H229, Appliance_Library!H230:H233, Appliance_Library!H234:H238, Appliance_Library!H239:H243, Appliance_Library!H244:H251, Appliance_Library!H252:H258, Appliance_Library!H259:H266, Appliance_Library!H267:H275, Appliance_Library!H276:H282, Appliance_Library!H283:H289, Appliance_Library!H290:H296, Appliance_Library!H297:H302, Appliance_Library!H303:H308, Appliance_Library!H309:H315, Appliance_Library!H316:H322 ), ROW()-ROW($H$4)+1)) -> 1 | F14: =IFERROR(C14*E14,0) -> 1200 | G14: =IFERROR(F14*B14*D14/1000,0) -> 0.48 | H14: =G14*30 -> 14.4 | I14: =IFERROR(F14*B14,0) -> 1200
A15: =IF(User_Inputs!$D$11="","", INDEX( CHOOSE(User_Inputs!$D$11, Appliance_Library!D15:D23, Appliance_Library!D24:D33, Appliance_Library!D34:D44, Appliance_Library!D45:D57, Appliance_Library!D58:D71, Appliance_Library!D72:D84, Appliance_Library!D85:D93, Appliance_Library!D94:D103, Appliance_Library!D104:D113, Appliance_Library!D114:D122, Appliance_Library!D123:D131, Appliance_Library!D132:D139, Appliance_Library!D140:D144, Appliance_Library!D145:D151, Appliance_Library!D152:D159, Appliance_Library!D160:D167, Appliance_Library!D168:D174, Appliance_Library!D175:D184, Appliance_Library!D185:D191, Appliance_Library!D192:D197, Appliance_Library!D198:D202, Appliance_Library!D203:D208, Appliance_Library!D209:D213, Appliance_Library!D214:D219, Appliance_Library!D220:D224, Appliance_Library!D225:D230, Appliance_Library!D231:D234, Appliance_Library!D235:D239, Appliance_Library!D240:D244, Appliance_Library!D245:D252, Appliance_Library!D253:D259, Appliance_Library!D260:D267, Appliance_Library!D268:D276, Appliance_Library!D277:D283, Appliance_Library!D284:D290, Appliance_Library!D291:D297, Appliance_Library!D298:D303, Appliance_Library!D304:D309, Appliance_Library!D310:D316, Appliance_Library!D317:D323 ), ROW()-ROW($D$4)+1)) -> #REF! | B15: =IF(User_Inputs!$D$11="","", INDEX( CHOOSE(User_Inputs!$D$11, Appliance_Library!E15:E23, Appliance_Library!E24:E33, Appliance_Library!E34:E44, Appliance_Library!E45:E57, Appliance_Library!E58:E71, Appliance_Library!E72:E84, Appliance_Library!E85:E93, Appliance_Library!E94:E103, Appliance_Library!E104:E113, Appliance_Library!E114:E122, Appliance_Library!E123:E131, Appliance_Library!E132:E139, Appliance_Library!E140:E144, Appliance_Library!E145:E151, Appliance_Library!E152:E159, Appliance_Library!E160:E167, Appliance_Library!E168:E174, Appliance_Library!E175:E184, Appliance_Library!E185:E191, Appliance_Library!E192:E197, Appliance_Library!E198:E202, Appliance_Library!E203:E208, Appliance_Library!E209:E213, Appliance_Library!E214:E219, Appliance_Library!E220:E224, Appliance_Library!E225:E230, Appliance_Library!E231:E234, Appliance_Library!E235:E239, Appliance_Library!E240:E244, Appliance_Library!E245:E252, Appliance_Library!E253:E259, Appliance_Library!E260:E267, Appliance_Library!E268:E276, Appliance_Library!E277:E283, Appliance_Library!E284:E290, Appliance_Library!E291:E297, Appliance_Library!E298:E303, Appliance_Library!E304:E309, Appliance_Library!E310:E316, Appliance_Library!E317:E323 ), ROW()-ROW($E$4)+1)) -> #REF! | C15: =IF(User_Inputs!$D$11="","", INDEX( CHOOSE(User_Inputs!$D$11, Appliance_Library!F15:F23, Appliance_Library!F24:F33, Appliance_Library!F34:F44, Appliance_Library!F45:F57, Appliance_Library!F58:F71, Appliance_Library!F72:F84, Appliance_Library!F85:F93, Appliance_Library!F94:F103, Appliance_Library!F104:F113, Appliance_Library!F114:F122, Appliance_Library!F123:F131, Appliance_Library!F132:F139, Appliance_Library!F140:F144, Appliance_Library!F145:F151, Appliance_Library!F152:F159, Appliance_Library!F160:F167, Appliance_Library!F168:F174, Appliance_Library!F175:F184, Appliance_Library!F185:F191, Appliance_Library!F192:F197, Appliance_Library!F198:F202, Appliance_Library!F203:F208, Appliance_Library!F209:F213, Appliance_Library!F214:F219, Appliance_Library!F220:F224, Appliance_Library!F225:F230, Appliance_Library!F231:F234, Appliance_Library!F235:F239, Appliance_Library!F240:F244, Appliance_Library!F245:F252, Appliance_Library!F253:F259, Appliance_Library!F260:F267, Appliance_Library!F268:F276, Appliance_Library!F277:F283, Appliance_Library!F284:F290, Appliance_Library!F291:F297, Appliance_Library!F298:F303, Appliance_Library!F304:F309, Appliance_Library!F310:F316, Appliance_Library!F317:F323 ), ROW()-ROW($F$4)+1)) -> #REF! | D15: =IF(User_Inputs!$D$11="","", INDEX( CHOOSE(User_Inputs!$D$11, Appliance_Library!G15:G23, Appliance_Library!G24:G33, Appliance_Library!G34:G44, Appliance_Library!G45:G57, Appliance_Library!G58:G71, Appliance_Library!G72:G84, Appliance_Library!G85:G93, Appliance_Library!G94:G103, Appliance_Library!G104:G113, Appliance_Library!G114:G122, Appliance_Library!G123:G131, Appliance_Library!G132:G139, Appliance_Library!G140:G144, Appliance_Library!G145:G151, Appliance_Library!G152:G159, Appliance_Library!G160:G167, Appliance_Library!G168:G174, Appliance_Library!G175:G184, Appliance_Library!G185:G191, Appliance_Library!G192:G197, Appliance_Library!G198:G202, Appliance_Library!G203:G208, Appliance_Library!G209:G213, Appliance_Library!G214:G219, Appliance_Library!G220:G224, Appliance_Library!G225:G230, Appliance_Library!G231:G234, Appliance_Library!G235:G239, Appliance_Library!G240:G244, Appliance_Library!G245:G252, Appliance_Library!G253:G259, Appliance_Library!G260:G267, Appliance_Library!G268:G276, Appliance_Library!G277:G283, Appliance_Library!G284:G290, Appliance_Library!G291:G297, Appliance_Library!G298:G303, Appliance_Library!G304:G309, Appliance_Library!G310:G316, Appliance_Library!G317:G323 ), ROW()-ROW($G$4)+1)) -> #REF! | E15: =IF(User_Inputs!$D$11="","", INDEX( CHOOSE(User_Inputs!$D$11, Appliance_Library!H15:H23, Appliance_Library!H24:H33, Appliance_Library!H34:H44, Appliance_Library!H45:H57, Appliance_Library!H58:H71, Appliance_Library!H72:H84, Appliance_Library!H85:H93, Appliance_Library!H94:H103, Appliance_Library!H104:H113, Appliance_Library!H114:H122, Appliance_Library!H123:H131, Appliance_Library!H132:H139, Appliance_Library!H140:H144, Appliance_Library!H145:H151, Appliance_Library!H152:H159, Appliance_Library!H160:H167, Appliance_Library!H168:H174, Appliance_Library!H175:H184, Appliance_Library!H185:H191, Appliance_Library!H192:H197, Appliance_Library!H198:H202, Appliance_Library!H203:H208, Appliance_Library!H209:H213, Appliance_Library!H214:H219, Appliance_Library!H220:H224, Appliance_Library!H225:H230, Appliance_Library!H231:H234, Appliance_Library!H235:H239, Appliance_Library!H240:H244, Appliance_Library!H245:H252, Appliance_Library!H253:H259, Appliance_Library!H260:H267, Appliance_Library!H268:H276, Appliance_Library!H277:H283, Appliance_Library!H284:H290, Appliance_Library!H291:H297, Appliance_Library!H298:H303, Appliance_Library!H304:H309, Appliance_Library!H310:H316, Appliance_Library!H317:H323 ), ROW()-ROW($H$4)+1)) -> #REF! | F15: =IFERROR(C15*E15,0) -> 0 | G15: =IFERROR(F15*B15*D15/1000,0) -> 0 | H15: =G15*30 -> 0 | I15: =IFERROR(F15*B15,0) -> 0
A16: =IF(User_Inputs!$D$11="","", INDEX( CHOOSE(User_Inputs!$D$11, Appliance_Library!D16:D24, Appliance_Library!D25:D34, Appliance_Library!D35:D45, Appliance_Library!D46:D58, Appliance_Library!D59:D72, Appliance_Library!D73:D85, Appliance_Library!D86:D94, Appliance_Library!D95:D104, Appliance_Library!D105:D114, Appliance_Library!D115:D123, Appliance_Library!D124:D132, Appliance_Library!D133:D140, Appliance_Library!D141:D145, Appliance_Library!D146:D152, Appliance_Library!D153:D160, Appliance_Library!D161:D168, Appliance_Library!D169:D175, Appliance_Library!D176:D185, Appliance_Library!D186:D192, Appliance_Library!D193:D198, Appliance_Library!D199:D203, Appliance_Library!D204:D209, Appliance_Library!D210:D214, Appliance_Library!D215:D220, Appliance_Library!D221:D225, Appliance_Library!D226:D231, Appliance_Library!D232:D235, Appliance_Library!D236:D240, Appliance_Library!D241:D245, Appliance_Library!D246:D253, Appliance_Library!D254:D260, Appliance_Library!D261:D268, Appliance_Library!D269:D277, Appliance_Library!D278:D284, Appliance_Library!D285:D291, Appliance_Library!D292:D298, Appliance_Library!D299:D304, Appliance_Library!D305:D310, Appliance_Library!D311:D317, Appliance_Library!D318:D324 ), ROW()-ROW($D$4)+1)) -> #REF! | B16: =IF(User_Inputs!$D$11="","", INDEX( CHOOSE(User_Inputs!$D$11, Appliance_Library!E16:E24, Appliance_Library!E25:E34, Appliance_Library!E35:E45, Appliance_Library!E46:E58, Appliance_Library!E59:E72, Appliance_Library!E73:E85, Appliance_Library!E86:E94, Appliance_Library!E95:E104, Appliance_Library!E105:E114, Appliance_Library!E115:E123, Appliance_Library!E124:E132, Appliance_Library!E133:E140, Appliance_Library!E141:E145, Appliance_Library!E146:E152, Appliance_Library!E153:E160, Appliance_Library!E161:E168, Appliance_Library!E169:E175, Appliance_Library!E176:E185, Appliance_Library!E186:E192, Appliance_Library!E193:E198, Appliance_Library!E199:E203, Appliance_Library!E204:E209, Appliance_Library!E210:E214, Appliance_Library!E215:E220, Appliance_Library!E221:E225, Appliance_Library!E226:E231, Appliance_Library!E232:E235, Appliance_Library!E236:E240, Appliance_Library!E241:E245, Appliance_Library!E246:E253, Appliance_Library!E254:E260, Appliance_Library!E261:E268, Appliance_Library!E269:E277, Appliance_Library!E278:E284, Appliance_Library!E285:E291, Appliance_Library!E292:E298, Appliance_Library!E299:E304, Appliance_Library!E305:E310, Appliance_Library!E311:E317, Appliance_Library!E318:E324 ), ROW()-ROW($E$4)+1)) -> #REF! | C16: =IF(User_Inputs!$D$11="","", INDEX( CHOOSE(User_Inputs!$D$11, Appliance_Library!F16:F24, Appliance_Library!F25:F34, Appliance_Library!F35:F45, Appliance_Library!F46:F58, Appliance_Library!F59:F72, Appliance_Library!F73:F85, Appliance_Library!F86:F94, Appliance_Library!F95:F104, Appliance_Library!F105:F114, Appliance_Library!F115:F123, Appliance_Library!F124:F132, Appliance_Library!F133:F140, Appliance_Library!F141:F145, Appliance_Library!F146:F152, Appliance_Library!F153:F160, Appliance_Library!F161:F168, Appliance_Library!F169:F175, Appliance_Library!F176:F185, Appliance_Library!F186:F192, Appliance_Library!F193:F198, Appliance_Library!F199:F203, Appliance_Library!F204:F209, Appliance_Library!F210:F214, Appliance_Library!F215:F220, Appliance_Library!F221:F225, Appliance_Library!F226:F231, Appliance_Library!F232:F235, Appliance_Library!F236:F240, Appliance_Library!F241:F245, Appliance_Library!F246:F253, Appliance_Library!F254:F260, Appliance_Library!F261:F268, Appliance_Library!F269:F277, Appliance_Library!F278:F284, Appliance_Library!F285:F291, Appliance_Library!F292:F298, Appliance_Library!F299:F304, Appliance_Library!F305:F310, Appliance_Library!F311:F317, Appliance_Library!F318:F324 ), ROW()-ROW($F$4)+1)) -> #REF! | D16: =IF(User_Inputs!$D$11="","", INDEX( CHOOSE(User_Inputs!$D$11, Appliance_Library!G16:G24, Appliance_Library!G25:G34, Appliance_Library!G35:G45, Appliance_Library!G46:G58, Appliance_Library!G59:G72, Appliance_Library!G73:G85, Appliance_Library!G86:G94, Appliance_Library!G95:G104, Appliance_Library!G105:G114, Appliance_Library!G115:G123, Appliance_Library!G124:G132, Appliance_Library!G133:G140, Appliance_Library!G141:G145, Appliance_Library!G146:G152, Appliance_Library!G153:G160, Appliance_Library!G161:G168, Appliance_Library!G169:G175, Appliance_Library!G176:G185, Appliance_Library!G186:G192, Appliance_Library!G193:G198, Appliance_Library!G199:G203, Appliance_Library!G204:G209, Appliance_Library!G210:G214, Appliance_Library!G215:G220, Appliance_Library!G221:G225, Appliance_Library!G226:G231, Appliance_Library!G232:G235, Appliance_Library!G236:G240, Appliance_Library!G241:G245, Appliance_Library!G246:G253, Appliance_Library!G254:G260, Appliance_Library!G261:G268, Appliance_Library!G269:G277, Appliance_Library!G278:G284, Appliance_Library!G285:G291, Appliance_Library!G292:G298, Appliance_Library!G299:G304, Appliance_Library!G305:G310, Appliance_Library!G311:G317, Appliance_Library!G318:G324 ), ROW()-ROW($G$4)+1)) -> #REF! | E16: =IF(User_Inputs!$D$11="","", INDEX( CHOOSE(User_Inputs!$D$11, Appliance_Library!H16:H24, Appliance_Library!H25:H34, Appliance_Library!H35:H45, Appliance_Library!H46:H58, Appliance_Library!H59:H72, Appliance_Library!H73:H85, Appliance_Library!H86:H94, Appliance_Library!H95:H104, Appliance_Library!H105:H114, Appliance_Library!H115:H123, Appliance_Library!H124:H132, Appliance_Library!H133:H140, Appliance_Library!H141:H145, Appliance_Library!H146:H152, Appliance_Library!H153:H160, Appliance_Library!H161:H168, Appliance_Library!H169:H175, Appliance_Library!H176:H185, Appliance_Library!H186:H192, Appliance_Library!H193:H198, Appliance_Library!H199:H203, Appliance_Library!H204:H209, Appliance_Library!H210:H214, Appliance_Library!H215:H220, Appliance_Library!H221:H225, Appliance_Library!H226:H231, Appliance_Library!H232:H235, Appliance_Library!H236:H240, Appliance_Library!H241:H245, Appliance_Library!H246:H253, Appliance_Library!H254:H260, Appliance_Library!H261:H268, Appliance_Library!H269:H277, Appliance_Library!H278:H284, Appliance_Library!H285:H291, Appliance_Library!H292:H298, Appliance_Library!H299:H304, Appliance_Library!H305:H310, Appliance_Library!H311:H317, Appliance_Library!H318:H324 ), ROW()-ROW($H$4)+1)) -> #REF! | F16: =IFERROR(C16*E16,0) -> 0 | G16: =IFERROR(F16*B16*D16/1000,0) -> 0 | H16: =G16*30 -> 0 | I16: =IFERROR(F16*B16,0) -> 0
A17: =IF(User_Inputs!$D$11="","", INDEX( CHOOSE(User_Inputs!$D$11, Appliance_Library!D17:D25, Appliance_Library!D26:D35, Appliance_Library!D36:D46, Appliance_Library!D47:D59, Appliance_Library!D60:D73, Appliance_Library!D74:D86, Appliance_Library!D87:D95, Appliance_Library!D96:D105, Appliance_Library!D106:D115, Appliance_Library!D116:D124, Appliance_Library!D125:D133, Appliance_Library!D134:D141, Appliance_Library!D142:D146, Appliance_Library!D147:D153, Appliance_Library!D154:D161, Appliance_Library!D162:D169, Appliance_Library!D170:D176, Appliance_Library!D177:D186, Appliance_Library!D187:D193, Appliance_Library!D194:D199, Appliance_Library!D200:D204, Appliance_Library!D205:D210, Appliance_Library!D211:D215, Appliance_Library!D216:D221, Appliance_Library!D222:D226, Appliance_Library!D227:D232, Appliance_Library!D233:D236, Appliance_Library!D237:D241, Appliance_Library!D242:D246, Appliance_Library!D247:D254, Appliance_Library!D255:D261, Appliance_Library!D262:D269, Appliance_Library!D270:D278, Appliance_Library!D279:D285, Appliance_Library!D286:D292, Appliance_Library!D293:D299, Appliance_Library!D300:D305, Appliance_Library!D306:D311, Appliance_Library!D312:D318, Appliance_Library!D319:D325 ), ROW()-ROW($D$4)+1)) -> #REF! | B17: =IF(User_Inputs!$D$11="","", INDEX( CHOOSE(User_Inputs!$D$11, Appliance_Library!E17:E25, Appliance_Library!E26:E35, Appliance_Library!E36:E46, Appliance_Library!E47:E59, Appliance_Library!E60:E73, Appliance_Library!E74:E86, Appliance_Library!E87:E95, Appliance_Library!E96:E105, Appliance_Library!E106:E115, Appliance_Library!E116:E124, Appliance_Library!E125:E133, Appliance_Library!E134:E141, Appliance_Library!E142:E146, Appliance_Library!E147:E153, Appliance_Library!E154:E161, Appliance_Library!E162:E169, Appliance_Library!E170:E176, Appliance_Library!E177:E186, Appliance_Library!E187:E193, Appliance_Library!E194:E199, Appliance_Library!E200:E204, Appliance_Library!E205:E210, Appliance_Library!E211:E215, Appliance_Library!E216:E221, Appliance_Library!E222:E226, Appliance_Library!E227:E232, Appliance_Library!E233:E236, Appliance_Library!E237:E241, Appliance_Library!E242:E246, Appliance_Library!E247:E254, Appliance_Library!E255:E261, Appliance_Library!E262:E269, Appliance_Library!E270:E278, Appliance_Library!E279:E285, Appliance_Library!E286:E292, Appliance_Library!E293:E299, Appliance_Library!E300:E305, Appliance_Library!E306:E311, Appliance_Library!E312:E318, Appliance_Library!E319:E325 ), ROW()-ROW($E$4)+1)) -> #REF! | C17: =IF(User_Inputs!$D$11="","", INDEX( CHOOSE(User_Inputs!$D$11, Appliance_Library!F17:F25, Appliance_Library!F26:F35, Appliance_Library!F36:F46, Appliance_Library!F47:F59, Appliance_Library!F60:F73, Appliance_Library!F74:F86, Appliance_Library!F87:F95, Appliance_Library!F96:F105, Appliance_Library!F106:F115, Appliance_Library!F116:F124, Appliance_Library!F125:F133, Appliance_Library!F134:F141, Appliance_Library!F142:F146, Appliance_Library!F147:F153, Appliance_Library!F154:F161, Appliance_Library!F162:F169, Appliance_Library!F170:F176, Appliance_Library!F177:F186, Appliance_Library!F187:F193, Appliance_Library!F194:F199, Appliance_Library!F200:F204, Appliance_Library!F205:F210, Appliance_Library!F211:F215, Appliance_Library!F216:F221, Appliance_Library!F222:F226, Appliance_Library!F227:F232, Appliance_Library!F233:F236, Appliance_Library!F237:F241, Appliance_Library!F242:F246, Appliance_Library!F247:F254, Appliance_Library!F255:F261, Appliance_Library!F262:F269, Appliance_Library!F270:F278, Appliance_Library!F279:F285, Appliance_Library!F286:F292, Appliance_Library!F293:F299, Appliance_Library!F300:F305, Appliance_Library!F306:F311, Appliance_Library!F312:F318, Appliance_Library!F319:F325 ), ROW()-ROW($F$4)+1)) -> #REF! | D17: =IF(User_Inputs!$D$11="","", INDEX( CHOOSE(User_Inputs!$D$11, Appliance_Library!G17:G25, Appliance_Library!G26:G35, Appliance_Library!G36:G46, Appliance_Library!G47:G59, Appliance_Library!G60:G73, Appliance_Library!G74:G86, Appliance_Library!G87:G95, Appliance_Library!G96:G105, Appliance_Library!G106:G115, Appliance_Library!G116:G124, Appliance_Library!G125:G133, Appliance_Library!G134:G141, Appliance_Library!G142:G146, Appliance_Library!G147:G153, Appliance_Library!G154:G161, Appliance_Library!G162:G169, Appliance_Library!G170:G176, Appliance_Library!G177:G186, Appliance_Library!G187:G193, Appliance_Library!G194:G199, Appliance_Library!G200:G204, Appliance_Library!G205:G210, Appliance_Library!G211:G215, Appliance_Library!G216:G221, Appliance_Library!G222:G226, Appliance_Library!G227:G232, Appliance_Library!G233:G236, Appliance_Library!G237:G241, Appliance_Library!G242:G246, Appliance_Library!G247:G254, Appliance_Library!G255:G261, Appliance_Library!G262:G269, Appliance_Library!G270:G278, Appliance_Library!G279:G285, Appliance_Library!G286:G292, Appliance_Library!G293:G299, Appliance_Library!G300:G305, Appliance_Library!G306:G311, Appliance_Library!G312:G318, Appliance_Library!G319:G325 ), ROW()-ROW($G$4)+1)) -> #REF! | E17: =IF(User_Inputs!$D$11="","", INDEX( CHOOSE(User_Inputs!$D$11, Appliance_Library!H17:H25, Appliance_Library!H26:H35, Appliance_Library!H36:H46, Appliance_Library!H47:H59, Appliance_Library!H60:H73, Appliance_Library!H74:H86, Appliance_Library!H87:H95, Appliance_Library!H96:H105, Appliance_Library!H106:H115, Appliance_Library!H116:H124, Appliance_Library!H125:H133, Appliance_Library!H134:H141, Appliance_Library!H142:H146, Appliance_Library!H147:H153, Appliance_Library!H154:H161, Appliance_Library!H162:H169, Appliance_Library!H170:H176, Appliance_Library!H177:H186, Appliance_Library!H187:H193, Appliance_Library!H194:H199, Appliance_Library!H200:H204, Appliance_Library!H205:H210, Appliance_Library!H211:H215, Appliance_Library!H216:H221, Appliance_Library!H222:H226, Appliance_Library!H227:H232, Appliance_Library!H233:H236, Appliance_Library!H237:H241, Appliance_Library!H242:H246, Appliance_Library!H247:H254, Appliance_Library!H255:H261, Appliance_Library!H262:H269, Appliance_Library!H270:H278, Appliance_Library!H279:H285, Appliance_Library!H286:H292, Appliance_Library!H293:H299, Appliance_Library!H300:H305, Appliance_Library!H306:H311, Appliance_Library!H312:H318, Appliance_Library!H319:H325 ), ROW()-ROW($H$4)+1)) -> #REF! | F17: =IFERROR(C17*E17,0) -> 0 | G17: =IFERROR(F17*B17*D17/1000,0) -> 0 | H17: =G17*30 -> 0 | I17: =IFERROR(F17*B17,0) -> 0
A18: =IF(User_Inputs!$D$11="","", INDEX( CHOOSE(User_Inputs!$D$11, Appliance_Library!D18:D26, Appliance_Library!D27:D36, Appliance_Library!D37:D47, Appliance_Library!D48:D60, Appliance_Library!D61:D74, Appliance_Library!D75:D87, Appliance_Library!D88:D96, Appliance_Library!D97:D106, Appliance_Library!D107:D116, Appliance_Library!D117:D125, Appliance_Library!D126:D134, Appliance_Library!D135:D142, Appliance_Library!D143:D147, Appliance_Library!D148:D154, Appliance_Library!D155:D162, Appliance_Library!D163:D170, Appliance_Library!D171:D177, Appliance_Library!D178:D187, Appliance_Library!D188:D194, Appliance_Library!D195:D200, Appliance_Library!D201:D205, Appliance_Library!D206:D211, Appliance_Library!D212:D216, Appliance_Library!D217:D222, Appliance_Library!D223:D227, Appliance_Library!D228:D233, Appliance_Library!D234:D237, Appliance_Library!D238:D242, Appliance_Library!D243:D247, Appliance_Library!D248:D255, Appliance_Library!D256:D262, Appliance_Library!D263:D270, Appliance_Library!D271:D279, Appliance_Library!D280:D286, Appliance_Library!D287:D293, Appliance_Library!D294:D300, Appliance_Library!D301:D306, Appliance_Library!D307:D312, Appliance_Library!D313:D319, Appliance_Library!D320:D326 ), ROW()-ROW($D$4)+1)) -> #REF! | B18: =IF(User_Inputs!$D$11="","", INDEX( CHOOSE(User_Inputs!$D$11, Appliance_Library!E18:E26, Appliance_Library!E27:E36, Appliance_Library!E37:E47, Appliance_Library!E48:E60, Appliance_Library!E61:E74, Appliance_Library!E75:E87, Appliance_Library!E88:E96, Appliance_Library!E97:E106, Appliance_Library!E107:E116, Appliance_Library!E117:E125, Appliance_Library!E126:E134, Appliance_Library!E135:E142, Appliance_Library!E143:E147, Appliance_Library!E148:E154, Appliance_Library!E155:E162, Appliance_Library!E163:E170, Appliance_Library!E171:E177, Appliance_Library!E178:E187, Appliance_Library!E188:E194, Appliance_Library!E195:E200, Appliance_Library!E201:E205, Appliance_Library!E206:E211, Appliance_Library!E212:E216, Appliance_Library!E217:E222, Appliance_Library!E223:E227, Appliance_Library!E228:E233, Appliance_Library!E234:E237, Appliance_Library!E238:E242, Appliance_Library!E243:E247, Appliance_Library!E248:E255, Appliance_Library!E256:E262, Appliance_Library!E263:E270, Appliance_Library!E271:E279, Appliance_Library!E280:E286, Appliance_Library!E287:E293, Appliance_Library!E294:E300, Appliance_Library!E301:E306, Appliance_Library!E307:E312, Appliance_Library!E313:E319, Appliance_Library!E320:E326 ), ROW()-ROW($E$4)+1)) -> #REF! | C18: =IF(User_Inputs!$D$11="","", INDEX( CHOOSE(User_Inputs!$D$11, Appliance_Library!F18:F26, Appliance_Library!F27:F36, Appliance_Library!F37:F47, Appliance_Library!F48:F60, Appliance_Library!F61:F74, Appliance_Library!F75:F87, Appliance_Library!F88:F96, Appliance_Library!F97:F106, Appliance_Library!F107:F116, Appliance_Library!F117:F125, Appliance_Library!F126:F134, Appliance_Library!F135:F142, Appliance_Library!F143:F147, Appliance_Library!F148:F154, Appliance_Library!F155:F162, Appliance_Library!F163:F170, Appliance_Library!F171:F177, Appliance_Library!F178:F187, Appliance_Library!F188:F194, Appliance_Library!F195:F200, Appliance_Library!F201:F205, Appliance_Library!F206:F211, Appliance_Library!F212:F216, Appliance_Library!F217:F222, Appliance_Library!F223:F227, Appliance_Library!F228:F233, Appliance_Library!F234:F237, Appliance_Library!F238:F242, Appliance_Library!F243:F247, Appliance_Library!F248:F255, Appliance_Library!F256:F262, Appliance_Library!F263:F270, Appliance_Library!F271:F279, Appliance_Library!F280:F286, Appliance_Library!F287:F293, Appliance_Library!F294:F300, Appliance_Library!F301:F306, Appliance_Library!F307:F312, Appliance_Library!F313:F319, Appliance_Library!F320:F326 ), ROW()-ROW($F$4)+1)) -> #REF! | D18: =IF(User_Inputs!$D$11="","", INDEX( CHOOSE(User_Inputs!$D$11, Appliance_Library!G18:G26, Appliance_Library!G27:G36, Appliance_Library!G37:G47, Appliance_Library!G48:G60, Appliance_Library!G61:G74, Appliance_Library!G75:G87, Appliance_Library!G88:G96, Appliance_Library!G97:G106, Appliance_Library!G107:G116, Appliance_Library!G117:G125, Appliance_Library!G126:G134, Appliance_Library!G135:G142, Appliance_Library!G143:G147, Appliance_Library!G148:G154, Appliance_Library!G155:G162, Appliance_Library!G163:G170, Appliance_Library!G171:G177, Appliance_Library!G178:G187, Appliance_Library!G188:G194, Appliance_Library!G195:G200, Appliance_Library!G201:G205, Appliance_Library!G206:G211, Appliance_Library!G212:G216, Appliance_Library!G217:G222, Appliance_Library!G223:G227, Appliance_Library!G228:G233, Appliance_Library!G234:G237, Appliance_Library!G238:G242, Appliance_Library!G243:G247, Appliance_Library!G248:G255, Appliance_Library!G256:G262, Appliance_Library!G263:G270, Appliance_Library!G271:G279, Appliance_Library!G280:G286, Appliance_Library!G287:G293, Appliance_Library!G294:G300, Appliance_Library!G301:G306, Appliance_Library!G307:G312, Appliance_Library!G313:G319, Appliance_Library!G320:G326 ), ROW()-ROW($G$4)+1)) -> #REF! | E18: =IF(User_Inputs!$D$11="","", INDEX( CHOOSE(User_Inputs!$D$11, Appliance_Library!H18:H26, Appliance_Library!H27:H36, Appliance_Library!H37:H47, Appliance_Library!H48:H60, Appliance_Library!H61:H74, Appliance_Library!H75:H87, Appliance_Library!H88:H96, Appliance_Library!H97:H106, Appliance_Library!H107:H116, Appliance_Library!H117:H125, Appliance_Library!H126:H134, Appliance_Library!H135:H142, Appliance_Library!H143:H147, Appliance_Library!H148:H154, Appliance_Library!H155:H162, Appliance_Library!H163:H170, Appliance_Library!H171:H177, Appliance_Library!H178:H187, Appliance_Library!H188:H194, Appliance_Library!H195:H200, Appliance_Library!H201:H205, Appliance_Library!H206:H211, Appliance_Library!H212:H216, Appliance_Library!H217:H222, Appliance_Library!H223:H227, Appliance_Library!H228:H233, Appliance_Library!H234:H237, Appliance_Library!H238:H242, Appliance_Library!H243:H247, Appliance_Library!H248:H255, Appliance_Library!H256:H262, Appliance_Library!H263:H270, Appliance_Library!H271:H279, Appliance_Library!H280:H286, Appliance_Library!H287:H293, Appliance_Library!H294:H300, Appliance_Library!H301:H306, Appliance_Library!H307:H312, Appliance_Library!H313:H319, Appliance_Library!H320:H326 ), ROW()-ROW($H$4)+1)) -> #REF! | F18: =IFERROR(C18*E18,0) -> 0 | G18: =IFERROR(F18*B18*D18/1000,0) -> 0 | H18: =G18*30 -> 0 | I18: =IFERROR(F18*B18,0) -> 0
A19: =IF(User_Inputs!$D$11="","", INDEX( CHOOSE(User_Inputs!$D$11, Appliance_Library!D19:D27, Appliance_Library!D28:D37, Appliance_Library!D38:D48, Appliance_Library!D49:D61, Appliance_Library!D62:D75, Appliance_Library!D76:D88, Appliance_Library!D89:D97, Appliance_Library!D98:D107, Appliance_Library!D108:D117, Appliance_Library!D118:D126, Appliance_Library!D127:D135, Appliance_Library!D136:D143, Appliance_Library!D144:D148, Appliance_Library!D149:D155, Appliance_Library!D156:D163, Appliance_Library!D164:D171, Appliance_Library!D172:D178, Appliance_Library!D179:D188, Appliance_Library!D189:D195, Appliance_Library!D196:D201, Appliance_Library!D202:D206, Appliance_Library!D207:D212, Appliance_Library!D213:D217, Appliance_Library!D218:D223, Appliance_Library!D224:D228, Appliance_Library!D229:D234, Appliance_Library!D235:D238, Appliance_Library!D239:D243, Appliance_Library!D244:D248, Appliance_Library!D249:D256, Appliance_Library!D257:D263, Appliance_Library!D264:D271, Appliance_Library!D272:D280, Appliance_Library!D281:D287, Appliance_Library!D288:D294, Appliance_Library!D295:D301, Appliance_Library!D302:D307, Appliance_Library!D308:D313, Appliance_Library!D314:D320, Appliance_Library!D321:D327 ), ROW()-ROW($D$4)+1)) -> #REF! | B19: =IF(User_Inputs!$D$11="","", INDEX( CHOOSE(User_Inputs!$D$11, Appliance_Library!E19:E27, Appliance_Library!E28:E37, Appliance_Library!E38:E48, Appliance_Library!E49:E61, Appliance_Library!E62:E75, Appliance_Library!E76:E88, Appliance_Library!E89:E97, Appliance_Library!E98:E107, Appliance_Library!E108:E117, Appliance_Library!E118:E126, Appliance_Library!E127:E135, Appliance_Library!E136:E143, Appliance_Library!E144:E148, Appliance_Library!E149:E155, Appliance_Library!E156:E163, Appliance_Library!E164:E171, Appliance_Library!E172:E178, Appliance_Library!E179:E188, Appliance_Library!E189:E195, Appliance_Library!E196:E201, Appliance_Library!E202:E206, Appliance_Library!E207:E212, Appliance_Library!E213:E217, Appliance_Library!E218:E223, Appliance_Library!E224:E228, Appliance_Library!E229:E234, Appliance_Library!E235:E238, Appliance_Library!E239:E243, Appliance_Library!E244:E248, Appliance_Library!E249:E256, Appliance_Library!E257:E263, Appliance_Library!E264:E271, Appliance_Library!E272:E280, Appliance_Library!E281:E287, Appliance_Library!E288:E294, Appliance_Library!E295:E301, Appliance_Library!E302:E307, Appliance_Library!E308:E313, Appliance_Library!E314:E320, Appliance_Library!E321:E327 ), ROW()-ROW($E$4)+1)) -> #REF! | C19: =IF(User_Inputs!$D$11="","", INDEX( CHOOSE(User_Inputs!$D$11, Appliance_Library!F19:F27, Appliance_Library!F28:F37, Appliance_Library!F38:F48, Appliance_Library!F49:F61, Appliance_Library!F62:F75, Appliance_Library!F76:F88, Appliance_Library!F89:F97, Appliance_Library!F98:F107, Appliance_Library!F108:F117, Appliance_Library!F118:F126, Appliance_Library!F127:F135, Appliance_Library!F136:F143, Appliance_Library!F144:F148, Appliance_Library!F149:F155, Appliance_Library!F156:F163, Appliance_Library!F164:F171, Appliance_Library!F172:F178, Appliance_Library!F179:F188, Appliance_Library!F189:F195, Appliance_Library!F196:F201, Appliance_Library!F202:F206, Appliance_Library!F207:F212, Appliance_Library!F213:F217, Appliance_Library!F218:F223, Appliance_Library!F224:F228, Appliance_Library!F229:F234, Appliance_Library!F235:F238, Appliance_Library!F239:F243, Appliance_Library!F244:F248, Appliance_Library!F249:F256, Appliance_Library!F257:F263, Appliance_Library!F264:F271, Appliance_Library!F272:F280, Appliance_Library!F281:F287, Appliance_Library!F288:F294, Appliance_Library!F295:F301, Appliance_Library!F302:F307, Appliance_Library!F308:F313, Appliance_Library!F314:F320, Appliance_Library!F321:F327 ), ROW()-ROW($F$4)+1)) -> #REF! | D19: =IF(User_Inputs!$D$11="","", INDEX( CHOOSE(User_Inputs!$D$11, Appliance_Library!G19:G27, Appliance_Library!G28:G37, Appliance_Library!G38:G48, Appliance_Library!G49:G61, Appliance_Library!G62:G75, Appliance_Library!G76:G88, Appliance_Library!G89:G97, Appliance_Library!G98:G107, Appliance_Library!G108:G117, Appliance_Library!G118:G126, Appliance_Library!G127:G135, Appliance_Library!G136:G143, Appliance_Library!G144:G148, Appliance_Library!G149:G155, Appliance_Library!G156:G163, Appliance_Library!G164:G171, Appliance_Library!G172:G178, Appliance_Library!G179:G188, Appliance_Library!G189:G195, Appliance_Library!G196:G201, Appliance_Library!G202:G206, Appliance_Library!G207:G212, Appliance_Library!G213:G217, Appliance_Library!G218:G223, Appliance_Library!G224:G228, Appliance_Library!G229:G234, Appliance_Library!G235:G238, Appliance_Library!G239:G243, Appliance_Library!G244:G248, Appliance_Library!G249:G256, Appliance_Library!G257:G263, Appliance_Library!G264:G271, Appliance_Library!G272:G280, Appliance_Library!G281:G287, Appliance_Library!G288:G294, Appliance_Library!G295:G301, Appliance_Library!G302:G307, Appliance_Library!G308:G313, Appliance_Library!G314:G320, Appliance_Library!G321:G327 ), ROW()-ROW($G$4)+1)) -> #REF! | E19: =IF(User_Inputs!$D$11="","", INDEX( CHOOSE(User_Inputs!$D$11, Appliance_Library!H19:H27, Appliance_Library!H28:H37, Appliance_Library!H38:H48, Appliance_Library!H49:H61, Appliance_Library!H62:H75, Appliance_Library!H76:H88, Appliance_Library!H89:H97, Appliance_Library!H98:H107, Appliance_Library!H108:H117, Appliance_Library!H118:H126, Appliance_Library!H127:H135, Appliance_Library!H136:H143, Appliance_Library!H144:H148, Appliance_Library!H149:H155, Appliance_Library!H156:H163, Appliance_Library!H164:H171, Appliance_Library!H172:H178, Appliance_Library!H179:H188, Appliance_Library!H189:H195, Appliance_Library!H196:H201, Appliance_Library!H202:H206, Appliance_Library!H207:H212, Appliance_Library!H213:H217, Appliance_Library!H218:H223, Appliance_Library!H224:H228, Appliance_Library!H229:H234, Appliance_Library!H235:H238, Appliance_Library!H239:H243, Appliance_Library!H244:H248, Appliance_Library!H249:H256, Appliance_Library!H257:H263, Appliance_Library!H264:H271, Appliance_Library!H272:H280, Appliance_Library!H281:H287, Appliance_Library!H288:H294, Appliance_Library!H295:H301, Appliance_Library!H302:H307, Appliance_Library!H308:H313, Appliance_Library!H314:H320, Appliance_Library!H321:H327 ), ROW()-ROW($H$4)+1)) -> #REF! | F19: =IFERROR(C19*E19,0) -> 0 | G19: =IFERROR(F19*B19*D19/1000,0) -> 0 | H19: =G19*30 -> 0 | I19: =IFERROR(F19*B19,0) -> 0
A20: =IF(User_Inputs!$D$11="","", INDEX( CHOOSE(User_Inputs!$D$11, Appliance_Library!D20:D28, Appliance_Library!D29:D38, Appliance_Library!D39:D49, Appliance_Library!D50:D62, Appliance_Library!D63:D76, Appliance_Library!D77:D89, Appliance_Library!D90:D98, Appliance_Library!D99:D108, Appliance_Library!D109:D118, Appliance_Library!D119:D127, Appliance_Library!D128:D136, Appliance_Library!D137:D144, Appliance_Library!D145:D149, Appliance_Library!D150:D156, Appliance_Library!D157:D164, Appliance_Library!D165:D172, Appliance_Library!D173:D179, Appliance_Library!D180:D189, Appliance_Library!D190:D196, Appliance_Library!D197:D202, Appliance_Library!D203:D207, Appliance_Library!D208:D213, Appliance_Library!D214:D218, Appliance_Library!D219:D224, Appliance_Library!D225:D229, Appliance_Library!D230:D235, Appliance_Library!D236:D239, Appliance_Library!D240:D244, Appliance_Library!D245:D249, Appliance_Library!D250:D257, Appliance_Library!D258:D264, Appliance_Library!D265:D272, Appliance_Library!D273:D281, Appliance_Library!D282:D288, Appliance_Library!D289:D295, Appliance_Library!D296:D302, Appliance_Library!D303:D308, Appliance_Library!D309:D314, Appliance_Library!D315:D321, Appliance_Library!D322:D328 ), ROW()-ROW($D$4)+1)) -> #REF! | B20: =IF(User_Inputs!$D$11="","", INDEX( CHOOSE(User_Inputs!$D$11, Appliance_Library!E20:E28, Appliance_Library!E29:E38, Appliance_Library!E39:E49, Appliance_Library!E50:E62, Appliance_Library!E63:E76, Appliance_Library!E77:E89, Appliance_Library!E90:E98, Appliance_Library!E99:E108, Appliance_Library!E109:E118, Appliance_Library!E119:E127, Appliance_Library!E128:E136, Appliance_Library!E137:E144, Appliance_Library!E145:E149, Appliance_Library!E150:E156, Appliance_Library!E157:E164, Appliance_Library!E165:E172, Appliance_Library!E173:E179, Appliance_Library!E180:E189, Appliance_Library!E190:E196, Appliance_Library!E197:E202, Appliance_Library!E203:E207, Appliance_Library!E208:E213, Appliance_Library!E214:E218, Appliance_Library!E219:E224, Appliance_Library!E225:E229, Appliance_Library!E230:E235, Appliance_Library!E236:E239, Appliance_Library!E240:E244, Appliance_Library!E245:E249, Appliance_Library!E250:E257, Appliance_Library!E258:E264, Appliance_Library!E265:E272, Appliance_Library!E273:E281, Appliance_Library!E282:E288, Appliance_Library!E289:E295, Appliance_Library!E296:E302, Appliance_Library!E303:E308, Appliance_Library!E309:E314, Appliance_Library!E315:E321, Appliance_Library!E322:E328 ), ROW()-ROW($E$4)+1)) -> #REF! | C20: =IF(User_Inputs!$D$11="","", INDEX( CHOOSE(User_Inputs!$D$11, Appliance_Library!F20:F28, Appliance_Library!F29:F38, Appliance_Library!F39:F49, Appliance_Library!F50:F62, Appliance_Library!F63:F76, Appliance_Library!F77:F89, Appliance_Library!F90:F98, Appliance_Library!F99:F108, Appliance_Library!F109:F118, Appliance_Library!F119:F127, Appliance_Library!F128:F136, Appliance_Library!F137:F144, Appliance_Library!F145:F149, Appliance_Library!F150:F156, Appliance_Library!F157:F164, Appliance_Library!F165:F172, Appliance_Library!F173:F179, Appliance_Library!F180:F189, Appliance_Library!F190:F196, Appliance_Library!F197:F202, Appliance_Library!F203:F207, Appliance_Library!F208:F213, Appliance_Library!F214:F218, Appliance_Library!F219:F224, Appliance_Library!F225:F229, Appliance_Library!F230:F235, Appliance_Library!F236:F239, Appliance_Library!F240:F244, Appliance_Library!F245:F249, Appliance_Library!F250:F257, Appliance_Library!F258:F264, Appliance_Library!F265:F272, Appliance_Library!F273:F281, Appliance_Library!F282:F288, Appliance_Library!F289:F295, Appliance_Library!F296:F302, Appliance_Library!F303:F308, Appliance_Library!F309:F314, Appliance_Library!F315:F321, Appliance_Library!F322:F328 ), ROW()-ROW($F$4)+1)) -> #REF! | D20: =IF(User_Inputs!$D$11="","", INDEX( CHOOSE(User_Inputs!$D$11, Appliance_Library!G20:G28, Appliance_Library!G29:G38, Appliance_Library!G39:G49, Appliance_Library!G50:G62, Appliance_Library!G63:G76, Appliance_Library!G77:G89, Appliance_Library!G90:G98, Appliance_Library!G99:G108, Appliance_Library!G109:G118, Appliance_Library!G119:G127, Appliance_Library!G128:G136, Appliance_Library!G137:G144, Appliance_Library!G145:G149, Appliance_Library!G150:G156, Appliance_Library!G157:G164, Appliance_Library!G165:G172, Appliance_Library!G173:G179, Appliance_Library!G180:G189, Appliance_Library!G190:G196, Appliance_Library!G197:G202, Appliance_Library!G203:G207, Appliance_Library!G208:G213, Appliance_Library!G214:G218, Appliance_Library!G219:G224, Appliance_Library!G225:G229, Appliance_Library!G230:G235, Appliance_Library!G236:G239, Appliance_Library!G240:G244, Appliance_Library!G245:G249, Appliance_Library!G250:G257, Appliance_Library!G258:G264, Appliance_Library!G265:G272, Appliance_Library!G273:G281, Appliance_Library!G282:G288, Appliance_Library!G289:G295, Appliance_Library!G296:G302, Appliance_Library!G303:G308, Appliance_Library!G309:G314, Appliance_Library!G315:G321, Appliance_Library!G322:G328 ), ROW()-ROW($G$4)+1)) -> #REF! | E20: =IF(User_Inputs!$D$11="","", INDEX( CHOOSE(User_Inputs!$D$11, Appliance_Library!H20:H28, Appliance_Library!H29:H38, Appliance_Library!H39:H49, Appliance_Library!H50:H62, Appliance_Library!H63:H76, Appliance_Library!H77:H89, Appliance_Library!H90:H98, Appliance_Library!H99:H108, Appliance_Library!H109:H118, Appliance_Library!H119:H127, Appliance_Library!H128:H136, Appliance_Library!H137:H144, Appliance_Library!H145:H149, Appliance_Library!H150:H156, Appliance_Library!H157:H164, Appliance_Library!H165:H172, Appliance_Library!H173:H179, Appliance_Library!H180:H189, Appliance_Library!H190:H196, Appliance_Library!H197:H202, Appliance_Library!H203:H207, Appliance_Library!H208:H213, Appliance_Library!H214:H218, Appliance_Library!H219:H224, Appliance_Library!H225:H229, Appliance_Library!H230:H235, Appliance_Library!H236:H239, Appliance_Library!H240:H244, Appliance_Library!H245:H249, Appliance_Library!H250:H257, Appliance_Library!H258:H264, Appliance_Library!H265:H272, Appliance_Library!H273:H281, Appliance_Library!H282:H288, Appliance_Library!H289:H295, Appliance_Library!H296:H302, Appliance_Library!H303:H308, Appliance_Library!H309:H314, Appliance_Library!H315:H321, Appliance_Library!H322:H328 ), ROW()-ROW($H$4)+1)) -> #REF! | F20: =IFERROR(C20*E20,0) -> 0 | G20: =IFERROR(F20*B20*D20/1000,0) -> 0 | H20: =G20*30 -> 0 | I20: =IFERROR(F20*B20,0) -> 0
F21: =IFERROR(C21*E21,0) -> 0 | G21: =IFERROR(F21*B21*D21/1000,0) -> 0 | H21: =G21*30 -> 0 | I21: =IFERROR(F21*B21,0) -> 0
F22: =IFERROR(C22*E22,0) -> 0 | G22: =IFERROR(F22*B22*D22/1000,0) -> 0 | H22: =G22*30 -> 0 | I22: =IFERROR(F22*B22,0) -> 0
F23: =IFERROR(C23*E23,0) -> 0 | G23: =IFERROR(F23*B23*D23/1000,0) -> 0 | H23: =G23*30 -> 0 | I23: =IFERROR(F23*#REF!,0) -> 0
F24: =IFERROR(C24*E24,0) -> 0 | G24: =IFERROR(F24*B24*D24/1000,0) -> 0 | H24: =G24*30 -> 0 | I24: =IFERROR(F24*B24,0) -> 0
F25: =IFERROR(C25*E25,0) -> 0 | G25: =IFERROR(F25*B25*D25/1000,0) -> 0 | H25: =G25*30 -> 0 | I25: =IFERROR(F25*#REF!,0) -> 0
F26: =IFERROR(C26*E26,0) -> 0 | G26: =IFERROR(F26*B26*D26/1000,0) -> 0 | H26: =G26*30 -> 0 | I26: =IFERROR(F26*B26,0) -> 0
F27: =IFERROR(C27*E27,0) -> 0 | G27: =IFERROR(F27*B27*D27/1000,0) -> 0 | H27: =G27*30 -> 0 | I27: =IFERROR(F27*#REF!,0) -> 0
F28: =IFERROR(C28*E28,0) -> 0 | G28: =IFERROR(F28*B28*D28/1000,0) -> 0 | H28: =G28*30 -> 0 | I28: =IFERROR(F28*B28,0) -> 0
F29: =IFERROR(C29*E29,0) -> 0 | G29: =IFERROR(F29*B29*D29/1000,0) -> 0 | H29: =G29*30 -> 0 | I29: =IFERROR(F29*#REF!,0) -> 0
F30: =IFERROR(C30*E30,0) -> 0 | G30: =IFERROR(F30*B30*D30/1000,0) -> 0 | H30: =G30*30 -> 0 | I30: =IFERROR(F30*#REF!,0) -> 0

Sheet Custom_Equipment
A1: Custom Equipment
A3: Equipment_Name | B3: Rated_Watts | C3: Load_Factor | D3: Quantity | E3: Hours_per_Day | F3: Effective_Watts | G3: Daily_kWh | H3: Monthly_kWh | I3: Peak_Watts | J3: Critical_Tag | L3: Custom Totals
F4: =IFERROR(B4*C4,0) -> 0 | G4: =IFERROR(F4*D4*E4/1000,0) -> 0 | H4: =G4*30 -> 0 | I4: =IFERROR(F4*D4,0) -> 0 | J4: No | L4: Daily kWh | M4: =SUM(G4:G23) -> 0
F5: =IFERROR(B5*C5,0) -> 0 | G5: =IFERROR(F5*D5*E5/1000,0) -> 0 | H5: =G5*30 -> 0 | I5: =IFERROR(F5*D5,0) -> 0 | J5: Yes | L5: Monthly kWh | M5: =SUM(H4:H23) -> 0
F6: =IFERROR(B6*C6,0) -> 0 | G6: =IFERROR(F6*D6*E6/1000,0) -> 0 | H6: =G6*30 -> 0 | I6: =IFERROR(F6*D6,0) -> 0 | J6: Yes | L6: Raw Peak kW | M6: =SUM(I4:I23)/1000 -> 0
F7: =IFERROR(B7*C7,0) -> 0 | G7: =IFERROR(F7*D7*E7/1000,0) -> 0 | H7: =G7*30 -> 0 | I7: =IFERROR(F7*D7,0) -> 0 | J7: No | L7: Diversity-adjusted Peak kW | M7: =M6*0.75 -> 0
F8: =IFERROR(B8*C8,0) -> 0 | G8: =IFERROR(F8*D8*E8/1000,0) -> 0 | H8: =G8*30 -> 0 | I8: =IFERROR(F8*D8,0) -> 0
F9: =IFERROR(B9*C9,0) -> 0 | G9: =IFERROR(F9*D9*E9/1000,0) -> 0 | H9: =G9*30 -> 0 | I9: =IFERROR(F9*D9,0) -> 0
F10: =IFERROR(B10*C10,0) -> 0 | G10: =IFERROR(F10*D10*E10/1000,0) -> 0 | H10: =G10*30 -> 0 | I10: =IFERROR(F10*D10,0) -> 0
F11: =IFERROR(B11*C11,0) -> 0 | G11: =IFERROR(F11*D11*E11/1000,0) -> 0 | H11: =G11*30 -> 0 | I11: =IFERROR(F11*D11,0) -> 0
F12: =IFERROR(B12*C12,0) -> 0 | G12: =IFERROR(F12*D12*E12/1000,0) -> 0 | H12: =G12*30 -> 0 | I12: =IFERROR(F12*D12,0) -> 0
F13: =IFERROR(B13*C13,0) -> 0 | G13: =IFERROR(F13*D13*E13/1000,0) -> 0 | H13: =G13*30 -> 0 | I13: =IFERROR(F13*D13,0) -> 0
F14: =IFERROR(B14*C14,0) -> 0 | G14: =IFERROR(F14*D14*E14/1000,0) -> 0 | H14: =G14*30 -> 0 | I14: =IFERROR(F14*D14,0) -> 0
F15: =IFERROR(B15*C15,0) -> 0 | G15: =IFERROR(F15*D15*E15/1000,0) -> 0 | H15: =G15*30 -> 0 | I15: =IFERROR(F15*D15,0) -> 0
F16: =IFERROR(B16*C16,0) -> 0 | G16: =IFERROR(F16*D16*E16/1000,0) -> 0 | H16: =G16*30 -> 0 | I16: =IFERROR(F16*D16,0) -> 0
F17: =IFERROR(B17*C17,0) -> 0 | G17: =IFERROR(F17*D17*E17/1000,0) -> 0 | H17: =G17*30 -> 0 | I17: =IFERROR(F17*D17,0) -> 0
F18: =IFERROR(B18*C18,0) -> 0 | G18: =IFERROR(F18*D18*E18/1000,0) -> 0 | H18: =G18*30 -> 0 | I18: =IFERROR(F18*D18,0) -> 0
F19: =IFERROR(B19*C19,0) -> 0 | G19: =IFERROR(F19*D19*E19/1000,0) -> 0 | H19: =G19*30 -> 0 | I19: =IFERROR(F19*D19,0) -> 0
... F23: =IFERROR(B23*C23,0) -> 0 | G23: =IFERROR(F23*D23*E23/1000,0) -> 0 | H23: =G23*30 -> 0 | I23: =IFERROR(F23*D23,0) -> 0

Sheet Objective_Logic
A1: Objective Logic

Sheet Assumptions
B18: 1
B19: 1
B20: 1
B21: 1
B22: 1
B23: 1

Sheet Load_Estimation
B4: =User_Inputs!B15 -> Appliances
B5: =Bill_Input!B11 -> 2653.9379
B6: =Appliance_Input!L5 -> 241.65
B7: =Custom_Equipment!M5 -> 0
B8: =IFERROR(CHOOSE(MATCH(B4,{"Bill","Appliances","Custom"},0),B5,B6,B7),0) -> 241.65
B9: =B8*12 -> 2899.8
B10: =IF(B4="Bill",IF(User_Inputs!B19>0,User_Inputs!B19,B8/(30*24)*3),IF(B4="Appliances",Appliance_Input!L6,IF(B4="Custom",Custom_Equipment!M7,0))) -> 2.885
B11: =IF(User_Inputs!B19>0,User_Inputs!B19,B10) -> 2.885
B12: =B11*User_Inputs!B24 -> 1.731

Sheet Battery_Sizing
B4: =User_Inputs!B14 -> Reduce Diesel Use
B5: =Load_Estimation!B12 -> 1.731
B6: =User_Inputs!B25 -> 4
B7: 1
B8: =B5*B6 -> 6.924
B9: =B7*MAX(0.5,B8) -> 6.924
B10: =B9 -> 6.924
B11: =Load_Estimation!B11*User_Inputs!B44 -> 2.885
B12: =B11 -> 2.885

Sheet Solar_Sizing
B4: =User_Inputs!B14 -> Reduce Diesel Use
B5: =Load_Estimation!B9 -> 2899.8
B6: 1
B7: =MIN(1,User_Inputs!B26*B6) -> 0.9
B8: =B5 -> 2899.8
B9: =User_Inputs!B21*User_Inputs!B22 -> 120
B10: =IFERROR(B9/User_Inputs!B45,0) -> 21.818182
B11: =IFERROR(B8/User_Inputs!B42,0) -> 1.9998621
B12: =B11 -> 1.9998621
B13: =B12*User_Inputs!B42 -> 2899.8
B14: =B13*User_Inputs!B26 -> 2609.82

Sheet Diesel_Economics
A1: Diesel Economics
B4: =User_Inputs!B13 -> Grid + Generator
B5: =MIN(1,User_Inputs!B20/24) -> 0.25
B6: =IFERROR(User_Inputs!B31/User_Inputs!B32,0) -> 342.85714
B7: =IF(B4="Grid Only",User_Inputs!B30,User_Inputs!B30*(1-B5)+B6*B5) -> 242.83929
B8: =IF(OR(B4="Grid + Generator",B4="Generator Only"),Solar_Sizing!B14*B5,0) -> 652.455
B9: =IFERROR(B8/User_Inputs!B32,0) -> 186.41571

Sheet Financial_Model
B4: =Solar_Sizing!B12*User_Inputs!B33 -> 599958.62 | D4: All zeros shown as -
B5: =Battery_Sizing!B10*User_Inputs!B34 -> 1800240
B6: =Battery_Sizing!B12*User_Inputs!B35 -> 663550
B7: =SUM(B4:B6) -> 3063748.6
B8: =B7*User_Inputs!B36 -> 367649.83
B9: =B7+B8 -> 3431398.5
B10: =Solar_Sizing!B14*Diesel_Economics!B7 -> 633766.82
B11: =B9*User_Inputs!B37 -> 68627.969
B12: =B10-B11 -> 565138.86
B13: =IF(B12>0,B9/B12,"") -> 6.0717794

Sheet Formula_Map

Sheet Lead_Routing

Sheet Outputs
A1: Outputs
A4: Assessment_ID | B4: =User_Inputs!B4 -> SV-0001
A5: Scenario_Name | B5: =User_Inputs!B5 -> Base Case
A6: Country | B6: =User_Inputs!B7 -> Nigeria
A7: Property_Type | B7: =User_Inputs!B10 -> Home
A8: Power_Setup | B8: =User_Inputs!B13 -> Grid + Generator
A9: Objective_Mode | B9: =User_Inputs!B14 -> Reduce Diesel Use
A10: Recommended Solar PV | B10: =Solar_Sizing!B12 -> 1.9998621 | C10: kWp
A11: Recommended Battery | B11: =Battery_Sizing!B10 -> 6.924 | C11: kWh
A12: Recommended Inverter | B12: =Battery_Sizing!B12 -> 2.885 | C12: kW
A13: Annual_PV_Generation_kWh | B13: =Solar_Sizing!B13 -> 2899.8
A14: Usable_Solar_kWh | B14: =Solar_Sizing!B14 -> 2609.82
A15: Estimated system cost | B15: =Financial_Model!B9 -> 3431398.5 | C15: Total_Capex
A16: Gross annual savings | B16: =Financial_Model!B10 -> 633766.82
A17: Annual O&M allowance | B17: =Financial_Model!B11 -> 68627.969
A18: Net annual savings | B18: =Financial_Model!B12 -> 565138.86
A19: Simple payback | B19: =Financial_Model!B13 -> 6.0717794 | C19: years
A20: Diesel Saved | B20: =Diesel_Economics!B9 -> 186.41571 | C20: Litres
A21: Lead_Type | B21: =Lead_Routing!B6 -> 0
A22: Recommended_Next_Step | B22: =Lead_Routing!B7 -> 0
A23: Primary_Recommendation_Text | B23: =IFERROR(VLOOKUP(User_Inputs!B14, Objective_Logic!A4:F7, 6, FALSE), "Review objective mapping") -> Review objective mapping
A24: Confidence_Note | B24: =IF(OR(User_Inputs!B21=0,User_Inputs!B19=0),"Preliminary estimate based on partial inputs","Preliminary estimate with user-supplied site context") -> Preliminary estimate based on partial inputs
A25: Disclaimer_Text | B25: ="Indicative estimate only. Final design, procurement and performance should be validated by detailed review." -> Indicative estimate only. Final design, procurement and performance should be validated by detailed review.
A27: Solar share | B27: =Solar_Sizing!B14/Load_Estimation!B9 -> 0.9
A28: Grid offset | B28: =(Solar_Sizing!B14*(1-User_Inputs!B20/24))/Load_Estimation!B9 -> 0.675
A29: Diesel reduction | B29: =(Solar_Sizing!B14*(User_Inputs!B20/24))/Load_Estimation!B9 -> 0.225
A31: System Class | B31: =IF(B12<3.5,"Class A",IF(B12<5,"Class B",IF(B12<10,"Class C",IF(B12<50,"Class D","Class E")))) -> Class A
A33: Bill selection
A34: Estimated Annual Load | B34: =Load_Estimation!B9 -> 2899.8 | C34: kWh
A35: Monthly Usage | B35: =Bill_Input!B11 -> 2653.9379 | C35: kWh
A36: Estimated Monthly Spend | B36: =Bill_Input!B13 -> 50625.675
A38: Appliance selection
A39: Daily Energy | B39: =Appliance_Input!L4 -> 8.055 | C39: kWh
A40: Monthly Energy | B40: =Appliance_Input!L5 -> 241.65 | C40: kWh
A41: Estimated Annual Load | B41: =Load_Estimation!B9 -> 2899.8 | C41: kWh
A43: Custom selection
A44: Daily Energy | B44: =Custom_Equipment!M4 -> 0 | C44: kWh
A45: Monthly Energy | B45: =Custom_Equipment!M5 -> 0 | C45: kWh
A46: Estimated Annual Load | B46: =Load_Estimation!B9 -> 2899.8 | C46: kWh

Sheet Developer_Bridge
A1: Developer Bridge Specification
A3: Write inputs to
B4: User_Inputs!B4:B43 (main scenario fields)
B5: Bill_Input!B5:B7 if Bill route is used
B6: Appliance_Input!A4:E23 if Appliance route is used
B7: Custom_Equipment!A4:E23 and J4:J23 if Custom route is used
A9: Read outputs from
B10: Outputs!B4:B24 only
B11: Key commercial routing: Outputs!B20:B21
B12: Optional reporting: Financial_Model, Solar_Sizing, Battery_Sizing
A14: Integration note | B14: Recommended architecture: Frontend UI -> backend API bridge -> Excel engine -> Outputs sheet -> results page / supplier matching / lead form.

Sheet Customer_Profile
A4: Field | B4: Value | C4: Guidance / Example | D4: Backend use
A5: Customer ID | B5: SV-0001 | C5: Unique Solarvy lead reference | D5: Used across trackers
A6: Customer Name | B6: John Peters | C6: Optional before introduction | D6: CRM
A7: Phone / Email | B7: jpeters234@gmail.com | C7: For introduction request only | D7: CRM
A8: Category | B8: =User_Inputs!B10 -> Home | C8: Home, Hotel, Commercial, Factory, Hospital, School | D8: Category scoring
A9: Template Used | B9: 4 Bedroom Duplex - Standard | C9: Selected quick template | D9: Context
A10: State | B10: =User_Inputs!B8 -> Lagos | C10: Customer state | D10: Location scoring
A11: City | C11: Customer city / area | D11: Location scoring
A12: Budget Band | B12: Mid-range | C12: Budget, Mid-range, Premium, Unknown | D12: Pricing fit
A13: Timeline | B13: Within 1 month | C13: Urgency helps prioritise | D13: Follow-up
A14: Backup Priority | B14: AC support | C14: Essential backup, AC support, whole facility, etc. | D14: Complexity
A15: Project Complexity | B15: =Lead_Routing!B4 -> 0 | C15: Low, Medium, High, Critical | D15: Risk/technical matching
A16: Estimated Daily kWh | B16: =Load_Estimation!B8/30 -> 8.055 | C16: From load template result | D16: System size scoring
A17: Suggested Solar Size_kWp | B17: =Outputs!B10 -> 1.9998621 | C17: From load template result | D17: Result display
A18: Suggested Battery Size_kWh | B18: =Outputs!B11 -> 6.924 | C18: From load template result | D18: Result display
A19: Suggested Inverter_kVA | B19: =Outputs!B12 -> 2.885 | C19: From load template result | D19: System size scoring
A20: Needs Site Visit | B20: Yes | C20: Yes / No | D20: Next step
A21: Needs Quote Review | B21: Yes | C21: Yes / No | D21: Quote review CTA
A22: Internal Notes | B22: Customer wants AC support and generator reduction. | C22: Not shown to customer | D22: Internal

Sheet Installer_Database
A4: Installer ID | B4: Installer Name | C4: Contact Person | D4: Phone | E4: Email | F4: State Coverage | G4: City Coverage | H4: Categories Covered | I4: Min kVA | J4: Max kVA | K4: Battery/Hybrid Exp | L4: Generator Integration | M4: Commercial Exp | N4: Industrial Exp | O4: Hospital/Critical Exp | P4: Years Exp | Q4: Past Projects | R4: Brands Used | S4: Warranty Support | T4: Response Speed | U4: Pricing Level | V4: Quality Rating | W4: Reliability Rating | X4: Client Feedback | Y4: Approval Status | Z4: Notes
A5: INST-001 | B5: Lagos Hybrid Power Ltd | C5: Tunde Ade | D5: 08000000001 | E5: ops@lagoshybrid.example | F5: Lagos | G5: Lekki; Ajah; VI; Ikoyi; Ikeja | H5: Home; Commercial; Hotel | I5: 3 | J5: 20 | K5: Strong | L5: Yes | M5: Yes | N5: No | O5: No | P5: 6 | Q5: 85 | R5: Victron; Deye; Felicity; JA Solar | S5: Strong | T5: Same day | U5: Mid-range | V5: Good | W5: Excellent | X5: Good | Y5: Preferred | Z5: Strong residential and SME hybrid delivery.
A6: INST-002 | B6: Abuja SolarCare Engineering | C6: Amina Bello | D6: 08000000002 | E6: info@abujasolarcare.example | F6: Abuja FCT | G6: Abuja | H6: Home; Hospital; School; Commercial | I6: 3 | J6: 30 | K6: Strong | L6: Yes | M6: Yes | N6: No | O6: Yes | P6: 8 | Q6: 120 | R6: SMA; Deye; Pylontech; Jinko | S6: Strong | T6: 24-48 hours | U6: Premium | V6: Excellent | W6: Good | X6: Good | Y6: Approved | Z6: Good for critical backup and Abuja projects.
A7: INST-003 | B7: Ogun Industrial Energy Works | C7: Segun Cole | D7: 08000000003 | E7: projects@ogunenergy.example | F7: Ogun; Lagos | G7: Abeokuta; Sagamu; Ikeja | H7: Factory; Commercial; School | I7: 10 | J7: 100 | K7: Moderate | L7: Yes | M7: Yes | N7: Yes | O7: No | P7: 10 | Q7: 70 | R7: Huawei; Deye; Longi; BYD | S7: Good | T7: 2-3 days | U7: Mid-range | V7: Good | W7: Good | X7: Acceptable | Y7: Approved | Z7: Good for warehouses and light factory loads.
A8: INST-004 | B8: Rivers Reliable Solar | C8: Ima Peters | D8: 08000000004 | E8: hello@riversreliable.example | F8: Rivers; Akwa Ibom | G8: Port Harcourt; Uyo | H8: Home; Hotel; Commercial; Hospital | I8: 5 | J8: 50 | K8: Strong | L8: Yes | M8: Yes | N8: No | O8: Yes | P8: 7 | Q8: 60 | R8: Deye; Must; Canadian Solar | S8: Good | T8: 24-48 hours | U8: Mid-range | V8: Good | W8: Good | X8: Good | Y8: Approved | Z8: Useful for Port Harcourt hotel/clinic projects.
A9: INST-005 | B9: Budget Solar Installers NG | C9: John Okoro | D9: 08000000005 | E9: sales@budgetsolar.example | F9: Lagos | G9: Surulere; Yaba; Ikeja | H9: Home; Commercial | I9: 1 | J9: 8 | K9: Basic | L9: No | M9: Some | N9: No | O9: No | P9: 3 | Q9: 45 | R9: Growatt; Felicity; Trina | S9: Basic | T9: Same day | U9: Budget | V9: Acceptable | W9: Average | X9: Acceptable | Y9: Approved | Z9: Best for small simple systems only.
A10: INST-006 | B10: Prime Critical Power Systems | C10: Fatima Usman | D10: 08000000006 | E10: support@primecritical.example | F10: Abuja FCT; Kano; Kaduna | G10: Abuja; Kano; Kaduna | H10: Hospital; Factory; School; Commercial | I10: 10 | J10: 150 | K10: Strong | L10: Yes | M10: Yes | N10: Yes | O10: Yes | P10: 12 | Q10: 150 | R10: SMA; Schneider; Huawei; CATL | S10: Strong | T10: 24-48 hours | U10: Premium | V10: Excellent | W10: Excellent | X10: Good | Y10: Preferred | Z10: High capability for hospitals and larger sites.
A11: INST-007
A12: INST-008
A13: INST-009
A14: INST-010
A15: INST-011
A16: INST-012
A17: INST-013
A18: INST-014
A19: INST-015
A20: INST-016
A21: INST-017
A22: INST-018
... A104: INST-100

Sheet Match_Engine
A4: Installer ID | B4: Approval Status | C4: Installer Name | D4: Location Score | E4: Category Score | F4: Size Score | G4: Technical Quality Score | H4: Battery/Hybrid Score | I4: Reliability Score | J4: Warranty Score | K4: Response Score | L4: Pricing Score | M4: Total Raw Score | N4: Max Score | O4: Match % | P4: Match Tier | Q4: Recommended? | R4: Customer-Facing Reason | S4: Internal Notes | T4: Result Rank
A5: =[1]Installer_Database!A5 -> INST-001 | B5: =Installer_Database!Y5 -> Preferred | C5: =Installer_Database!B5 -> Lagos Hybrid Power Ltd | D5: =IF(C5="","",IF(ISNUMBER(SEARCH(Customer_Profile!$B$11,Installer_Database!G5)),15,IF(ISNUMBER(SEARCH(Customer_Profile!$B$10,Installer_Database!F5)),12,IF(ISNUMBER(SEARCH("National",Installer_Database!F5)),7,0)))) -> 15 | E5: =IF(C5="","",IF(ISNUMBER(SEARCH(Customer_Profile!$B$8,Installer_Database!H5)),15,IF(OR(AND(Customer_Profile!$B$8="Hospital",ISNUMBER(SEARCH("Commercial",Installer_Database!H5))),AND(Customer_Profile!$B$8="Hotel",ISNUMBER(SEARCH("Commercial",Installer_Database!H5))),AND(Customer_Profile!$B$8="School",ISNUMBER(SEARCH("Commercial",Installer_Database!H5)))),8,0))) -> 15 | F5: =IF(C5="","",IFERROR(IF(VALUE(LEFT(Customer_Profile!$B$19,FIND("-",Customer_Profile!$B$19&"-")-1))<=Installer_Database!J5,15,IF(VALUE(LEFT(Customer_Profile!$B$19,FIND("-",Customer_Profile!$B$19&"-")-1))<=Installer_Database!J5*1.25,10,5)),8)) -> 15 | G5: =IF(C5="","",IF(Installer_Database!V5="Excellent",15,IF(Installer_Database!V5="Good",12,IF(Installer_Database!V5="Acceptable",8,IF(Installer_Database!V5="Weak",4,IF(Installer_Database!V5="Unverified",5,5)))))) -> 12 | H5: =IF(C5="","",IF(Installer_Database!K5="Strong",10,IF(Installer_Database!K5="Moderate",7,IF(Installer_Database!K5="Basic",4,IF(Installer_Database!K5="No",0,5))))) -> 10 | I5: =IF(C5="","",IF(Installer_Database!W5="Excellent",10,IF(Installer_Database!W5="Good",8,IF(Installer_Database!W5="Acceptable",5,IF(Installer_Database!W5="Weak",2,IF(Installer_Database!W5="Unverified",4,4)))))) -> 10 | J5: =IF(C5="","",IF(Installer_Database!S5="Excellent",10,IF(Installer_Database!S5="Good",8,IF(Installer_Database!S5="Acceptable",5,IF(Installer_Database!S5="Weak",2,IF(Installer_Database!S5="Unverified",4,IF(Installer_Database!S5="Strong",10,IF(Installer_Database!S5="Basic",5,4)))))))) -> 10 | K5: =IF(C5="","",IF(Installer_Database!T5="Same day",5,IF(Installer_Database!T5="24-48 hours",4,IF(Installer_Database!T5="2-3 days",3,IF(Installer_Database!T5="Slow",1,2))))) -> 5 | L5: =IF(C5="","",IF(Installer_Database!U5=Customer_Profile!$B$12,5,IF(OR(Installer_Database!U5="Mid-range",Customer_Profile!$B$12="Unknown"),3,1))) -> 5 | M5: =IF(C5="","",SUM(D5:L5)) -> 97 | N5: =100 -> 100 | O5: =IF(C5="","",M5/N5) -> 0.97 | P5: =IF(C5="","",IF(O5>=0.85,"Excellent Match",IF(O5>=0.7,"Good Match",IF(O5>=0.55,"Possible Match","Do Not Recommend")))) -> Excellent Match | Q5: =IF(C5="","",IF(AND(O5>=0.7,OR(B5="Approved",B5="Preferred")),"Yes","No")) -> Yes | R5: =IF(C5="","",IF(LEN(IF(D5>=12,"; serves your location","") &IF(E5>=15,"; experienced in your project type",IF(E5>=8,"; related project experience","")) &IF(H5>=7,"; good battery/hybrid capability","") &IF(J5>=8,"; strong after-sales support",""))=0,"", MID(IF(D5>=12,"; serves your location","") &IF(E5>=15,"; experienced in your project type",IF(E5>=8,"; related project experience","")) &IF(H5>=7,"; good battery/hybrid capability","") &IF(J5>=8,"; strong after-sales support",""),3,999))) -> serves your location; experienced in your project type; good battery/hybrid capability; strong after-sales support | S5: =IF(C5="","",Installer_Database!Z5) -> Strong residential and SME hybrid delivery. | T5: =IFERROR(RANK(O5,$O$5:$O$104,0),"") -> 1
A6: =[1]Installer_Database!A6 -> INST-002 | B6: =Installer_Database!Y6 -> Approved | C6: =Installer_Database!B6 -> Abuja SolarCare Engineering | D6: =IF(C6="","",IF(ISNUMBER(SEARCH(Customer_Profile!$B$11,Installer_Database!G6)),15,IF(ISNUMBER(SEARCH(Customer_Profile!$B$10,Installer_Database!F6)),12,IF(ISNUMBER(SEARCH("National",Installer_Database!F6)),7,0)))) -> 15 | E6: =IF(C6="","",IF(ISNUMBER(SEARCH(Customer_Profile!$B$8,Installer_Database!H6)),15,IF(OR(AND(Customer_Profile!$B$8="Hospital",ISNUMBER(SEARCH("Commercial",Installer_Database!H6))),AND(Customer_Profile!$B$8="Hotel",ISNUMBER(SEARCH("Commercial",Installer_Database!H6))),AND(Customer_Profile!$B$8="School",ISNUMBER(SEARCH("Commercial",Installer_Database!H6)))),8,0))) -> 15 | F6: =IF(C6="","",IFERROR(IF(VALUE(LEFT(Customer_Profile!$B$19,FIND("-",Customer_Profile!$B$19&"-")-1))<=Installer_Database!J6,15,IF(VALUE(LEFT(Customer_Profile!$B$19,FIND("-",Customer_Profile!$B$19&"-")-1))<=Installer_Database!J6*1.25,10,5)),8)) -> 15 | G6: =IF(C6="","",IF(Installer_Database!V6="Excellent",15,IF(Installer_Database!V6="Good",12,IF(Installer_Database!V6="Acceptable",8,IF(Installer_Database!V6="Weak",4,IF(Installer_Database!V6="Unverified",5,5)))))) -> 15 | H6: =IF(C6="","",IF(Installer_Database!K6="Strong",10,IF(Installer_Database!K6="Moderate",7,IF(Installer_Database!K6="Basic",4,IF(Installer_Database!K6="No",0,5))))) -> 10 | I6: =IF(C6="","",IF(Installer_Database!W6="Excellent",10,IF(Installer_Database!W6="Good",8,IF(Installer_Database!W6="Acceptable",5,IF(Installer_Database!W6="Weak",2,IF(Installer_Database!W6="Unverified",4,4)))))) -> 8 | J6: =IF(C6="","",IF(Installer_Database!S6="Excellent",10,IF(Installer_Database!S6="Good",8,IF(Installer_Database!S6="Acceptable",5,IF(Installer_Database!S6="Weak",2,IF(Installer_Database!S6="Unverified",4,IF(Installer_Database!S6="Strong",10,IF(Installer_Database!S6="Basic",5,4)))))))) -> 10 | K6: =IF(C6="","",IF(Installer_Database!T6="Same day",5,IF(Installer_Database!T6="24-48 hours",4,IF(Installer_Database!T6="2-3 days",3,IF(Installer_Database!T6="Slow",1,2))))) -> 4 | L6: =IF(C6="","",IF(Installer_Database!U6=Customer_Profile!$B$12,5,IF(OR(Installer_Database!U6="Mid-range",Customer_Profile!$B$12="Unknown"),3,1))) -> 1 | M6: =IF(C6="","",SUM(D6:L6)) -> 93 | N6: =100 -> 100 | O6: =IF(C6="","",M6/N6) -> 0.93 | P6: =IF(C6="","",IF(O6>=0.85,"Excellent Match",IF(O6>=0.7,"Good Match",IF(O6>=0.55,"Possible Match","Do Not Recommend")))) -> Excellent Match | Q6: =IF(C6="","",IF(AND(O6>=0.7,OR(B6="Approved",B6="Preferred")),"Yes","No")) -> Yes | R6: =IF(C6="","",IF(LEN(IF(D6>=12,"; serves your location","") &IF(E6>=15,"; experienced in your project type",IF(E6>=8,"; related project experience","")) &IF(H6>=7,"; good battery/hybrid capability","") &IF(J6>=8,"; strong after-sales support",""))=0,"", MID(IF(D6>=12,"; serves your location","") &IF(E6>=15,"; experienced in your project type",IF(E6>=8,"; related project experience","")) &IF(H6>=7,"; good battery/hybrid capability","") &IF(J6>=8,"; strong after-sales support",""),3,999))) -> serves your location; experienced in your project type; good battery/hybrid capability; strong after-sales support | S6: =IF(C6="","",Installer_Database!Z6) -> Good for critical backup and Abuja projects. | T6: =IFERROR(RANK(O6,$O$5:$O$104,0),"") -> 2
A7: =[1]Installer_Database!A7 -> INST-003 | B7: =Installer_Database!Y7 -> Approved | C7: =Installer_Database!B7 -> Ogun Industrial Energy Works | D7: =IF(C7="","",IF(ISNUMBER(SEARCH(Customer_Profile!$B$11,Installer_Database!G7)),15,IF(ISNUMBER(SEARCH(Customer_Profile!$B$10,Installer_Database!F7)),12,IF(ISNUMBER(SEARCH("National",Installer_Database!F7)),7,0)))) -> 15 | E7: =IF(C7="","",IF(ISNUMBER(SEARCH(Customer_Profile!$B$8,Installer_Database!H7)),15,IF(OR(AND(Customer_Profile!$B$8="Hospital",ISNUMBER(SEARCH("Commercial",Installer_Database!H7))),AND(Customer_Profile!$B$8="Hotel",ISNUMBER(SEARCH("Commercial",Installer_Database!H7))),AND(Customer_Profile!$B$8="School",ISNUMBER(SEARCH("Commercial",Installer_Database!H7)))),8,0))) -> 0 | F7: =IF(C7="","",IFERROR(IF(VALUE(LEFT(Customer_Profile!$B$19,FIND("-",Customer_Profile!$B$19&"-")-1))<=Installer_Database!J7,15,IF(VALUE(LEFT(Customer_Profile!$B$19,FIND("-",Customer_Profile!$B$19&"-")-1))<=Installer_Database!J7*1.25,10,5)),8)) -> 15 | G7: =IF(C7="","",IF(Installer_Database!V7="Excellent",15,IF(Installer_Database!V7="Good",12,IF(Installer_Database!V7="Acceptable",8,IF(Installer_Database!V7="Weak",4,IF(Installer_Database!V7="Unverified",5,5)))))) -> 12 | H7: =IF(C7="","",IF(Installer_Database!K7="Strong",10,IF(Installer_Database!K7="Moderate",7,IF(Installer_Database!K7="Basic",4,IF(Installer_Database!K7="No",0,5))))) -> 7 | I7: =IF(C7="","",IF(Installer_Database!W7="Excellent",10,IF(Installer_Database!W7="Good",8,IF(Installer_Database!W7="Acceptable",5,IF(Installer_Database!W7="Weak",2,IF(Installer_Database!W7="Unverified",4,4)))))) -> 8 | J7: =IF(C7="","",IF(Installer_Database!S7="Excellent",10,IF(Installer_Database!S7="Good",8,IF(Installer_Database!S7="Acceptable",5,IF(Installer_Database!S7="Weak",2,IF(Installer_Database!S7="Unverified",4,IF(Installer_Database!S7="Strong",10,IF(Installer_Database!S7="Basic",5,4)))))))) -> 8 | K7: =IF(C7="","",IF(Installer_Database!T7="Same day",5,IF(Installer_Database!T7="24-48 hours",4,IF(Installer_Database!T7="2-3 days",3,IF(Installer_Database!T7="Slow",1,2))))) -> 3 | L7: =IF(C7="","",IF(Installer_Database!U7=Customer_Profile!$B$12,5,IF(OR(Installer_Database!U7="Mid-range",Customer_Profile!$B$12="Unknown"),3,1))) -> 5 | M7: =IF(C7="","",SUM(D7:L7)) -> 73 | N7: =100 -> 100 | O7: =IF(C7="","",M7/N7) -> 0.73 | P7: =IF(C7="","",IF(O7>=0.85,"Excellent Match",IF(O7>=0.7,"Good Match",IF(O7>=0.55,"Possible Match","Do Not Recommend")))) -> Good Match | Q7: =IF(C7="","",IF(AND(O7>=0.7,OR(B7="Approved",B7="Preferred")),"Yes","No")) -> Yes | R7: =IF(C7="","",IF(LEN(IF(D7>=12,"; serves your location","") &IF(E7>=15,"; experienced in your project type",IF(E7>=8,"; related project experience","")) &IF(H7>=7,"; good battery/hybrid capability","") &IF(J7>=8,"; strong after-sales support",""))=0,"", MID(IF(D7>=12,"; serves your location","") &IF(E7>=15,"; experienced in your project type",IF(E7>=8,"; related project experience","")) &IF(H7>=7,"; good battery/hybrid capability","") &IF(J7>=8,"; strong after-sales support",""),3,999))) -> serves your location; good battery/hybrid capability; strong after-sales support | S7: =IF(C7="","",Installer_Database!Z7) -> Good for warehouses and light factory loads. | T7: =IFERROR(RANK(O7,$O$5:$O$104,0),"") -> 5
A8: =[1]Installer_Database!A8 -> INST-004 | B8: =Installer_Database!Y8 -> Approved | C8: =Installer_Database!B8 -> Rivers Reliable Solar | D8: =IF(C8="","",IF(ISNUMBER(SEARCH(Customer_Profile!$B$11,Installer_Database!G8)),15,IF(ISNUMBER(SEARCH(Customer_Profile!$B$10,Installer_Database!F8)),12,IF(ISNUMBER(SEARCH("National",Installer_Database!F8)),7,0)))) -> 15 | E8: =IF(C8="","",IF(ISNUMBER(SEARCH(Customer_Profile!$B$8,Installer_Database!H8)),15,IF(OR(AND(Customer_Profile!$B$8="Hospital",ISNUMBER(SEARCH("Commercial",Installer_Database!H8))),AND(Customer_Profile!$B$8="Hotel",ISNUMBER(SEARCH("Commercial",Installer_Database!H8))),AND(Customer_Profile!$B$8="School",ISNUMBER(SEARCH("Commercial",Installer_Database!H8)))),8,0))) -> 15 | F8: =IF(C8="","",IFERROR(IF(VALUE(LEFT(Customer_Profile!$B$19,FIND("-",Customer_Profile!$B$19&"-")-1))<=Installer_Database!J8,15,IF(VALUE(LEFT(Customer_Profile!$B$19,FIND("-",Customer_Profile!$B$19&"-")-1))<=Installer_Database!J8*1.25,10,5)),8)) -> 15 | G8: =IF(C8="","",IF(Installer_Database!V8="Excellent",15,IF(Installer_Database!V8="Good",12,IF(Installer_Database!V8="Acceptable",8,IF(Installer_Database!V8="Weak",4,IF(Installer_Database!V8="Unverified",5,5)))))) -> 12 | H8: =IF(C8="","",IF(Installer_Database!K8="Strong",10,IF(Installer_Database!K8="Moderate",7,IF(Installer_Database!K8="Basic",4,IF(Installer_Database!K8="No",0,5))))) -> 10 | I8: =IF(C8="","",IF(Installer_Database!W8="Excellent",10,IF(Installer_Database!W8="Good",8,IF(Installer_Database!W8="Acceptable",5,IF(Installer_Database!W8="Weak",2,IF(Installer_Database!W8="Unverified",4,4)))))) -> 8 | J8: =IF(C8="","",IF(Installer_Database!S8="Excellent",10,IF(Installer_Database!S8="Good",8,IF(Installer_Database!S8="Acceptable",5,IF(Installer_Database!S8="Weak",2,IF(Installer_Database!S8="Unverified",4,IF(Installer_Database!S8="Strong",10,IF(Installer_Database!S8="Basic",5,4)))))))) -> 8 | K8: =IF(C8="","",IF(Installer_Database!T8="Same day",5,IF(Installer_Database!T8="24-48 hours",4,IF(Installer_Database!T8="2-3 days",3,IF(Installer_Database!T8="Slow",1,2))))) -> 4 | L8: =IF(C8="","",IF(Installer_Database!U8=Customer_Profile!$B$12,5,IF(OR(Installer_Database!U8="Mid-range",Customer_Profile!$B$12="Unknown"),3,1))) -> 5 | M8: =IF(C8="","",SUM(D8:L8)) -> 92 | N8: =100 -> 100 | O8: =IF(C8="","",M8/N8) -> 0.92 | P8: =IF(C8="","",IF(O8>=0.85,"Excellent Match",IF(O8>=0.7,"Good Match",IF(O8>=0.55,"Possible Match","Do Not Recommend")))) -> Excellent Match | Q8: =IF(C8="","",IF(AND(O8>=0.7,OR(B8="Approved",B8="Preferred")),"Yes","No")) -> Yes | R8: =IF(C8="","",IF(LEN(IF(D8>=12,"; serves your location","") &IF(E8>=15,"; experienced in your project type",IF(E8>=8,"; related project experience","")) &IF(H8>=7,"; good battery/hybrid capability","") &IF(J8>=8,"; strong after-sales support",""))=0,"", MID(IF(D8>=12,"; serves your location","") &IF(E8>=15,"; experienced in your project type",IF(E8>=8,"; related project experience","")) &IF(H8>=7,"; good battery/hybrid capability","") &IF(J8>=8,"; strong after-sales support",""),3,999))) -> serves your location; experienced in your project type; good battery/hybrid capability; strong after-sales support | S8: =IF(C8="","",Installer_Database!Z8) -> Useful for Port Harcourt hotel/clinic projects. | T8: =IFERROR(RANK(O8,$O$5:$O$104,0),"") -> 3
A9: =[1]Installer_Database!A9 -> INST-005 | B9: =Installer_Database!Y9 -> Approved | C9: =Installer_Database!B9 -> Budget Solar Installers NG | D9: =IF(C9="","",IF(ISNUMBER(SEARCH(Customer_Profile!$B$11,Installer_Database!G9)),15,IF(ISNUMBER(SEARCH(Customer_Profile!$B$10,Installer_Database!F9)),12,IF(ISNUMBER(SEARCH("National",Installer_Database!F9)),7,0)))) -> 15 | E9: =IF(C9="","",IF(ISNUMBER(SEARCH(Customer_Profile!$B$8,Installer_Database!H9)),15,IF(OR(AND(Customer_Profile!$B$8="Hospital",ISNUMBER(SEARCH("Commercial",Installer_Database!H9))),AND(Customer_Profile!$B$8="Hotel",ISNUMBER(SEARCH("Commercial",Installer_Database!H9))),AND(Customer_Profile!$B$8="School",ISNUMBER(SEARCH("Commercial",Installer_Database!H9)))),8,0))) -> 15 | F9: =IF(C9="","",IFERROR(IF(VALUE(LEFT(Customer_Profile!$B$19,FIND("-",Customer_Profile!$B$19&"-")-1))<=Installer_Database!J9,15,IF(VALUE(LEFT(Customer_Profile!$B$19,FIND("-",Customer_Profile!$B$19&"-")-1))<=Installer_Database!J9*1.25,10,5)),8)) -> 15 | G9: =IF(C9="","",IF(Installer_Database!V9="Excellent",15,IF(Installer_Database!V9="Good",12,IF(Installer_Database!V9="Acceptable",8,IF(Installer_Database!V9="Weak",4,IF(Installer_Database!V9="Unverified",5,5)))))) -> 8 | H9: =IF(C9="","",IF(Installer_Database!K9="Strong",10,IF(Installer_Database!K9="Moderate",7,IF(Installer_Database!K9="Basic",4,IF(Installer_Database!K9="No",0,5))))) -> 4 | I9: =IF(C9="","",IF(Installer_Database!W9="Excellent",10,IF(Installer_Database!W9="Good",8,IF(Installer_Database!W9="Acceptable",5,IF(Installer_Database!W9="Weak",2,IF(Installer_Database!W9="Unverified",4,4)))))) -> 4 | J9: =IF(C9="","",IF(Installer_Database!S9="Excellent",10,IF(Installer_Database!S9="Good",8,IF(Installer_Database!S9="Acceptable",5,IF(Installer_Database!S9="Weak",2,IF(Installer_Database!S9="Unverified",4,IF(Installer_Database!S9="Strong",10,IF(Installer_Database!S9="Basic",5,4)))))))) -> 5 | K9: =IF(C9="","",IF(Installer_Database!T9="Same day",5,IF(Installer_Database!T9="24-48 hours",4,IF(Installer_Database!T9="2-3 days",3,IF(Installer_Database!T9="Slow",1,2))))) -> 5 | L9: =IF(C9="","",IF(Installer_Database!U9=Customer_Profile!$B$12,5,IF(OR(Installer_Database!U9="Mid-range",Customer_Profile!$B$12="Unknown"),3,1))) -> 1 | M9: =IF(C9="","",SUM(D9:L9)) -> 72 | N9: =100 -> 100 | O9: =IF(C9="","",M9/N9) -> 0.72 | P9: =IF(C9="","",IF(O9>=0.85,"Excellent Match",IF(O9>=0.7,"Good Match",IF(O9>=0.55,"Possible Match","Do Not Recommend")))) -> Good Match | Q9: =IF(C9="","",IF(AND(O9>=0.7,OR(B9="Approved",B9="Preferred")),"Yes","No")) -> Yes | R9: =IF(C9="","",IF(LEN(IF(D9>=12,"; serves your location","") &IF(E9>=15,"; experienced in your project type",IF(E9>=8,"; related project experience","")) &IF(H9>=7,"; good battery/hybrid capability","") &IF(J9>=8,"; strong after-sales support",""))=0,"", MID(IF(D9>=12,"; serves your location","") &IF(E9>=15,"; experienced in your project type",IF(E9>=8,"; related project experience","")) &IF(H9>=7,"; good battery/hybrid capability","") &IF(J9>=8,"; strong after-sales support",""),3,999))) -> serves your location; experienced in your project type | S9: =IF(C9="","",Installer_Database!Z9) -> Best for small simple systems only. | T9: =IFERROR(RANK(O9,$O$5:$O$104,0),"") -> 6
A10: =[1]Installer_Database!A10 -> INST-006 | B10: =Installer_Database!Y10 -> Preferred | C10: =Installer_Database!B10 -> Prime Critical Power Systems | D10: =IF(C10="","",IF(ISNUMBER(SEARCH(Customer_Profile!$B$11,Installer_Database!G10)),15,IF(ISNUMBER(SEARCH(Customer_Profile!$B$10,Installer_Database!F10)),12,IF(ISNUMBER(SEARCH("National",Installer_Database!F10)),7,0)))) -> 15 | E10: =IF(C10="","",IF(ISNUMBER(SEARCH(Customer_Profile!$B$8,Installer_Database!H10)),15,IF(OR(AND(Customer_Profile!$B$8="Hospital",ISNUMBER(SEARCH("Commercial",Installer_Database!H10))),AND(Customer_Profile!$B$8="Hotel",ISNUMBER(SEARCH("Commercial",Installer_Database!H10))),AND(Customer_Profile!$B$8="School",ISNUMBER(SEARCH("Commercial",Installer_Database!H10)))),8,0))) -> 0 | F10: =IF(C10="","",IFERROR(IF(VALUE(LEFT(Customer_Profile!$B$19,FIND("-",Customer_Profile!$B$19&"-")-1))<=Installer_Database!J10,15,IF(VALUE(LEFT(Customer_Profile!$B$19,FIND("-",Customer_Profile!$B$19&"-")-1))<=Installer_Database!J10*1.25,10,5)),8)) -> 15 | G10: =IF(C10="","",IF(Installer_Database!V10="Excellent",15,IF(Installer_Database!V10="Good",12,IF(Installer_Database!V10="Acceptable",8,IF(Installer_Database!V10="Weak",4,IF(Installer_Database!V10="Unverified",5,5)))))) -> 15 | H10: =IF(C10="","",IF(Installer_Database!K10="Strong",10,IF(Installer_Database!K10="Moderate",7,IF(Installer_Database!K10="Basic",4,IF(Installer_Database!K10="No",0,5))))) -> 10 | I10: =IF(C10="","",IF(Installer_Database!W10="Excellent",10,IF(Installer_Database!W10="Good",8,IF(Installer_Database!W10="Acceptable",5,IF(Installer_Database!W10="Weak",2,IF(Installer_Database!W10="Unverified",4,4)))))) -> 10 | J10: =IF(C10="","",IF(Installer_Database!S10="Excellent",10,IF(Installer_Database!S10="Good",8,IF(Installer_Database!S10="Acceptable",5,IF(Installer_Database!S10="Weak",2,IF(Installer_Database!S10="Unverified",4,IF(Installer_Database!S10="Strong",10,IF(Installer_Database!S10="Basic",5,4)))))))) -> 10 | K10: =IF(C10="","",IF(Installer_Database!T10="Same day",5,IF(Installer_Database!T10="24-48 hours",4,IF(Installer_Database!T10="2-3 days",3,IF(Installer_Database!T10="Slow",1,2))))) -> 4 | L10: =IF(C10="","",IF(Installer_Database!U10=Customer_Profile!$B$12,5,IF(OR(Installer_Database!U10="Mid-range",Customer_Profile!$B$12="Unknown"),3,1))) -> 1 | M10: =IF(C10="","",SUM(D10:L10)) -> 80 | N10: =100 -> 100 | O10: =IF(C10="","",M10/N10) -> 0.8 | P10: =IF(C10="","",IF(O10>=0.85,"Excellent Match",IF(O10>=0.7,"Good Match",IF(O10>=0.55,"Possible Match","Do Not Recommend")))) -> Good Match | Q10: =IF(C10="","",IF(AND(O10>=0.7,OR(B10="Approved",B10="Preferred")),"Yes","No")) -> Yes | R10: =IF(C10="","",IF(LEN(IF(D10>=12,"; serves your location","") &IF(E10>=15,"; experienced in your project type",IF(E10>=8,"; related project experience","")) &IF(H10>=7,"; good battery/hybrid capability","") &IF(J10>=8,"; strong after-sales support",""))=0,"", MID(IF(D10>=12,"; serves your location","") &IF(E10>=15,"; experienced in your project type",IF(E10>=8,"; related project experience","")) &IF(H10>=7,"; good battery/hybrid capability","") &IF(J10>=8,"; strong after-sales support",""),3,999))) -> serves your location; good battery/hybrid capability; strong after-sales support | S10: =IF(C10="","",Installer_Database!Z10) -> High capability for hospitals and larger sites. | T10: =IFERROR(RANK(O10,$O$5:$O$104,0),"") -> 4
A11: =[1]Installer_Database!A11 -> INST-007 | B11: =Installer_Database!Y11 -> 0 | C11: =Installer_Database!B11 -> 0 | D11: =IF(C11="","",IF(ISNUMBER(SEARCH(Customer_Profile!$B$11,Installer_Database!G11)),15,IF(ISNUMBER(SEARCH(Customer_Profile!$B$10,Installer_Database!F11)),12,IF(ISNUMBER(SEARCH("National",Installer_Database!F11)),7,0)))) -> 0 | E11: =IF(C11="","",IF(ISNUMBER(SEARCH(Customer_Profile!$B$8,Installer_Database!H11)),15,IF(OR(AND(Customer_Profile!$B$8="Hospital",ISNUMBER(SEARCH("Commercial",Installer_Database!H11))),AND(Customer_Profile!$B$8="Hotel",ISNUMBER(SEARCH("Commercial",Installer_Database!H11))),AND(Customer_Profile!$B$8="School",ISNUMBER(SEARCH("Commercial",Installer_Database!H11)))),8,0))) -> 0 | F11: =IF(C11="","",IFERROR(IF(VALUE(LEFT(Customer_Profile!$B$19,FIND("-",Customer_Profile!$B$19&"-")-1))<=Installer_Database!J11,15,IF(VALUE(LEFT(Customer_Profile!$B$19,FIND("-",Customer_Profile!$B$19&"-")-1))<=Installer_Database!J11*1.25,10,5)),8)) -> 5 | G11: =IF(C11="","",IF(Installer_Database!V11="Excellent",15,IF(Installer_Database!V11="Good",12,IF(Installer_Database!V11="Acceptable",8,IF(Installer_Database!V11="Weak",4,IF(Installer_Database!V11="Unverified",5,5)))))) -> 5 | H11: =IF(C11="","",IF(Installer_Database!K11="Strong",10,IF(Installer_Database!K11="Moderate",7,IF(Installer_Database!K11="Basic",4,IF(Installer_Database!K11="No",0,5))))) -> 5 | I11: =IF(C11="","",IF(Installer_Database!W11="Excellent",10,IF(Installer_Database!W11="Good",8,IF(Installer_Database!W11="Acceptable",5,IF(Installer_Database!W11="Weak",2,IF(Installer_Database!W11="Unverified",4,4)))))) -> 4 | J11: =IF(C11="","",IF(Installer_Database!S11="Excellent",10,IF(Installer_Database!S11="Good",8,IF(Installer_Database!S11="Acceptable",5,IF(Installer_Database!S11="Weak",2,IF(Installer_Database!S11="Unverified",4,IF(Installer_Database!S11="Strong",10,IF(Installer_Database!S11="Basic",5,4)))))))) -> 4 | K11: =IF(C11="","",IF(Installer_Database!T11="Same day",5,IF(Installer_Database!T11="24-48 hours",4,IF(Installer_Database!T11="2-3 days",3,IF(Installer_Database!T11="Slow",1,2))))) -> 2 | L11: =IF(C11="","",IF(Installer_Database!U11=Customer_Profile!$B$12,5,IF(OR(Installer_Database!U11="Mid-range",Customer_Profile!$B$12="Unknown"),3,1))) -> 1 | M11: =IF(C11="","",SUM(D11:L11)) -> 26 | N11: =100 -> 100 | O11: =IF(C11="","",M11/N11) -> 0.26 | P11: =IF(C11="","",IF(O11>=0.85,"Excellent Match",IF(O11>=0.7,"Good Match",IF(O11>=0.55,"Possible Match","Do Not Recommend")))) -> Do Not Recommend | Q11: =IF(C11="","",IF(AND(O11>=0.7,OR(B11="Approved",B11="Preferred")),"Yes","No")) -> No | R11: =IF(C11="","",IF(LEN(IF(D11>=12,"; serves your location","") &IF(E11>=15,"; experienced in your project type",IF(E11>=8,"; related project experience","")) &IF(H11>=7,"; good battery/hybrid capability","") &IF(J11>=8,"; strong after-sales support",""))=0,"", MID(IF(D11>=12,"; serves your location","") &IF(E11>=15,"; experienced in your project type",IF(E11>=8,"; related project experience","")) &IF(H11>=7,"; good battery/hybrid capability","") &IF(J11>=8,"; strong after-sales support",""),3,999))) | S11: =IF(C11="","",Installer_Database!Z11) -> 0 | T11: =IFERROR(RANK(O11,$O$5:$O$104,0),"") -> 7
A12: =[1]Installer_Database!A12 -> INST-008 | B12: =Installer_Database!Y12 -> 0 | C12: =Installer_Database!B12 -> 0 | D12: =IF(C12="","",IF(ISNUMBER(SEARCH(Customer_Profile!$B$11,Installer_Database!G12)),15,IF(ISNUMBER(SEARCH(Customer_Profile!$B$10,Installer_Database!F12)),12,IF(ISNUMBER(SEARCH("National",Installer_Database!F12)),7,0)))) -> 0 | E12: =IF(C12="","",IF(ISNUMBER(SEARCH(Customer_Profile!$B$8,Installer_Database!H12)),15,IF(OR(AND(Customer_Profile!$B$8="Hospital",ISNUMBER(SEARCH("Commercial",Installer_Database!H12))),AND(Customer_Profile!$B$8="Hotel",ISNUMBER(SEARCH("Commercial",Installer_Database!H12))),AND(Customer_Profile!$B$8="School",ISNUMBER(SEARCH("Commercial",Installer_Database!H12)))),8,0))) -> 0 | F12: =IF(C12="","",IFERROR(IF(VALUE(LEFT(Customer_Profile!$B$19,FIND("-",Customer_Profile!$B$19&"-")-1))<=Installer_Database!J12,15,IF(VALUE(LEFT(Customer_Profile!$B$19,FIND("-",Customer_Profile!$B$19&"-")-1))<=Installer_Database!J12*1.25,10,5)),8)) -> 5 | G12: =IF(C12="","",IF(Installer_Database!V12="Excellent",15,IF(Installer_Database!V12="Good",12,IF(Installer_Database!V12="Acceptable",8,IF(Installer_Database!V12="Weak",4,IF(Installer_Database!V12="Unverified",5,5)))))) -> 5 | H12: =IF(C12="","",IF(Installer_Database!K12="Strong",10,IF(Installer_Database!K12="Moderate",7,IF(Installer_Database!K12="Basic",4,IF(Installer_Database!K12="No",0,5))))) -> 5 | I12: =IF(C12="","",IF(Installer_Database!W12="Excellent",10,IF(Installer_Database!W12="Good",8,IF(Installer_Database!W12="Acceptable",5,IF(Installer_Database!W12="Weak",2,IF(Installer_Database!W12="Unverified",4,4)))))) -> 4 | J12: =IF(C12="","",IF(Installer_Database!S12="Excellent",10,IF(Installer_Database!S12="Good",8,IF(Installer_Database!S12="Acceptable",5,IF(Installer_Database!S12="Weak",2,IF(Installer_Database!S12="Unverified",4,IF(Installer_Database!S12="Strong",10,IF(Installer_Database!S12="Basic",5,4)))))))) -> 4 | K12: =IF(C12="","",IF(Installer_Database!T12="Same day",5,IF(Installer_Database!T12="24-48 hours",4,IF(Installer_Database!T12="2-3 days",3,IF(Installer_Database!T12="Slow",1,2))))) -> 2 | L12: =IF(C12="","",IF(Installer_Database!U12=Customer_Profile!$B$12,5,IF(OR(Installer_Database!U12="Mid-range",Customer_Profile!$B$12="Unknown"),3,1))) -> 1 | M12: =IF(C12="","",SUM(D12:L12)) -> 26 | N12: =100 -> 100 | O12: =IF(C12="","",M12/N12) -> 0.26 | P12: =IF(C12="","",IF(O12>=0.85,"Excellent Match",IF(O12>=0.7,"Good Match",IF(O12>=0.55,"Possible Match","Do Not Recommend")))) -> Do Not Recommend | Q12: =IF(C12="","",IF(AND(O12>=0.7,OR(B12="Approved",B12="Preferred")),"Yes","No")) -> No | R12: =IF(C12="","",IF(LEN(IF(D12>=12,"; serves your location","") &IF(E12>=15,"; experienced in your project type",IF(E12>=8,"; related project experience","")) &IF(H12>=7,"; good battery/hybrid capability","") &IF(J12>=8,"; strong after-sales support",""))=0,"", MID(IF(D12>=12,"; serves your location","") &IF(E12>=15,"; experienced in your project type",IF(E12>=8,"; related project experience","")) &IF(H12>=7,"; good battery/hybrid capability","") &IF(J12>=8,"; strong after-sales support",""),3,999))) | S12: =IF(C12="","",Installer_Database!Z12) -> 0 | T12: =IFERROR(RANK(O12,$O$5:$O$104,0),"") -> 7
A13: =[1]Installer_Database!A13 -> INST-009 | B13: =Installer_Database!Y13 -> 0 | C13: =Installer_Database!B13 -> 0 | D13: =IF(C13="","",IF(ISNUMBER(SEARCH(Customer_Profile!$B$11,Installer_Database!G13)),15,IF(ISNUMBER(SEARCH(Customer_Profile!$B$10,Installer_Database!F13)),12,IF(ISNUMBER(SEARCH("National",Installer_Database!F13)),7,0)))) -> 0 | E13: =IF(C13="","",IF(ISNUMBER(SEARCH(Customer_Profile!$B$8,Installer_Database!H13)),15,IF(OR(AND(Customer_Profile!$B$8="Hospital",ISNUMBER(SEARCH("Commercial",Installer_Database!H13))),AND(Customer_Profile!$B$8="Hotel",ISNUMBER(SEARCH("Commercial",Installer_Database!H13))),AND(Customer_Profile!$B$8="School",ISNUMBER(SEARCH("Commercial",Installer_Database!H13)))),8,0))) -> 0 | F13: =IF(C13="","",IFERROR(IF(VALUE(LEFT(Customer_Profile!$B$19,FIND("-",Customer_Profile!$B$19&"-")-1))<=Installer_Database!J13,15,IF(VALUE(LEFT(Customer_Profile!$B$19,FIND("-",Customer_Profile!$B$19&"-")-1))<=Installer_Database!J13*1.25,10,5)),8)) -> 5 | G13: =IF(C13="","",IF(Installer_Database!V13="Excellent",15,IF(Installer_Database!V13="Good",12,IF(Installer_Database!V13="Acceptable",8,IF(Installer_Database!V13="Weak",4,IF(Installer_Database!V13="Unverified",5,5)))))) -> 5 | H13: =IF(C13="","",IF(Installer_Database!K13="Strong",10,IF(Installer_Database!K13="Moderate",7,IF(Installer_Database!K13="Basic",4,IF(Installer_Database!K13="No",0,5))))) -> 5 | I13: =IF(C13="","",IF(Installer_Database!W13="Excellent",10,IF(Installer_Database!W13="Good",8,IF(Installer_Database!W13="Acceptable",5,IF(Installer_Database!W13="Weak",2,IF(Installer_Database!W13="Unverified",4,4)))))) -> 4 | J13: =IF(C13="","",IF(Installer_Database!S13="Excellent",10,IF(Installer_Database!S13="Good",8,IF(Installer_Database!S13="Acceptable",5,IF(Installer_Database!S13="Weak",2,IF(Installer_Database!S13="Unverified",4,IF(Installer_Database!S13="Strong",10,IF(Installer_Database!S13="Basic",5,4)))))))) -> 4 | K13: =IF(C13="","",IF(Installer_Database!T13="Same day",5,IF(Installer_Database!T13="24-48 hours",4,IF(Installer_Database!T13="2-3 days",3,IF(Installer_Database!T13="Slow",1,2))))) -> 2 | L13: =IF(C13="","",IF(Installer_Database!U13=Customer_Profile!$B$12,5,IF(OR(Installer_Database!U13="Mid-range",Customer_Profile!$B$12="Unknown"),3,1))) -> 1 | M13: =IF(C13="","",SUM(D13:L13)) -> 26 | N13: =100 -> 100 | O13: =IF(C13="","",M13/N13) -> 0.26 | P13: =IF(C13="","",IF(O13>=0.85,"Excellent Match",IF(O13>=0.7,"Good Match",IF(O13>=0.55,"Possible Match","Do Not Recommend")))) -> Do Not Recommend | Q13: =IF(C13="","",IF(AND(O13>=0.7,OR(B13="Approved",B13="Preferred")),"Yes","No")) -> No | R13: =IF(C13="","",IF(LEN(IF(D13>=12,"; serves your location","") &IF(E13>=15,"; experienced in your project type",IF(E13>=8,"; related project experience","")) &IF(H13>=7,"; good battery/hybrid capability","") &IF(J13>=8,"; strong after-sales support",""))=0,"", MID(IF(D13>=12,"; serves your location","") &IF(E13>=15,"; experienced in your project type",IF(E13>=8,"; related project experience","")) &IF(H13>=7,"; good battery/hybrid capability","") &IF(J13>=8,"; strong after-sales support",""),3,999))) | S13: =IF(C13="","",Installer_Database!Z13) -> 0 | T13: =IFERROR(RANK(O13,$O$5:$O$104,0),"") -> 7
A14: =[1]Installer_Database!A14 -> INST-010 | B14: =Installer_Database!Y14 -> 0 | C14: =Installer_Database!B14 -> 0 | D14: =IF(C14="","",IF(ISNUMBER(SEARCH(Customer_Profile!$B$11,Installer_Database!G14)),15,IF(ISNUMBER(SEARCH(Customer_Profile!$B$10,Installer_Database!F14)),12,IF(ISNUMBER(SEARCH("National",Installer_Database!F14)),7,0)))) -> 0 | E14: =IF(C14="","",IF(ISNUMBER(SEARCH(Customer_Profile!$B$8,Installer_Database!H14)),15,IF(OR(AND(Customer_Profile!$B$8="Hospital",ISNUMBER(SEARCH("Commercial",Installer_Database!H14))),AND(Customer_Profile!$B$8="Hotel",ISNUMBER(SEARCH("Commercial",Installer_Database!H14))),AND(Customer_Profile!$B$8="School",ISNUMBER(SEARCH("Commercial",Installer_Database!H14)))),8,0))) -> 0 | F14: =IF(C14="","",IFERROR(IF(VALUE(LEFT(Customer_Profile!$B$19,FIND("-",Customer_Profile!$B$19&"-")-1))<=Installer_Database!J14,15,IF(VALUE(LEFT(Customer_Profile!$B$19,FIND("-",Customer_Profile!$B$19&"-")-1))<=Installer_Database!J14*1.25,10,5)),8)) -> 5 | G14: =IF(C14="","",IF(Installer_Database!V14="Excellent",15,IF(Installer_Database!V14="Good",12,IF(Installer_Database!V14="Acceptable",8,IF(Installer_Database!V14="Weak",4,IF(Installer_Database!V14="Unverified",5,5)))))) -> 5 | H14: =IF(C14="","",IF(Installer_Database!K14="Strong",10,IF(Installer_Database!K14="Moderate",7,IF(Installer_Database!K14="Basic",4,IF(Installer_Database!K14="No",0,5))))) -> 5 | I14: =IF(C14="","",IF(Installer_Database!W14="Excellent",10,IF(Installer_Database!W14="Good",8,IF(Installer_Database!W14="Acceptable",5,IF(Installer_Database!W14="Weak",2,IF(Installer_Database!W14="Unverified",4,4)))))) -> 4 | J14: =IF(C14="","",IF(Installer_Database!S14="Excellent",10,IF(Installer_Database!S14="Good",8,IF(Installer_Database!S14="Acceptable",5,IF(Installer_Database!S14="Weak",2,IF(Installer_Database!S14="Unverified",4,IF(Installer_Database!S14="Strong",10,IF(Installer_Database!S14="Basic",5,4)))))))) -> 4 | K14: =IF(C14="","",IF(Installer_Database!T14="Same day",5,IF(Installer_Database!T14="24-48 hours",4,IF(Installer_Database!T14="2-3 days",3,IF(Installer_Database!T14="Slow",1,2))))) -> 2 | L14: =IF(C14="","",IF(Installer_Database!U14=Customer_Profile!$B$12,5,IF(OR(Installer_Database!U14="Mid-range",Customer_Profile!$B$12="Unknown"),3,1))) -> 1 | M14: =IF(C14="","",SUM(D14:L14)) -> 26 | N14: =100 -> 100 | O14: =IF(C14="","",M14/N14) -> 0.26 | P14: =IF(C14="","",IF(O14>=0.85,"Excellent Match",IF(O14>=0.7,"Good Match",IF(O14>=0.55,"Possible Match","Do Not Recommend")))) -> Do Not Recommend | Q14: =IF(C14="","",IF(AND(O14>=0.7,OR(B14="Approved",B14="Preferred")),"Yes","No")) -> No | R14: =IF(C14="","",IF(LEN(IF(D14>=12,"; serves your location","") &IF(E14>=15,"; experienced in your project type",IF(E14>=8,"; related project experience","")) &IF(H14>=7,"; good battery/hybrid capability","") &IF(J14>=8,"; strong after-sales support",""))=0,"", MID(IF(D14>=12,"; serves your location","") &IF(E14>=15,"; experienced in your project type",IF(E14>=8,"; related project experience","")) &IF(H14>=7,"; good battery/hybrid capability","") &IF(J14>=8,"; strong after-sales support",""),3,999))) | S14: =IF(C14="","",Installer_Database!Z14) -> 0 | T14: =IFERROR(RANK(O14,$O$5:$O$104,0),"") -> 7
A15: =[1]Installer_Database!A15 -> INST-011 | B15: =Installer_Database!Y15 -> 0 | C15: =Installer_Database!B15 -> 0 | D15: =IF(C15="","",IF(ISNUMBER(SEARCH(Customer_Profile!$B$11,Installer_Database!G15)),15,IF(ISNUMBER(SEARCH(Customer_Profile!$B$10,Installer_Database!F15)),12,IF(ISNUMBER(SEARCH("National",Installer_Database!F15)),7,0)))) -> 0 | E15: =IF(C15="","",IF(ISNUMBER(SEARCH(Customer_Profile!$B$8,Installer_Database!H15)),15,IF(OR(AND(Customer_Profile!$B$8="Hospital",ISNUMBER(SEARCH("Commercial",Installer_Database!H15))),AND(Customer_Profile!$B$8="Hotel",ISNUMBER(SEARCH("Commercial",Installer_Database!H15))),AND(Customer_Profile!$B$8="School",ISNUMBER(SEARCH("Commercial",Installer_Database!H15)))),8,0))) -> 0 | F15: =IF(C15="","",IFERROR(IF(VALUE(LEFT(Customer_Profile!$B$19,FIND("-",Customer_Profile!$B$19&"-")-1))<=Installer_Database!J15,15,IF(VALUE(LEFT(Customer_Profile!$B$19,FIND("-",Customer_Profile!$B$19&"-")-1))<=Installer_Database!J15*1.25,10,5)),8)) -> 5 | G15: =IF(C15="","",IF(Installer_Database!V15="Excellent",15,IF(Installer_Database!V15="Good",12,IF(Installer_Database!V15="Acceptable",8,IF(Installer_Database!V15="Weak",4,IF(Installer_Database!V15="Unverified",5,5)))))) -> 5 | H15: =IF(C15="","",IF(Installer_Database!K15="Strong",10,IF(Installer_Database!K15="Moderate",7,IF(Installer_Database!K15="Basic",4,IF(Installer_Database!K15="No",0,5))))) -> 5 | I15: =IF(C15="","",IF(Installer_Database!W15="Excellent",10,IF(Installer_Database!W15="Good",8,IF(Installer_Database!W15="Acceptable",5,IF(Installer_Database!W15="Weak",2,IF(Installer_Database!W15="Unverified",4,4)))))) -> 4 | J15: =IF(C15="","",IF(Installer_Database!S15="Excellent",10,IF(Installer_Database!S15="Good",8,IF(Installer_Database!S15="Acceptable",5,IF(Installer_Database!S15="Weak",2,IF(Installer_Database!S15="Unverified",4,IF(Installer_Database!S15="Strong",10,IF(Installer_Database!S15="Basic",5,4)))))))) -> 4 | K15: =IF(C15="","",IF(Installer_Database!T15="Same day",5,IF(Installer_Database!T15="24-48 hours",4,IF(Installer_Database!T15="2-3 days",3,IF(Installer_Database!T15="Slow",1,2))))) -> 2 | L15: =IF(C15="","",IF(Installer_Database!U15=Customer_Profile!$B$12,5,IF(OR(Installer_Database!U15="Mid-range",Customer_Profile!$B$12="Unknown"),3,1))) -> 1 | M15: =IF(C15="","",SUM(D15:L15)) -> 26 | N15: =100 -> 100 | O15: =IF(C15="","",M15/N15) -> 0.26 | P15: =IF(C15="","",IF(O15>=0.85,"Excellent Match",IF(O15>=0.7,"Good Match",IF(O15>=0.55,"Possible Match","Do Not Recommend")))) -> Do Not Recommend | Q15: =IF(C15="","",IF(AND(O15>=0.7,OR(B15="Approved",B15="Preferred")),"Yes","No")) -> No | R15: =IF(C15="","",IF(LEN(IF(D15>=12,"; serves your location","") &IF(E15>=15,"; experienced in your project type",IF(E15>=8,"; related project experience","")) &IF(H15>=7,"; good battery/hybrid capability","") &IF(J15>=8,"; strong after-sales support",""))=0,"", MID(IF(D15>=12,"; serves your location","") &IF(E15>=15,"; experienced in your project type",IF(E15>=8,"; related project experience","")) &IF(H15>=7,"; good battery/hybrid capability","") &IF(J15>=8,"; strong after-sales support",""),3,999))) | S15: =IF(C15="","",Installer_Database!Z15) -> 0 | T15: =IFERROR(RANK(O15,$O$5:$O$104,0),"") -> 7
A16: =[1]Installer_Database!A16 -> INST-012 | B16: =Installer_Database!Y16 -> 0 | C16: =Installer_Database!B16 -> 0 | D16: =IF(C16="","",IF(ISNUMBER(SEARCH(Customer_Profile!$B$11,Installer_Database!G16)),15,IF(ISNUMBER(SEARCH(Customer_Profile!$B$10,Installer_Database!F16)),12,IF(ISNUMBER(SEARCH("National",Installer_Database!F16)),7,0)))) -> 0 | E16: =IF(C16="","",IF(ISNUMBER(SEARCH(Customer_Profile!$B$8,Installer_Database!H16)),15,IF(OR(AND(Customer_Profile!$B$8="Hospital",ISNUMBER(SEARCH("Commercial",Installer_Database!H16))),AND(Customer_Profile!$B$8="Hotel",ISNUMBER(SEARCH("Commercial",Installer_Database!H16))),AND(Customer_Profile!$B$8="School",ISNUMBER(SEARCH("Commercial",Installer_Database!H16)))),8,0))) -> 0 | F16: =IF(C16="","",IFERROR(IF(VALUE(LEFT(Customer_Profile!$B$19,FIND("-",Customer_Profile!$B$19&"-")-1))<=Installer_Database!J16,15,IF(VALUE(LEFT(Customer_Profile!$B$19,FIND("-",Customer_Profile!$B$19&"-")-1))<=Installer_Database!J16*1.25,10,5)),8)) -> 5 | G16: =IF(C16="","",IF(Installer_Database!V16="Excellent",15,IF(Installer_Database!V16="Good",12,IF(Installer_Database!V16="Acceptable",8,IF(Installer_Database!V16="Weak",4,IF(Installer_Database!V16="Unverified",5,5)))))) -> 5 | H16: =IF(C16="","",IF(Installer_Database!K16="Strong",10,IF(Installer_Database!K16="Moderate",7,IF(Installer_Database!K16="Basic",4,IF(Installer_Database!K16="No",0,5))))) -> 5 | I16: =IF(C16="","",IF(Installer_Database!W16="Excellent",10,IF(Installer_Database!W16="Good",8,IF(Installer_Database!W16="Acceptable",5,IF(Installer_Database!W16="Weak",2,IF(Installer_Database!W16="Unverified",4,4)))))) -> 4 | J16: =IF(C16="","",IF(Installer_Database!S16="Excellent",10,IF(Installer_Database!S16="Good",8,IF(Installer_Database!S16="Acceptable",5,IF(Installer_Database!S16="Weak",2,IF(Installer_Database!S16="Unverified",4,IF(Installer_Database!S16="Strong",10,IF(Installer_Database!S16="Basic",5,4)))))))) -> 4 | K16: =IF(C16="","",IF(Installer_Database!T16="Same day",5,IF(Installer_Database!T16="24-48 hours",4,IF(Installer_Database!T16="2-3 days",3,IF(Installer_Database!T16="Slow",1,2))))) -> 2 | L16: =IF(C16="","",IF(Installer_Database!U16=Customer_Profile!$B$12,5,IF(OR(Installer_Database!U16="Mid-range",Customer_Profile!$B$12="Unknown"),3,1))) -> 1 | M16: =IF(C16="","",SUM(D16:L16)) -> 26 | N16: =100 -> 100 | O16: =IF(C16="","",M16/N16) -> 0.26 | P16: =IF(C16="","",IF(O16>=0.85,"Excellent Match",IF(O16>=0.7,"Good Match",IF(O16>=0.55,"Possible Match","Do Not Recommend")))) -> Do Not Recommend | Q16: =IF(C16="","",IF(AND(O16>=0.7,OR(B16="Approved",B16="Preferred")),"Yes","No")) -> No | R16: =IF(C16="","",IF(LEN(IF(D16>=12,"; serves your location","") &IF(E16>=15,"; experienced in your project type",IF(E16>=8,"; related project experience","")) &IF(H16>=7,"; good battery/hybrid capability","") &IF(J16>=8,"; strong after-sales support",""))=0,"", MID(IF(D16>=12,"; serves your location","") &IF(E16>=15,"; experienced in your project type",IF(E16>=8,"; related project experience","")) &IF(H16>=7,"; good battery/hybrid capability","") &IF(J16>=8,"; strong after-sales support",""),3,999))) | S16: =IF(C16="","",Installer_Database!Z16) -> 0 | T16: =IFERROR(RANK(O16,$O$5:$O$104,0),"") -> 7
... A104: =[1]Installer_Database!A104 -> INST-100 | B104: =Installer_Database!Y104 -> 0 | C104: =Installer_Database!B104 -> 0 | D104: =IF(C104="","",IF(ISNUMBER(SEARCH(Customer_Profile!$B$11,Installer_Database!G104)),15,IF(ISNUMBER(SEARCH(Customer_Profile!$B$10,Installer_Database!F104)),12,IF(ISNUMBER(SEARCH("National",Installer_Database!F104)),7,0)))) -> 0 | E104: =IF(C104="","",IF(ISNUMBER(SEARCH(Customer_Profile!$B$8,Installer_Database!H104)),15,IF(OR(AND(Customer_Profile!$B$8="Hospital",ISNUMBER(SEARCH("Commercial",Installer_Database!H104))),AND(Customer_Profile!$B$8="Hotel",ISNUMBER(SEARCH("Commercial",Installer_Database!H104))),AND(Customer_Profile!$B$8="School",ISNUMBER(SEARCH("Commercial",Installer_Database!H104)))),8,0))) -> 0 | F104: =IF(C104="","",IFERROR(IF(VALUE(LEFT(Customer_Profile!$B$19,FIND("-",Customer_Profile!$B$19&"-")-1))<=Installer_Database!J104,15,IF(VALUE(LEFT(Customer_Profile!$B$19,FIND("-",Customer_Profile!$B$19&"-")-1))<=Installer_Database!J104*1.25,10,5)),8)) -> 5 | G104: =IF(C104="","",IF(Installer_Database!V104="Excellent",15,IF(Installer_Database!V104="Good",12,IF(Installer_Database!V104="Acceptable",8,IF(Installer_Database!V104="Weak",4,IF(Installer_Database!V104="Unverified",5,5)))))) -> 5 | H104: =IF(C104="","",IF(Installer_Database!K104="Strong",10,IF(Installer_Database!K104="Moderate",7,IF(Installer_Database!K104="Basic",4,IF(Installer_Database!K104="No",0,5))))) -> 5 | I104: =IF(C104="","",IF(Installer_Database!W104="Excellent",10,IF(Installer_Database!W104="Good",8,IF(Installer_Database!W104="Acceptable",5,IF(Installer_Database!W104="Weak",2,IF(Installer_Database!W104="Unverified",4,4)))))) -> 4 | J104: =IF(C104="","",IF(Installer_Database!S104="Excellent",10,IF(Installer_Database!S104="Good",8,IF(Installer_Database!S104="Acceptable",5,IF(Installer_Database!S104="Weak",2,IF(Installer_Database!S104="Unverified",4,IF(Installer_Database!S104="Strong",10,IF(Installer_Database!S104="Basic",5,4)))))))) -> 4 | K104: =IF(C104="","",IF(Installer_Database!T104="Same day",5,IF(Installer_Database!T104="24-48 hours",4,IF(Installer_Database!T104="2-3 days",3,IF(Installer_Database!T104="Slow",1,2))))) -> 2 | L104: =IF(C104="","",IF(Installer_Database!U104=Customer_Profile!$B$12,5,IF(OR(Installer_Database!U104="Mid-range",Customer_Profile!$B$12="Unknown"),3,1))) -> 1 | M104: =IF(C104="","",SUM(D104:L104)) -> 26 | N104: =100 -> 100 | O104: =IF(C104="","",M104/N104) -> 0.26 | P104: =IF(C104="","",IF(O104>=0.85,"Excellent Match",IF(O104>=0.7,"Good Match",IF(O104>=0.55,"Possible Match","Do Not Recommend")))) -> Do Not Recommend | Q104: =IF(C104="","",IF(AND(O104>=0.7,OR(B104="Approved",B104="Preferred")),"Yes","No")) -> No | R104: =IF(C104="","",IF(LEN(IF(D104>=12,"; serves your location","") &IF(E104>=15,"; experienced in your project type",IF(E104>=8,"; related project experience","")) &IF(H104>=7,"; good battery/hybrid capability","") &IF(J104>=8,"; strong after-sales support",""))=0,"", MID(IF(D104>=12,"; serves your location","") &IF(E104>=15,"; experienced in your project type",IF(E104>=8,"; related project experience","")) &IF(H104>=7,"; good battery/hybrid capability","") &IF(J104>=8,"; strong after-sales support",""),3,999))) | S104: =IF(C104="","",Installer_Database!Z104) -> 0 | T104: =IFERROR(RANK(O104,$O$5:$O$104,0),"") -> 7

Sheet Installer_Results_Output
A4: Customer Result Field | B4: Value | C4: Display Text
A5: Category | B5: =Customer_Profile!B5 -> SV-0001 | C5: =[1]Customer_Profile!B5 -> SV-0001
A6: Template | B6: =Customer_Profile!B6 -> John Peters | C6: =[1]Customer_Profile!B6 -> Example Customer
A7: Email | B7: =Customer_Profile!B7 -> jpeters234@gmail.com | C7: =Customer_Profile!B7 -> jpeters234@gmail.com
A8: Category | B8: =Customer_Profile!B8 -> Home | C8: =Customer_Profile!B8 -> Home
A9: Estimated Daily Load | B9: =TEXT(Customer_Profile!B16,"0.0") & " kWh/day" -> 8.1 kWh/day | C9: =TEXT(Customer_Profile!B16,"0.0") & " kWh/day" -> 8.1 kWh/day
A10: Suggested Solar | B10: =TEXT(Customer_Profile!B17,"0.0") & " kWp" -> 2.0 kWp | C10: =TEXT(Customer_Profile!B17,"0.0") & " kWp" -> 2.0 kWp
A11: Suggested Battery | B11: =TEXT(Customer_Profile!B18,"0.0") & " kWh" -> 6.9 kWh | C11: =TEXT(Customer_Profile!B18,"0.0") & " kWh" -> 6.9 kWh
A12: Suggested Inverter | B12: =TEXT(Customer_Profile!B19,"0.0") & " kVA" -> 2.9 kVA | C12: =TEXT(Customer_Profile!B19,"0.0") & " kVA" -> 2.9 kVA
A15: Card # | B15: Installer Name | C15: Match % | D15: Match Tier | E15: Best Suited For | F15: Coverage | G15: Strengths | H15: Pricing | I15: Response | J15: Primary CTA | K15: Secondary CTA
A16: 1 | B16: =IFERROR(INDEX(Match_Engine!$C$5:$C$104,MATCH(LARGE(Match_Engine!$O$5:$O$104,1),Match_Engine!$O$5:$O$104,0)),"") -> Lagos Hybrid Power Ltd | C16: =IF(B16="","",INDEX(Match_Engine!$O$5:$O$104,MATCH(B16,[1]Match_Engine!$C$5:$C$104,0))) -> 0.97 | D16: =IF(B16="","",INDEX(Match_Engine!$P$5:$P$104,MATCH(B16,[1]Match_Engine!$C$5:$C$104,0))) -> Excellent Match | E16: =IF(B16="","",Customer_Profile!$B$8&" projects") -> Home projects | F16: =IF(B16="","",INDEX([1]Installer_Database!$F$5:$F$104,MATCH(B16,[1]Installer_Database!$B$5:$B$104,0))) -> Lagos | G16: =IF(B16="","",INDEX(Match_Engine!$R$5:$R$104,MATCH(B16,[1]Match_Engine!$C$5:$C$104,0))) -> serves your location; experienced in your project type; good battery/hybrid capability; strong after-sales support | H16: =IF(B16="","",INDEX([1]Installer_Database!$U$5:$U$104,MATCH(B16,[1]Installer_Database!$B$5:$B$104,0))) -> Mid-range | I16: =IF(B16="","",INDEX([1]Installer_Database!$T$5:$T$104,MATCH(B16,[1]Installer_Database!$B$5:$B$104,0))) -> Same day | J16: Request Introduction | K16: Get Independent Review
A17: 2 | B17: =IFERROR(INDEX(Match_Engine!$C$5:$C$104,MATCH(LARGE(Match_Engine!$O$5:$O$104,2),Match_Engine!$O$5:$O$104,0)),"") -> Abuja SolarCare Engineering | C17: =IF(B17="","",INDEX(Match_Engine!$O$5:$O$104,MATCH(B17,[1]Match_Engine!$C$5:$C$104,0))) -> 0.93 | D17: =IF(B17="","",INDEX(Match_Engine!$P$5:$P$104,MATCH(B17,[1]Match_Engine!$C$5:$C$104,0))) -> Excellent Match | E17: =IF(B17="","",Customer_Profile!$B$8&" projects") -> Home projects | F17: =IF(B17="","",INDEX([1]Installer_Database!$F$5:$F$104,MATCH(B17,[1]Installer_Database!$B$5:$B$104,0))) -> Abuja FCT | G17: =IF(B17="","",INDEX(Match_Engine!$R$5:$R$104,MATCH(B17,[1]Match_Engine!$C$5:$C$104,0))) -> serves your location; experienced in your project type; good battery/hybrid capability; strong after-sales support | H17: =IF(B17="","",INDEX([1]Installer_Database!$U$5:$U$104,MATCH(B17,[1]Installer_Database!$B$5:$B$104,0))) -> Premium | I17: =IF(B17="","",INDEX([1]Installer_Database!$T$5:$T$104,MATCH(B17,[1]Installer_Database!$B$5:$B$104,0))) -> 24-48 hours | J17: Request Introduction | K17: Get Independent Review
A18: 3 | B18: =IFERROR(INDEX(Match_Engine!$C$5:$C$104,MATCH(LARGE(Match_Engine!$O$5:$O$104,3),Match_Engine!$O$5:$O$104,0)),"") -> Rivers Reliable Solar | C18: =IF(B18="","",INDEX(Match_Engine!$O$5:$O$104,MATCH(B18,[1]Match_Engine!$C$5:$C$104,0))) -> 0.92 | D18: =IF(B18="","",INDEX(Match_Engine!$P$5:$P$104,MATCH(B18,[1]Match_Engine!$C$5:$C$104,0))) -> Excellent Match | E18: =IF(B18="","",Customer_Profile!$B$8&" projects") -> Home projects | F18: =IF(B18="","",INDEX([1]Installer_Database!$F$5:$F$104,MATCH(B18,[1]Installer_Database!$B$5:$B$104,0))) -> Rivers; Akwa Ibom | G18: =IF(B18="","",INDEX(Match_Engine!$R$5:$R$104,MATCH(B18,[1]Match_Engine!$C$5:$C$104,0))) -> serves your location; experienced in your project type; good battery/hybrid capability; strong after-sales support | H18: =IF(B18="","",INDEX([1]Installer_Database!$U$5:$U$104,MATCH(B18,[1]Installer_Database!$B$5:$B$104,0))) -> Mid-range | I18: =IF(B18="","",INDEX([1]Installer_Database!$T$5:$T$104,MATCH(B18,[1]Installer_Database!$B$5:$B$104,0))) -> 24-48 hours | J18: Request Introduction | K18: Get Independent Review
A19: 4 | B19: =IFERROR(INDEX(Match_Engine!$C$5:$C$104,MATCH(LARGE(Match_Engine!$O$5:$O$104,4),Match_Engine!$O$5:$O$104,0)),"") -> Prime Critical Power Systems | C19: =IF(B19="","",INDEX(Match_Engine!$O$5:$O$104,MATCH(B19,[1]Match_Engine!$C$5:$C$104,0))) -> 0.8 | D19: =IF(B19="","",INDEX(Match_Engine!$P$5:$P$104,MATCH(B19,[1]Match_Engine!$C$5:$C$104,0))) -> Good Match | E19: =IF(B19="","",Customer_Profile!$B$8&" projects") -> Home projects | F19: =IF(B19="","",INDEX([1]Installer_Database!$F$5:$F$104,MATCH(B19,[1]Installer_Database!$B$5:$B$104,0))) -> Abuja FCT; Kano; Kaduna | G19: =IF(B19="","",INDEX(Match_Engine!$R$5:$R$104,MATCH(B19,[1]Match_Engine!$C$5:$C$104,0))) -> serves your location; good battery/hybrid capability; strong after-sales support | H19: =IF(B19="","",INDEX([1]Installer_Database!$U$5:$U$104,MATCH(B19,[1]Installer_Database!$B$5:$B$104,0))) -> Premium | I19: =IF(B19="","",INDEX([1]Installer_Database!$T$5:$T$104,MATCH(B19,[1]Installer_Database!$B$5:$B$104,0))) -> 24-48 hours | J19: Request Introduction | K19: Get Independent Review
A20: 5 | B20: =IFERROR(INDEX(Match_Engine!$C$5:$C$104,MATCH(LARGE(Match_Engine!$O$5:$O$104,5),Match_Engine!$O$5:$O$104,0)),"") -> Ogun Industrial Energy Works | C20: =IF(B20="","",INDEX(Match_Engine!$O$5:$O$104,MATCH(B20,[1]Match_Engine!$C$5:$C$104,0))) -> 0.73 | D20: =IF(B20="","",INDEX(Match_Engine!$P$5:$P$104,MATCH(B20,[1]Match_Engine!$C$5:$C$104,0))) -> Good Match | E20: =IF(B20="","",[1]Customer_Profile!$B$8&" projects") -> Home projects | F20: =IF(B20="","",INDEX([1]Installer_Database!$F$5:$F$104,MATCH(B20,[1]Installer_Database!$B$5:$B$104,0))) -> Ogun; Lagos | G20: =IF(B20="","",INDEX(Match_Engine!$R$5:$R$104,MATCH(B20,[1]Match_Engine!$C$5:$C$104,0))) -> serves your location; good battery/hybrid capability; strong after-sales support | H20: =IF(B20="","",INDEX([1]Installer_Database!$U$5:$U$104,MATCH(B20,[1]Installer_Database!$B$5:$B$104,0))) -> Mid-range | I20: =IF(B20="","",INDEX([1]Installer_Database!$T$5:$T$104,MATCH(B20,[1]Installer_Database!$B$5:$B$104,0))) -> 2-3 days | J20: Request Introduction | K20: Get Independent Review

Sheet Introduction_Tracker
A1: Request ID | B1: Date | C1: Customer ID | D1: Customer Name | E1: Phone | F1: Email | G1: Category | H1: Location | I1: Installer ID | J1: Installer Name | K1: Status | L1: Next Action | M1: Owner | N1: Notes
A2: INTRO-001 | K2: New
A3: INTRO-002 | K3: New
A4: INTRO-003 | K4: New
A5: INTRO-004 | K5: New
A6: INTRO-005 | K6: New
A7: INTRO-006 | K7: New
A8: INTRO-007 | K8: New
A9: INTRO-008 | K9: New
A10: INTRO-009 | K10: New
A11: INTRO-010 | K11: New
A12: INTRO-011 | K12: New
A13: INTRO-012 | K13: New
... A51: INTRO-050 | K51: New

Sheet Quote_Review_Tracker
A1: Review ID | B1: Date | C1: Customer ID | D1: Customer Name | E1: Category | F1: Location | G1: Quote Source Installer | H1: Quoted Solar kWp | I1: Quoted Battery kWh | J1: Quoted Inverter kVA | K1: Quoted Price | L1: Review Status | M1: Risk Level | N1: Recommendation | O1: Notes
A2: QR-001 | L2: New
A3: QR-002 | L3: New
A4: QR-003 | L4: New
A5: QR-004 | L5: New
A6: QR-005 | L6: New
A7: QR-006 | L7: New
A8: QR-007 | L8: New
A9: QR-008 | L9: New
A10: QR-009 | L10: New
A11: QR-010 | L11: New
A12: QR-011 | L12: New
A13: QR-012 | L13: New
... A51: QR-050 | L51: New
